Workbook

Sheet DASHBOARD
B2: VALENCIA COLOURSMILE PAINT TRADING DATABASE
B3: SELECT MONTH | C3: AUGUST
B4: SELECT YEAR | C4: 2026
B5: SELECT DAY | C5: 17
B7: TOTAL SALES | F7: TOTAL PURCHASES | J7: STOCK VALUE
B8: {=IF(C3="ALL MONTH", SUMIFS(SALES!K:K, SALES!A:A, ">="&DATE(C4, 1, 1), SALES!A:A, "<="&DATE(C4, 12, 31)), IF(C5="ALL", SUMIFS(SALES!K:K, SALES!A:A, ">="&DATE(C4, MATCH(C3, {"JANUARY","FEBRUARY","MARCH","APRIL","MAY","JUNE","JULY","AUGUST","SEPTEMBER","OCTOBER","NOVEMBER","DECEMBER"}, 0), 1), SALES!A:A, "<="&EOMONTH(DATE(C4, MATCH(C3, {"JANUARY","FEBRUARY","MARCH","APRIL","MAY","JUNE","JULY","AUGUST","SEPTEMBER","OCTOBER","NOVEMBER","DECEMBER"}, 0), 1), 0)), SUMIFS(SALES!K:K, SALES!A:A, DATE(C4, MATCH(C3, {"JANUARY","FEBRUARY","MARCH","APRIL","MAY","JUNE","JULY","AUGUST","SEPTEMBER","OCTOBER","NOVEMBER","DECEMBER"}, 0), C5))))} -> 5980 | F8: {=IF(C3="ALL MONTH", SUMIFS('STOCK IN TRANSFER'!J:J, 'STOCK IN TRANSFER'!A:A, ">="&DATE(C4, 1, 1), 'STOCK IN TRANSFER'!A:A, "<="&DATE(C4, 12, 31), 'STOCK IN TRANSFER'!F:F, "STOCK IN"), IF(C5="ALL", SUMIFS('STOCK IN TRANSFER'!J:J, 'STOCK IN TRANSFER'!A:A, ">="&DATE(C4, MATCH(C3, {"JANUARY","FEBRUARY","MARCH","APRIL","MAY","JUNE","JULY","AUGUST","SEPTEMBER","OCTOBER","NOVEMBER","DECEMBER"}, 0), 1), 'STOCK IN TRANSFER'!A:A, "<="&EOMONTH(DATE(C4, MATCH(C3, {"JANUARY","FEBRUARY","MARCH","APRIL","MAY","JUNE","JULY","AUGUST","SEPTEMBER","OCTOBER","NOVEMBER","DECEMBER"}, 0), 1), 0), 'STOCK IN TRANSFER'!F:F, "STOCK IN"), SUMIFS('STOCK IN TRANSFER'!J:J, 'STOCK IN TRANSFER'!A:A, DATE(C4, MATCH(C3, {"JANUARY","FEBRUARY","MARCH","APRIL","MAY","JUNE","JULY","AUGUST","SEPTEMBER","OCTOBER","NOVEMBER","DECEMBER"}, 0), C5), 'STOCK IN TRANSFER'!F:F, "STOCK IN")))} -> 0 | J8: =SUMPRODUCT('MASTER ITEM LIST'!C2:C18, 'MASTER ITEM LIST'!E2:E18) -> 887558.98

Sheet MASTER ITEM LIST
A1: ITEM CODE | B1: DESCRIPTION | C1: COST | D1: UNIT | E1: AVAILABLE STOCKS | F1: SRP
A2: ROS-633 | B2: RAIN OR SHINE CHOCOLATE BROWN 4L | C2: 665 | D2: GALON | E2: =SUMIFS('STOCK IN TRANSFER'!G:G, 'STOCK IN TRANSFER'!E:E, B2, 'STOCK IN TRANSFER'!F:F, "STOCK IN") + SUMIFS('STOCK IN TRANSFER'!G:G, 'STOCK IN TRANSFER'!E:E, B2, 'STOCK IN TRANSFER'!F:F, "ADJUSTMENT (+)") - SUMIFS('STOCK IN TRANSFER'!G:G, 'STOCK IN TRANSFER'!E:E, B2, 'STOCK IN TRANSFER'!F:F, "ADJUSTMENT (-)") - SUMIFS('STOCK IN TRANSFER'!G:G, 'STOCK IN TRANSFER'!E:E, B2, 'STOCK IN TRANSFER'!F:F, "STOCK TRANSFER") - SUMIFS(SALES!H:H, SALES!E:E, B2) -> 0
A3: ROSCB-1L | B3: RAIN OR SHINE CHOCOLATE BROWN 1L | C3: 0 | D3: LITER | E3: =SUMIFS('STOCK IN TRANSFER'!G:G, 'STOCK IN TRANSFER'!E:E, B3, 'STOCK IN TRANSFER'!F:F, "STOCK IN") + SUMIFS('STOCK IN TRANSFER'!G:G, 'STOCK IN TRANSFER'!E:E, B3, 'STOCK IN TRANSFER'!F:F, "ADJUSTMENT (+)") - SUMIFS('STOCK IN TRANSFER'!G:G, 'STOCK IN TRANSFER'!E:E, B3, 'STOCK IN TRANSFER'!F:F, "ADJUSTMENT (-)") - SUMIFS('STOCK IN TRANSFER'!G:G, 'STOCK IN TRANSFER'!E:E, B3, 'STOCK IN TRANSFER'!F:F, "STOCK TRANSFER") - SUMIFS(SALES!H:H, SALES!E:E, B3) -> 0
A4: ROS-701 | B4: RAIN OR SHINE BAGUIO GREEN 4L | C4: 665 | D4: GALON | E4: =SUMIFS('STOCK IN TRANSFER'!G:G, 'STOCK IN TRANSFER'!E:E, B4, 'STOCK IN TRANSFER'!F:F, "STOCK IN") + SUMIFS('STOCK IN TRANSFER'!G:G, 'STOCK IN TRANSFER'!E:E, B4, 'STOCK IN TRANSFER'!F:F, "ADJUSTMENT (+)") - SUMIFS('STOCK IN TRANSFER'!G:G, 'STOCK IN TRANSFER'!E:E, B4, 'STOCK IN TRANSFER'!F:F, "ADJUSTMENT (-)") - SUMIFS('STOCK IN TRANSFER'!G:G, 'STOCK IN TRANSFER'!E:E, B4, 'STOCK IN TRANSFER'!F:F, "STOCK TRANSFER") - SUMIFS(SALES!H:H, SALES!E:E, B4) -> 0
A5: POLYGTHIN-4L | B5: POLYGLOSS URETHANE THINNER 4L | C5: 675 | D5: GALON | E5: =SUMIFS('STOCK IN TRANSFER'!G:G, 'STOCK IN TRANSFER'!E:E, B5, 'STOCK IN TRANSFER'!F:F, "STOCK IN") + SUMIFS('STOCK IN TRANSFER'!G:G, 'STOCK IN TRANSFER'!E:E, B5, 'STOCK IN TRANSFER'!F:F, "ADJUSTMENT (+)") - SUMIFS('STOCK IN TRANSFER'!G:G, 'STOCK IN TRANSFER'!E:E, B5, 'STOCK IN TRANSFER'!F:F, "ADJUSTMENT (-)") - SUMIFS('STOCK IN TRANSFER'!G:G, 'STOCK IN TRANSFER'!E:E, B5, 'STOCK IN TRANSFER'!F:F, "STOCK TRANSFER") - SUMIFS(SALES!H:H, SALES!E:E, B5) -> 0
A6: PGTB-4L | B6: POLYGLOSS PU PHTHALO BLUE 4L | C6: 1883 | D6: GALON | E6: =SUMIFS('STOCK IN TRANSFER'!G:G, 'STOCK IN TRANSFER'!E:E, B6, 'STOCK IN TRANSFER'!F:F, "STOCK IN") + SUMIFS('STOCK IN TRANSFER'!G:G, 'STOCK IN TRANSFER'!E:E, B6, 'STOCK IN TRANSFER'!F:F, "ADJUSTMENT (+)") - SUMIFS('STOCK IN TRANSFER'!G:G, 'STOCK IN TRANSFER'!E:E, B6, 'STOCK IN TRANSFER'!F:F, "ADJUSTMENT (-)") - SUMIFS('STOCK IN TRANSFER'!G:G, 'STOCK IN TRANSFER'!E:E, B6, 'STOCK IN TRANSFER'!F:F, "STOCK TRANSFER") - SUMIFS(SALES!H:H, SALES!E:E, B6) -> 0
A7: PGMF-4L | B7: POLYGLOSS PU MICA RED FINE 4L | C7: 2822 | D7: GALON | E7: =SUMIFS('STOCK IN TRANSFER'!G:G, 'STOCK IN TRANSFER'!E:E, B7, 'STOCK IN TRANSFER'!F:F, "STOCK IN") + SUMIFS('STOCK IN TRANSFER'!G:G, 'STOCK IN TRANSFER'!E:E, B7, 'STOCK IN TRANSFER'!F:F, "ADJUSTMENT (+)") - SUMIFS('STOCK IN TRANSFER'!G:G, 'STOCK IN TRANSFER'!E:E, B7, 'STOCK IN TRANSFER'!F:F, "ADJUSTMENT (-)") - SUMIFS('STOCK IN TRANSFER'!G:G, 'STOCK IN TRANSFER'!E:E, B7, 'STOCK IN TRANSFER'!F:F, "STOCK TRANSFER") - SUMIFS(SALES!H:H, SALES!E:E, B7) -> 0
A8: PGMC-4L | B8: POLYGLOSS PU METALLIC COARSE 4L | C8: 1743 | D8: GALON | E8: =SUMIFS('STOCK IN TRANSFER'!G:G, 'STOCK IN TRANSFER'!E:E, B8, 'STOCK IN TRANSFER'!F:F, "STOCK IN") + SUMIFS('STOCK IN TRANSFER'!G:G, 'STOCK IN TRANSFER'!E:E, B8, 'STOCK IN TRANSFER'!F:F, "ADJUSTMENT (+)") - SUMIFS('STOCK IN TRANSFER'!G:G, 'STOCK IN TRANSFER'!E:E, B8, 'STOCK IN TRANSFER'!F:F, "ADJUSTMENT (-)") - SUMIFS('STOCK IN TRANSFER'!G:G, 'STOCK IN TRANSFER'!E:E, B8, 'STOCK IN TRANSFER'!F:F, "STOCK TRANSFER") - SUMIFS(SALES!H:H, SALES!E:E, B8) -> 0
A9: PGJB-4L | B9: POLYGLOSS PU JET BLACK 4L | C9: 1828 | D9: GALON | E9: =SUMIFS('STOCK IN TRANSFER'!G:G, 'STOCK IN TRANSFER'!E:E, B9, 'STOCK IN TRANSFER'!F:F, "STOCK IN") + SUMIFS('STOCK IN TRANSFER'!G:G, 'STOCK IN TRANSFER'!E:E, B9, 'STOCK IN TRANSFER'!F:F, "ADJUSTMENT (+)") - SUMIFS('STOCK IN TRANSFER'!G:G, 'STOCK IN TRANSFER'!E:E, B9, 'STOCK IN TRANSFER'!F:F, "ADJUSTMENT (-)") - SUMIFS('STOCK IN TRANSFER'!G:G, 'STOCK IN TRANSFER'!E:E, B9, 'STOCK IN TRANSFER'!F:F, "STOCK TRANSFER") - SUMIFS(SALES!H:H, SALES!E:E, B9) -> 0
A10: PGFB-4L | B10: POLYGLOSS PU FLAT BLACK 4L | C10: 1930 | D10: GALON | E10: =SUMIFS('STOCK IN TRANSFER'!G:G, 'STOCK IN TRANSFER'!E:E, B10, 'STOCK IN TRANSFER'!F:F, "STOCK IN") + SUMIFS('STOCK IN TRANSFER'!G:G, 'STOCK IN TRANSFER'!E:E, B10, 'STOCK IN TRANSFER'!F:F, "ADJUSTMENT (+)") - SUMIFS('STOCK IN TRANSFER'!G:G, 'STOCK IN TRANSFER'!E:E, B10, 'STOCK IN TRANSFER'!F:F, "ADJUSTMENT (-)") - SUMIFS('STOCK IN TRANSFER'!G:G, 'STOCK IN TRANSFER'!E:E, B10, 'STOCK IN TRANSFER'!F:F, "STOCK TRANSFER") - SUMIFS(SALES!H:H, SALES!E:E, B10) -> 0
A11: PGANTI-C-1L | B11: POLYGLOSS ANTI-CORROSSION | C11: 440 | D11: LITER | E11: =SUMIFS('STOCK IN TRANSFER'!G:G, 'STOCK IN TRANSFER'!E:E, B11, 'STOCK IN TRANSFER'!F:F, "STOCK IN") + SUMIFS('STOCK IN TRANSFER'!G:G, 'STOCK IN TRANSFER'!E:E, B11, 'STOCK IN TRANSFER'!F:F, "ADJUSTMENT (+)") - SUMIFS('STOCK IN TRANSFER'!G:G, 'STOCK IN TRANSFER'!E:E, B11, 'STOCK IN TRANSFER'!F:F, "ADJUSTMENT (-)") - SUMIFS('STOCK IN TRANSFER'!G:G, 'STOCK IN TRANSFER'!E:E, B11, 'STOCK IN TRANSFER'!F:F, "STOCK TRANSFER") - SUMIFS(SALES!H:H, SALES!E:E, B11) -> 3
A12: PLQDW-4L | B12: PLATONE QDE WHITE 4L | C12: 650 | D12: GAL | E12: =SUMIFS('STOCK IN TRANSFER'!G:G, 'STOCK IN TRANSFER'!E:E, B12, 'STOCK IN TRANSFER'!F:F, "STOCK IN") + SUMIFS('STOCK IN TRANSFER'!G:G, 'STOCK IN TRANSFER'!E:E, B12, 'STOCK IN TRANSFER'!F:F, "ADJUSTMENT (+)") - SUMIFS('STOCK IN TRANSFER'!G:G, 'STOCK IN TRANSFER'!E:E, B12, 'STOCK IN TRANSFER'!F:F, "ADJUSTMENT (-)") - SUMIFS('STOCK IN TRANSFER'!G:G, 'STOCK IN TRANSFER'!E:E, B12, 'STOCK IN TRANSFER'!F:F, "STOCK TRANSFER") - SUMIFS(SALES!H:H, SALES!E:E, B12) -> 0
A13: PLQDB-1L | B13: PLATONE QDE BLACK 1L | C13: 0 | D13: LITER | E13: =SUMIFS('STOCK IN TRANSFER'!G:G, 'STOCK IN TRANSFER'!E:E, B13, 'STOCK IN TRANSFER'!F:F, "STOCK IN") + SUMIFS('STOCK IN TRANSFER'!G:G, 'STOCK IN TRANSFER'!E:E, B13, 'STOCK IN TRANSFER'!F:F, "ADJUSTMENT (+)") - SUMIFS('STOCK IN TRANSFER'!G:G, 'STOCK IN TRANSFER'!E:E, B13, 'STOCK IN TRANSFER'!F:F, "ADJUSTMENT (-)") - SUMIFS('STOCK IN TRANSFER'!G:G, 'STOCK IN TRANSFER'!E:E, B13, 'STOCK IN TRANSFER'!F:F, "STOCK TRANSFER") - SUMIFS(SALES!H:H, SALES!E:E, B13) -> 0
... A80: QSHG710-5L | B80: Q-SHIELD EXTRA HG-710 GLOSS WHITE 5L | C80: 851 | D80: GAL | E80: =SUMIFS('STOCK IN TRANSFER'!G:G, 'STOCK IN TRANSFER'!E:E, B80, 'STOCK IN TRANSFER'!F:F, "STOCK IN") + SUMIFS('STOCK IN TRANSFER'!G:G, 'STOCK IN TRANSFER'!E:E, B80, 'STOCK IN TRANSFER'!F:F, "ADJUSTMENT (+)") - SUMIFS('STOCK IN TRANSFER'!G:G, 'STOCK IN TRANSFER'!E:E, B80, 'STOCK IN TRANSFER'!F:F, "ADJUSTMENT (-)") - SUMIFS('STOCK IN TRANSFER'!G:G, 'STOCK IN TRANSFER'!E:E, B80, 'STOCK IN TRANSFER'!F:F, "STOCK TRANSFER") - SUMIFS(SALES!H:H, SALES!E:E, B80) -> 12
A81: QSHG710-1L | B81: Q-SHIELD EXTRA HG-710 GLOSS WHITE 1L | D81: LITER | E81: =SUMIFS('STOCK IN TRANSFER'!G:G, 'STOCK IN TRANSFER'!E:E, B81, 'STOCK IN TRANSFER'!F:F, "STOCK IN") + SUMIFS('STOCK IN TRANSFER'!G:G, 'STOCK IN TRANSFER'!E:E, B81, 'STOCK IN TRANSFER'!F:F, "ADJUSTMENT (+)") - SUMIFS('STOCK IN TRANSFER'!G:G, 'STOCK IN TRANSFER'!E:E, B81, 'STOCK IN TRANSFER'!F:F, "ADJUSTMENT (-)") - SUMIFS('STOCK IN TRANSFER'!G:G, 'STOCK IN TRANSFER'!E:E, B81, 'STOCK IN TRANSFER'!F:F, "STOCK TRANSFER") - SUMIFS(SALES!H:H, SALES!E:E, B81) -> 0
A82: QSHG710-15L | B82: Q-SHIELD EXTRA HG-710 GLOSS WHITE 15L | C82: 2442 | D82: PAIL | E82: =SUMIFS('STOCK IN TRANSFER'!G:G, 'STOCK IN TRANSFER'!E:E, B82, 'STOCK IN TRANSFER'!F:F, "STOCK IN") + SUMIFS('STOCK IN TRANSFER'!G:G, 'STOCK IN TRANSFER'!E:E, B82, 'STOCK IN TRANSFER'!F:F, "ADJUSTMENT (+)") - SUMIFS('STOCK IN TRANSFER'!G:G, 'STOCK IN TRANSFER'!E:E, B82, 'STOCK IN TRANSFER'!F:F, "ADJUSTMENT (-)") - SUMIFS('STOCK IN TRANSFER'!G:G, 'STOCK IN TRANSFER'!E:E, B82, 'STOCK IN TRANSFER'!F:F, "STOCK TRANSFER") - SUMIFS(SALES!H:H, SALES!E:E, B82) -> 4
A83: PYLZWH-02 | B83: PYLOX LAZER WHITE 02 | C83: 95 | D83: CAN | E83: =SUMIFS('STOCK IN TRANSFER'!G:G, 'STOCK IN TRANSFER'!E:E, B83, 'STOCK IN TRANSFER'!F:F, "STOCK IN") + SUMIFS('STOCK IN TRANSFER'!G:G, 'STOCK IN TRANSFER'!E:E, B83, 'STOCK IN TRANSFER'!F:F, "ADJUSTMENT (+)") - SUMIFS('STOCK IN TRANSFER'!G:G, 'STOCK IN TRANSFER'!E:E, B83, 'STOCK IN TRANSFER'!F:F, "ADJUSTMENT (-)") - SUMIFS('STOCK IN TRANSFER'!G:G, 'STOCK IN TRANSFER'!E:E, B83, 'STOCK IN TRANSFER'!F:F, "STOCK TRANSFER") - SUMIFS(SALES!H:H, SALES!E:E, B83) -> -1
A84: PLYZVIO-20 | B84: PYLOX LAZER VIOLET 20 | C84: 95 | D84: CAN | E84: =SUMIFS('STOCK IN TRANSFER'!G:G, 'STOCK IN TRANSFER'!E:E, B84, 'STOCK IN TRANSFER'!F:F, "STOCK IN") + SUMIFS('STOCK IN TRANSFER'!G:G, 'STOCK IN TRANSFER'!E:E, B84, 'STOCK IN TRANSFER'!F:F, "ADJUSTMENT (+)") - SUMIFS('STOCK IN TRANSFER'!G:G, 'STOCK IN TRANSFER'!E:E, B84, 'STOCK IN TRANSFER'!F:F, "ADJUSTMENT (-)") - SUMIFS('STOCK IN TRANSFER'!G:G, 'STOCK IN TRANSFER'!E:E, B84, 'STOCK IN TRANSFER'!F:F, "STOCK TRANSFER") - SUMIFS(SALES!H:H, SALES!E:E, B84) -> 10
A85: PLYZSKBL-22 | B85: PYLOX LAZER SKY BLUE 22 | C85: 95 | D85: CAN | E85: =SUMIFS('STOCK IN TRANSFER'!G:G, 'STOCK IN TRANSFER'!E:E, B85, 'STOCK IN TRANSFER'!F:F, "STOCK IN") + SUMIFS('STOCK IN TRANSFER'!G:G, 'STOCK IN TRANSFER'!E:E, B85, 'STOCK IN TRANSFER'!F:F, "ADJUSTMENT (+)") - SUMIFS('STOCK IN TRANSFER'!G:G, 'STOCK IN TRANSFER'!E:E, B85, 'STOCK IN TRANSFER'!F:F, "ADJUSTMENT (-)") - SUMIFS('STOCK IN TRANSFER'!G:G, 'STOCK IN TRANSFER'!E:E, B85, 'STOCK IN TRANSFER'!F:F, "STOCK TRANSFER") - SUMIFS(SALES!H:H, SALES!E:E, B85) -> 4
A86: PLYZSIL-42 | B86: PYLOX LAZER SILVER 42 | C86: 95 | D86: CAN | E86: =SUMIFS('STOCK IN TRANSFER'!G:G, 'STOCK IN TRANSFER'!E:E, B86, 'STOCK IN TRANSFER'!F:F, "STOCK IN") + SUMIFS('STOCK IN TRANSFER'!G:G, 'STOCK IN TRANSFER'!E:E, B86, 'STOCK IN TRANSFER'!F:F, "ADJUSTMENT (+)") - SUMIFS('STOCK IN TRANSFER'!G:G, 'STOCK IN TRANSFER'!E:E, B86, 'STOCK IN TRANSFER'!F:F, "ADJUSTMENT (-)") - SUMIFS('STOCK IN TRANSFER'!G:G, 'STOCK IN TRANSFER'!E:E, B86, 'STOCK IN TRANSFER'!F:F, "STOCK TRANSFER") - SUMIFS(SALES!H:H, SALES!E:E, B86) -> 2
A87: PLYZPRGR-145 | B87: PYLOX LAZER PRIMER GRAY 145 | C87: 95 | D87: CAN | E87: =SUMIFS('STOCK IN TRANSFER'!G:G, 'STOCK IN TRANSFER'!E:E, B87, 'STOCK IN TRANSFER'!F:F, "STOCK IN") + SUMIFS('STOCK IN TRANSFER'!G:G, 'STOCK IN TRANSFER'!E:E, B87, 'STOCK IN TRANSFER'!F:F, "ADJUSTMENT (+)") - SUMIFS('STOCK IN TRANSFER'!G:G, 'STOCK IN TRANSFER'!E:E, B87, 'STOCK IN TRANSFER'!F:F, "ADJUSTMENT (-)") - SUMIFS('STOCK IN TRANSFER'!G:G, 'STOCK IN TRANSFER'!E:E, B87, 'STOCK IN TRANSFER'!F:F, "STOCK TRANSFER") - SUMIFS(SALES!H:H, SALES!E:E, B87) -> 1
A88: PLYZMTW-03 | B88: PYLOX LAZER MATT WHITE 03 | C88: 95 | D88: CAN | E88: =SUMIFS('STOCK IN TRANSFER'!G:G, 'STOCK IN TRANSFER'!E:E, B88, 'STOCK IN TRANSFER'!F:F, "STOCK IN") + SUMIFS('STOCK IN TRANSFER'!G:G, 'STOCK IN TRANSFER'!E:E, B88, 'STOCK IN TRANSFER'!F:F, "ADJUSTMENT (+)") - SUMIFS('STOCK IN TRANSFER'!G:G, 'STOCK IN TRANSFER'!E:E, B88, 'STOCK IN TRANSFER'!F:F, "ADJUSTMENT (-)") - SUMIFS('STOCK IN TRANSFER'!G:G, 'STOCK IN TRANSFER'!E:E, B88, 'STOCK IN TRANSFER'!F:F, "STOCK TRANSFER") - SUMIFS(SALES!H:H, SALES!E:E, B88) -> -7
A89: PLYZLTGR-33 | B89: PYLOX LAZER LIGHT GREEN 33 | C89: 95 | D89: CAN | E89: =SUMIFS('STOCK IN TRANSFER'!G:G, 'STOCK IN TRANSFER'!E:E, B89, 'STOCK IN TRANSFER'!F:F, "STOCK IN") + SUMIFS('STOCK IN TRANSFER'!G:G, 'STOCK IN TRANSFER'!E:E, B89, 'STOCK IN TRANSFER'!F:F, "ADJUSTMENT (+)") - SUMIFS('STOCK IN TRANSFER'!G:G, 'STOCK IN TRANSFER'!E:E, B89, 'STOCK IN TRANSFER'!F:F, "ADJUSTMENT (-)") - SUMIFS('STOCK IN TRANSFER'!G:G, 'STOCK IN TRANSFER'!E:E, B89, 'STOCK IN TRANSFER'!F:F, "STOCK TRANSFER") - SUMIFS(SALES!H:H, SALES!E:E, B89) -> 4
A90: PLYZHTRSIL-709 | B90: PYLOX LAZER HEAT RESISTANT SILVER 709 | C90: 162 | D90: CAN | E90: =SUMIFS('STOCK IN TRANSFER'!G:G, 'STOCK IN TRANSFER'!E:E, B90, 'STOCK IN TRANSFER'!F:F, "STOCK IN") + SUMIFS('STOCK IN TRANSFER'!G:G, 'STOCK IN TRANSFER'!E:E, B90, 'STOCK IN TRANSFER'!F:F, "ADJUSTMENT (+)") - SUMIFS('STOCK IN TRANSFER'!G:G, 'STOCK IN TRANSFER'!E:E, B90, 'STOCK IN TRANSFER'!F:F, "ADJUSTMENT (-)") - SUMIFS('STOCK IN TRANSFER'!G:G, 'STOCK IN TRANSFER'!E:E, B90, 'STOCK IN TRANSFER'!F:F, "STOCK TRANSFER") - SUMIFS(SALES!H:H, SALES!E:E, B90) -> 4
A91: PLYZGLD-705 | B91: PYLOX LAZER GOLD 705 | C91: 117 | D91: CAN | E91: =SUMIFS('STOCK IN TRANSFER'!G:G, 'STOCK IN TRANSFER'!E:E, B91, 'STOCK IN TRANSFER'!F:F, "STOCK IN") + SUMIFS('STOCK IN TRANSFER'!G:G, 'STOCK IN TRANSFER'!E:E, B91, 'STOCK IN TRANSFER'!F:F, "ADJUSTMENT (+)") - SUMIFS('STOCK IN TRANSFER'!G:G, 'STOCK IN TRANSFER'!E:E, B91, 'STOCK IN TRANSFER'!F:F, "ADJUSTMENT (-)") - SUMIFS('STOCK IN TRANSFER'!G:G, 'STOCK IN TRANSFER'!E:E, B91, 'STOCK IN TRANSFER'!F:F, "STOCK TRANSFER") - SUMIFS(SALES!H:H, SALES!E:E, B91) -> 1
A92: PLYZGBLK-48 | B92: PYLOX LAZER GLOSS BLACK 48 | C92: 95 | D92: CAN | E92: =SUMIFS('STOCK IN TRANSFER'!G:G, 'STOCK IN TRANSFER'!E:E, B92, 'STOCK IN TRANSFER'!F:F, "STOCK IN") + SUMIFS('STOCK IN TRANSFER'!G:G, 'STOCK IN TRANSFER'!E:E, B92, 'STOCK IN TRANSFER'!F:F, "ADJUSTMENT (+)") - SUMIFS('STOCK IN TRANSFER'!G:G, 'STOCK IN TRANSFER'!E:E, B92, 'STOCK IN TRANSFER'!F:F, "ADJUSTMENT (-)") - SUMIFS('STOCK IN TRANSFER'!G:G, 'STOCK IN TRANSFER'!E:E, B92, 'STOCK IN TRANSFER'!F:F, "STOCK TRANSFER") - SUMIFS(SALES!H:H, SALES!E:E, B92) -> 3
A93: PLYZFLOUVIO-604 | B93: PYLOX LAZER FLOURESCENT VIOLET 604 | C93: 135 | D93: CAN | E93: =SUMIFS('STOCK IN TRANSFER'!G:G, 'STOCK IN TRANSFER'!E:E, B93, 'STOCK IN TRANSFER'!F:F, "STOCK IN") + SUMIFS('STOCK IN TRANSFER'!G:G, 'STOCK IN TRANSFER'!E:E, B93, 'STOCK IN TRANSFER'!F:F, "ADJUSTMENT (+)") - SUMIFS('STOCK IN TRANSFER'!G:G, 'STOCK IN TRANSFER'!E:E, B93, 'STOCK IN TRANSFER'!F:F, "ADJUSTMENT (-)") - SUMIFS('STOCK IN TRANSFER'!G:G, 'STOCK IN TRANSFER'!E:E, B93, 'STOCK IN TRANSFER'!F:F, "STOCK TRANSFER") - SUMIFS(SALES!H:H, SALES!E:E, B93) -> 8
... A116: PLQDEY-4L | B116: PLATONE QDE YELLOW 4L | C116: 836 | D116: GAL | E116: =SUMIFS('STOCK IN TRANSFER'!G:G, 'STOCK IN TRANSFER'!E:E, B116, 'STOCK IN TRANSFER'!F:F, "STOCK IN") + SUMIFS('STOCK IN TRANSFER'!G:G, 'STOCK IN TRANSFER'!E:E, B116, 'STOCK IN TRANSFER'!F:F, "ADJUSTMENT (+)") - SUMIFS('STOCK IN TRANSFER'!G:G, 'STOCK IN TRANSFER'!E:E, B116, 'STOCK IN TRANSFER'!F:F, "ADJUSTMENT (-)") - SUMIFS('STOCK IN TRANSFER'!G:G, 'STOCK IN TRANSFER'!E:E, B116, 'STOCK IN TRANSFER'!F:F, "STOCK TRANSFER") - SUMIFS(SALES!H:H, SALES!E:E, B116) -> 0
A117: PLQDW-1L | B117: PLATONE QDE WHITE 1L | D117: LITER | E117: =SUMIFS('STOCK IN TRANSFER'!G:G, 'STOCK IN TRANSFER'!E:E, B117, 'STOCK IN TRANSFER'!F:F, "STOCK IN") + SUMIFS('STOCK IN TRANSFER'!G:G, 'STOCK IN TRANSFER'!E:E, B117, 'STOCK IN TRANSFER'!F:F, "ADJUSTMENT (+)") - SUMIFS('STOCK IN TRANSFER'!G:G, 'STOCK IN TRANSFER'!E:E, B117, 'STOCK IN TRANSFER'!F:F, "ADJUSTMENT (-)") - SUMIFS('STOCK IN TRANSFER'!G:G, 'STOCK IN TRANSFER'!E:E, B117, 'STOCK IN TRANSFER'!F:F, "STOCK TRANSFER") - SUMIFS(SALES!H:H, SALES!E:E, B117) -> 0
A118: PLQDRB-4L | B118: PLATONE QDE ROYAL BLUE 4L | C118: 698 | D118: GAL | E118: =SUMIFS('STOCK IN TRANSFER'!G:G, 'STOCK IN TRANSFER'!E:E, B118, 'STOCK IN TRANSFER'!F:F, "STOCK IN") + SUMIFS('STOCK IN TRANSFER'!G:G, 'STOCK IN TRANSFER'!E:E, B118, 'STOCK IN TRANSFER'!F:F, "ADJUSTMENT (+)") - SUMIFS('STOCK IN TRANSFER'!G:G, 'STOCK IN TRANSFER'!E:E, B118, 'STOCK IN TRANSFER'!F:F, "ADJUSTMENT (-)") - SUMIFS('STOCK IN TRANSFER'!G:G, 'STOCK IN TRANSFER'!E:E, B118, 'STOCK IN TRANSFER'!F:F, "STOCK TRANSFER") - SUMIFS(SALES!H:H, SALES!E:E, B118) -> 0
A119: PLQDLY-4L | B119: PLATONE QDE LEMON YELLOW 4L | C119: 836 | D119: GAL | E119: =SUMIFS('STOCK IN TRANSFER'!G:G, 'STOCK IN TRANSFER'!E:E, B119, 'STOCK IN TRANSFER'!F:F, "STOCK IN") + SUMIFS('STOCK IN TRANSFER'!G:G, 'STOCK IN TRANSFER'!E:E, B119, 'STOCK IN TRANSFER'!F:F, "ADJUSTMENT (+)") - SUMIFS('STOCK IN TRANSFER'!G:G, 'STOCK IN TRANSFER'!E:E, B119, 'STOCK IN TRANSFER'!F:F, "ADJUSTMENT (-)") - SUMIFS('STOCK IN TRANSFER'!G:G, 'STOCK IN TRANSFER'!E:E, B119, 'STOCK IN TRANSFER'!F:F, "STOCK TRANSFER") - SUMIFS(SALES!H:H, SALES!E:E, B119) -> 0
A120: PLQDJG-4L | B120: PLATONE QDE JADE GREEN 4L | C120: 732 | D120: GAL | E120: =SUMIFS('STOCK IN TRANSFER'!G:G, 'STOCK IN TRANSFER'!E:E, B120, 'STOCK IN TRANSFER'!F:F, "STOCK IN") + SUMIFS('STOCK IN TRANSFER'!G:G, 'STOCK IN TRANSFER'!E:E, B120, 'STOCK IN TRANSFER'!F:F, "ADJUSTMENT (+)") - SUMIFS('STOCK IN TRANSFER'!G:G, 'STOCK IN TRANSFER'!E:E, B120, 'STOCK IN TRANSFER'!F:F, "ADJUSTMENT (-)") - SUMIFS('STOCK IN TRANSFER'!G:G, 'STOCK IN TRANSFER'!E:E, B120, 'STOCK IN TRANSFER'!F:F, "STOCK TRANSFER") - SUMIFS(SALES!H:H, SALES!E:E, B120) -> 1
A121: PLQDIR-4L | B121: PLATONE QDE INTERNATIONAL RED 4L | C121: 773 | D121: GAL | E121: =SUMIFS('STOCK IN TRANSFER'!G:G, 'STOCK IN TRANSFER'!E:E, B121, 'STOCK IN TRANSFER'!F:F, "STOCK IN") + SUMIFS('STOCK IN TRANSFER'!G:G, 'STOCK IN TRANSFER'!E:E, B121, 'STOCK IN TRANSFER'!F:F, "ADJUSTMENT (+)") - SUMIFS('STOCK IN TRANSFER'!G:G, 'STOCK IN TRANSFER'!E:E, B121, 'STOCK IN TRANSFER'!F:F, "ADJUSTMENT (-)") - SUMIFS('STOCK IN TRANSFER'!G:G, 'STOCK IN TRANSFER'!E:E, B121, 'STOCK IN TRANSFER'!F:F, "STOCK TRANSFER") - SUMIFS(SALES!H:H, SALES!E:E, B121) -> 3
A122: PLQDG-4L | B122: PLATONE QDE GREEN 4L | C122: 1593 | D122: GALON | E122: =SUMIFS('STOCK IN TRANSFER'!G:G, 'STOCK IN TRANSFER'!E:E, B122, 'STOCK IN TRANSFER'!F:F, "STOCK IN") + SUMIFS('STOCK IN TRANSFER'!G:G, 'STOCK IN TRANSFER'!E:E, B122, 'STOCK IN TRANSFER'!F:F, "ADJUSTMENT (+)") - SUMIFS('STOCK IN TRANSFER'!G:G, 'STOCK IN TRANSFER'!E:E, B122, 'STOCK IN TRANSFER'!F:F, "ADJUSTMENT (-)") - SUMIFS('STOCK IN TRANSFER'!G:G, 'STOCK IN TRANSFER'!E:E, B122, 'STOCK IN TRANSFER'!F:F, "STOCK TRANSFER") - SUMIFS(SALES!H:H, SALES!E:E, B122) -> 1
A123: PLQDCB-4L | B123: PLATONE QDE CHOCOLATE BROWN 4L | C123: 668 | D123: GAL | E123: =SUMIFS('STOCK IN TRANSFER'!G:G, 'STOCK IN TRANSFER'!E:E, B123, 'STOCK IN TRANSFER'!F:F, "STOCK IN") + SUMIFS('STOCK IN TRANSFER'!G:G, 'STOCK IN TRANSFER'!E:E, B123, 'STOCK IN TRANSFER'!F:F, "ADJUSTMENT (+)") - SUMIFS('STOCK IN TRANSFER'!G:G, 'STOCK IN TRANSFER'!E:E, B123, 'STOCK IN TRANSFER'!F:F, "ADJUSTMENT (-)") - SUMIFS('STOCK IN TRANSFER'!G:G, 'STOCK IN TRANSFER'!E:E, B123, 'STOCK IN TRANSFER'!F:F, "STOCK TRANSFER") - SUMIFS(SALES!H:H, SALES!E:E, B123) -> 2
A124: PLQDB-4L | B124: PLATONE QDE BLACK 4L | C124: 661 | D124: GAL | E124: =SUMIFS('STOCK IN TRANSFER'!G:G, 'STOCK IN TRANSFER'!E:E, B124, 'STOCK IN TRANSFER'!F:F, "STOCK IN") + SUMIFS('STOCK IN TRANSFER'!G:G, 'STOCK IN TRANSFER'!E:E, B124, 'STOCK IN TRANSFER'!F:F, "ADJUSTMENT (+)") - SUMIFS('STOCK IN TRANSFER'!G:G, 'STOCK IN TRANSFER'!E:E, B124, 'STOCK IN TRANSFER'!F:F, "ADJUSTMENT (-)") - SUMIFS('STOCK IN TRANSFER'!G:G, 'STOCK IN TRANSFER'!E:E, B124, 'STOCK IN TRANSFER'!F:F, "STOCK TRANSFER") - SUMIFS(SALES!H:H, SALES!E:E, B124) -> 2
A125: BOTTLE | B125: PLASTIC EMPTY BOTTLE | C125: 6.25 | D125: PC/S | E125: =SUMIFS('STOCK IN TRANSFER'!G:G, 'STOCK IN TRANSFER'!E:E, B125, 'STOCK IN TRANSFER'!F:F, "STOCK IN") + SUMIFS('STOCK IN TRANSFER'!G:G, 'STOCK IN TRANSFER'!E:E, B125, 'STOCK IN TRANSFER'!F:F, "ADJUSTMENT (+)") - SUMIFS('STOCK IN TRANSFER'!G:G, 'STOCK IN TRANSFER'!E:E, B125, 'STOCK IN TRANSFER'!F:F, "ADJUSTMENT (-)") - SUMIFS('STOCK IN TRANSFER'!G:G, 'STOCK IN TRANSFER'!E:E, B125, 'STOCK IN TRANSFER'!F:F, "STOCK TRANSFER") - SUMIFS(SALES!H:H, SALES!E:E, B125) -> 0
A126: ROS-238 | B126: PISTACHIO ELASTOMERIC WATER FROOFING PAINT ROS-238 RAIN OR SHINE 4L | C126: 681.4 | D126: 4L | E126: =SUMIFS('STOCK IN TRANSFER'!G:G, 'STOCK IN TRANSFER'!E:E, B126, 'STOCK IN TRANSFER'!F:F, "STOCK IN") + SUMIFS('STOCK IN TRANSFER'!G:G, 'STOCK IN TRANSFER'!E:E, B126, 'STOCK IN TRANSFER'!F:F, "ADJUSTMENT (+)") - SUMIFS('STOCK IN TRANSFER'!G:G, 'STOCK IN TRANSFER'!E:E, B126, 'STOCK IN TRANSFER'!F:F, "ADJUSTMENT (-)") - SUMIFS('STOCK IN TRANSFER'!G:G, 'STOCK IN TRANSFER'!E:E, B126, 'STOCK IN TRANSFER'!F:F, "STOCK TRANSFER") - SUMIFS(SALES!H:H, SALES!E:E, B126) -> 1
A127: PINEPETHBLUE-4L | B127: PINACLE EPOXY ENAMEL THALO BLUE 4L | C127: 1160 | D127: GALON | E127: =SUMIFS('STOCK IN TRANSFER'!G:G, 'STOCK IN TRANSFER'!E:E, B127, 'STOCK IN TRANSFER'!F:F, "STOCK IN") + SUMIFS('STOCK IN TRANSFER'!G:G, 'STOCK IN TRANSFER'!E:E, B127, 'STOCK IN TRANSFER'!F:F, "ADJUSTMENT (+)") - SUMIFS('STOCK IN TRANSFER'!G:G, 'STOCK IN TRANSFER'!E:E, B127, 'STOCK IN TRANSFER'!F:F, "ADJUSTMENT (-)") - SUMIFS('STOCK IN TRANSFER'!G:G, 'STOCK IN TRANSFER'!E:E, B127, 'STOCK IN TRANSFER'!F:F, "STOCK TRANSFER") - SUMIFS(SALES!H:H, SALES!E:E, B127) -> 0
A128: PWTCO-9033 | B128: PHTHALO GREEN TINTING COLOR PWTCO-9033 1/4L PREMIUM WELCOAT | C128: 80.5933 | D128: 1/4L | E128: =SUMIFS('STOCK IN TRANSFER'!G:G, 'STOCK IN TRANSFER'!E:E, B128, 'STOCK IN TRANSFER'!F:F, "STOCK IN") + SUMIFS('STOCK IN TRANSFER'!G:G, 'STOCK IN TRANSFER'!E:E, B128, 'STOCK IN TRANSFER'!F:F, "ADJUSTMENT (+)") - SUMIFS('STOCK IN TRANSFER'!G:G, 'STOCK IN TRANSFER'!E:E, B128, 'STOCK IN TRANSFER'!F:F, "ADJUSTMENT (-)") - SUMIFS('STOCK IN TRANSFER'!G:G, 'STOCK IN TRANSFER'!E:E, B128, 'STOCK IN TRANSFER'!F:F, "STOCK TRANSFER") - SUMIFS(SALES!H:H, SALES!E:E, B128) -> 0
A129: PWTAC-8717-1L | B129: PERMANENT VIOLET ACRY-COLOR PWTAC-8717 1L WELCOAT PREMIUM | C129: 181.764 | D129: 1L | E129: =SUMIFS('STOCK IN TRANSFER'!G:G, 'STOCK IN TRANSFER'!E:E, B129, 'STOCK IN TRANSFER'!F:F, "STOCK IN") + SUMIFS('STOCK IN TRANSFER'!G:G, 'STOCK IN TRANSFER'!E:E, B129, 'STOCK IN TRANSFER'!F:F, "ADJUSTMENT (+)") - SUMIFS('STOCK IN TRANSFER'!G:G, 'STOCK IN TRANSFER'!E:E, B129, 'STOCK IN TRANSFER'!F:F, "ADJUSTMENT (-)") - SUMIFS('STOCK IN TRANSFER'!G:G, 'STOCK IN TRANSFER'!E:E, B129, 'STOCK IN TRANSFER'!F:F, "STOCK TRANSFER") - SUMIFS(SALES!H:H, SALES!E:E, B129) -> 0
... A136: SKIMCOAT | B136: NIPPON SKIMCOAT PAIL | C136: 1755 | D136: PAIL | E136: =SUMIFS('STOCK IN TRANSFER'!G:G, 'STOCK IN TRANSFER'!E:E, B136, 'STOCK IN TRANSFER'!F:F, "STOCK IN") + SUMIFS('STOCK IN TRANSFER'!G:G, 'STOCK IN TRANSFER'!E:E, B136, 'STOCK IN TRANSFER'!F:F, "ADJUSTMENT (+)") - SUMIFS('STOCK IN TRANSFER'!G:G, 'STOCK IN TRANSFER'!E:E, B136, 'STOCK IN TRANSFER'!F:F, "ADJUSTMENT (-)") - SUMIFS('STOCK IN TRANSFER'!G:G, 'STOCK IN TRANSFER'!E:E, B136, 'STOCK IN TRANSFER'!F:F, "STOCK TRANSFER") - SUMIFS(SALES!H:H, SALES!E:E, B136) -> 0
B137: NIPPON PREMIUM HS CLEAR W/HARDENER 1L | C137: 585 | D137: LITER | E137: =SUMIFS('STOCK IN TRANSFER'!G:G, 'STOCK IN TRANSFER'!E:E, B137, 'STOCK IN TRANSFER'!F:F, "STOCK IN") + SUMIFS('STOCK IN TRANSFER'!G:G, 'STOCK IN TRANSFER'!E:E, B137, 'STOCK IN TRANSFER'!F:F, "ADJUSTMENT (+)") - SUMIFS('STOCK IN TRANSFER'!G:G, 'STOCK IN TRANSFER'!E:E, B137, 'STOCK IN TRANSFER'!F:F, "ADJUSTMENT (-)") - SUMIFS('STOCK IN TRANSFER'!G:G, 'STOCK IN TRANSFER'!E:E, B137, 'STOCK IN TRANSFER'!F:F, "STOCK TRANSFER") - SUMIFS(SALES!H:H, SALES!E:E, B137) -> 0
A138: PUT3050-4KG | B138: NIPPON PAINT FILLERMAX BODY FILLER WITH HARDENER 4KG | C138: 565 | D138: GAL | E138: =SUMIFS('STOCK IN TRANSFER'!G:G, 'STOCK IN TRANSFER'!E:E, B138, 'STOCK IN TRANSFER'!F:F, "STOCK IN") + SUMIFS('STOCK IN TRANSFER'!G:G, 'STOCK IN TRANSFER'!E:E, B138, 'STOCK IN TRANSFER'!F:F, "ADJUSTMENT (+)") - SUMIFS('STOCK IN TRANSFER'!G:G, 'STOCK IN TRANSFER'!E:E, B138, 'STOCK IN TRANSFER'!F:F, "ADJUSTMENT (-)") - SUMIFS('STOCK IN TRANSFER'!G:G, 'STOCK IN TRANSFER'!E:E, B138, 'STOCK IN TRANSFER'!F:F, "STOCK TRANSFER") - SUMIFS(SALES!H:H, SALES!E:E, B138) -> 0
A139: MPJOINTCMPND-5L | B139: NIPPON MULTI-PURPOSE JOINT COMPOUND 5L | C139: 400 | D139: GAL/S | E139: =SUMIFS('STOCK IN TRANSFER'!G:G, 'STOCK IN TRANSFER'!E:E, B139, 'STOCK IN TRANSFER'!F:F, "STOCK IN") + SUMIFS('STOCK IN TRANSFER'!G:G, 'STOCK IN TRANSFER'!E:E, B139, 'STOCK IN TRANSFER'!F:F, "ADJUSTMENT (+)") - SUMIFS('STOCK IN TRANSFER'!G:G, 'STOCK IN TRANSFER'!E:E, B139, 'STOCK IN TRANSFER'!F:F, "ADJUSTMENT (-)") - SUMIFS('STOCK IN TRANSFER'!G:G, 'STOCK IN TRANSFER'!E:E, B139, 'STOCK IN TRANSFER'!F:F, "STOCK TRANSFER") - SUMIFS(SALES!H:H, SALES!E:E, B139) -> 4
A140: NMPREDOX-LTR | B140: NIPPON METAL PRIMER RED OXIDE LITER | C140: 147 | D140: LTR | E140: =SUMIFS('STOCK IN TRANSFER'!G:G, 'STOCK IN TRANSFER'!E:E, B140, 'STOCK IN TRANSFER'!F:F, "STOCK IN") + SUMIFS('STOCK IN TRANSFER'!G:G, 'STOCK IN TRANSFER'!E:E, B140, 'STOCK IN TRANSFER'!F:F, "ADJUSTMENT (+)") - SUMIFS('STOCK IN TRANSFER'!G:G, 'STOCK IN TRANSFER'!E:E, B140, 'STOCK IN TRANSFER'!F:F, "ADJUSTMENT (-)") - SUMIFS('STOCK IN TRANSFER'!G:G, 'STOCK IN TRANSFER'!E:E, B140, 'STOCK IN TRANSFER'!F:F, "STOCK TRANSFER") - SUMIFS(SALES!H:H, SALES!E:E, B140) -> 0
A141: NMPREDOX-GAL | B141: NIPPON METAL PRIMER RED OXIDE GAL | C141: 515 | D141: GAL | E141: =SUMIFS('STOCK IN TRANSFER'!G:G, 'STOCK IN TRANSFER'!E:E, B141, 'STOCK IN TRANSFER'!F:F, "STOCK IN") + SUMIFS('STOCK IN TRANSFER'!G:G, 'STOCK IN TRANSFER'!E:E, B141, 'STOCK IN TRANSFER'!F:F, "ADJUSTMENT (+)") - SUMIFS('STOCK IN TRANSFER'!G:G, 'STOCK IN TRANSFER'!E:E, B141, 'STOCK IN TRANSFER'!F:F, "ADJUSTMENT (-)") - SUMIFS('STOCK IN TRANSFER'!G:G, 'STOCK IN TRANSFER'!E:E, B141, 'STOCK IN TRANSFER'!F:F, "STOCK TRANSFER") - SUMIFS(SALES!H:H, SALES!E:E, B141) -> 9
A142: NLT-4L | B142: NIPPON LACQUER THINNER 4L | C142: 435 | D142: GAL | E142: =SUMIFS('STOCK IN TRANSFER'!G:G, 'STOCK IN TRANSFER'!E:E, B142, 'STOCK IN TRANSFER'!F:F, "STOCK IN") + SUMIFS('STOCK IN TRANSFER'!G:G, 'STOCK IN TRANSFER'!E:E, B142, 'STOCK IN TRANSFER'!F:F, "ADJUSTMENT (+)") - SUMIFS('STOCK IN TRANSFER'!G:G, 'STOCK IN TRANSFER'!E:E, B142, 'STOCK IN TRANSFER'!F:F, "ADJUSTMENT (-)") - SUMIFS('STOCK IN TRANSFER'!G:G, 'STOCK IN TRANSFER'!E:E, B142, 'STOCK IN TRANSFER'!F:F, "STOCK TRANSFER") - SUMIFS(SALES!H:H, SALES!E:E, B142) -> 7
A143: NLSS-4L | B143: NIPPON LACQUER SANDING SEALER 4L | C143: 611 | D143: GALON | E143: =SUMIFS('STOCK IN TRANSFER'!G:G, 'STOCK IN TRANSFER'!E:E, B143, 'STOCK IN TRANSFER'!F:F, "STOCK IN") + SUMIFS('STOCK IN TRANSFER'!G:G, 'STOCK IN TRANSFER'!E:E, B143, 'STOCK IN TRANSFER'!F:F, "ADJUSTMENT (+)") - SUMIFS('STOCK IN TRANSFER'!G:G, 'STOCK IN TRANSFER'!E:E, B143, 'STOCK IN TRANSFER'!F:F, "ADJUSTMENT (-)") - SUMIFS('STOCK IN TRANSFER'!G:G, 'STOCK IN TRANSFER'!E:E, B143, 'STOCK IN TRANSFER'!F:F, "STOCK TRANSFER") - SUMIFS(SALES!H:H, SALES!E:E, B143) -> 0
A144: HS-1L | B144: NIPPON HS FILLER 1L | C144: 550 | D144: LITER | E144: =SUMIFS('STOCK IN TRANSFER'!G:G, 'STOCK IN TRANSFER'!E:E, B144, 'STOCK IN TRANSFER'!F:F, "STOCK IN") + SUMIFS('STOCK IN TRANSFER'!G:G, 'STOCK IN TRANSFER'!E:E, B144, 'STOCK IN TRANSFER'!F:F, "ADJUSTMENT (+)") - SUMIFS('STOCK IN TRANSFER'!G:G, 'STOCK IN TRANSFER'!E:E, B144, 'STOCK IN TRANSFER'!F:F, "ADJUSTMENT (-)") - SUMIFS('STOCK IN TRANSFER'!G:G, 'STOCK IN TRANSFER'!E:E, B144, 'STOCK IN TRANSFER'!F:F, "STOCK TRANSFER") - SUMIFS(SALES!H:H, SALES!E:E, B144) -> 10
A145: NFI46G-5KG | B145: NIPPON FLEXI-SEAL 146 GRAY 5KG | C145: 1342 | D145: 5KG | E145: =SUMIFS('STOCK IN TRANSFER'!G:G, 'STOCK IN TRANSFER'!E:E, B145, 'STOCK IN TRANSFER'!F:F, "STOCK IN") + SUMIFS('STOCK IN TRANSFER'!G:G, 'STOCK IN TRANSFER'!E:E, B145, 'STOCK IN TRANSFER'!F:F, "ADJUSTMENT (+)") - SUMIFS('STOCK IN TRANSFER'!G:G, 'STOCK IN TRANSFER'!E:E, B145, 'STOCK IN TRANSFER'!F:F, "ADJUSTMENT (-)") - SUMIFS('STOCK IN TRANSFER'!G:G, 'STOCK IN TRANSFER'!E:E, B145, 'STOCK IN TRANSFER'!F:F, "STOCK TRANSFER") - SUMIFS(SALES!H:H, SALES!E:E, B145) -> 0
A146: NFWE-4L | B146: NIPPON FLATWALL ENAMEL WHITE 4L | C146: 615 | D146: GAL | E146: =SUMIFS('STOCK IN TRANSFER'!G:G, 'STOCK IN TRANSFER'!E:E, B146, 'STOCK IN TRANSFER'!F:F, "STOCK IN") + SUMIFS('STOCK IN TRANSFER'!G:G, 'STOCK IN TRANSFER'!E:E, B146, 'STOCK IN TRANSFER'!F:F, "ADJUSTMENT (+)") - SUMIFS('STOCK IN TRANSFER'!G:G, 'STOCK IN TRANSFER'!E:E, B146, 'STOCK IN TRANSFER'!F:F, "ADJUSTMENT (-)") - SUMIFS('STOCK IN TRANSFER'!G:G, 'STOCK IN TRANSFER'!E:E, B146, 'STOCK IN TRANSFER'!F:F, "STOCK TRANSFER") - SUMIFS(SALES!H:H, SALES!E:E, B146) -> 2
A147: OTH10AD-1L | B147: NIPPON FLATTENING AGENT PASTE 1L | C147: 620 | D147: LITER | E147: =SUMIFS('STOCK IN TRANSFER'!G:G, 'STOCK IN TRANSFER'!E:E, B147, 'STOCK IN TRANSFER'!F:F, "STOCK IN") + SUMIFS('STOCK IN TRANSFER'!G:G, 'STOCK IN TRANSFER'!E:E, B147, 'STOCK IN TRANSFER'!F:F, "ADJUSTMENT (+)") - SUMIFS('STOCK IN TRANSFER'!G:G, 'STOCK IN TRANSFER'!E:E, B147, 'STOCK IN TRANSFER'!F:F, "ADJUSTMENT (-)") - SUMIFS('STOCK IN TRANSFER'!G:G, 'STOCK IN TRANSFER'!E:E, B147, 'STOCK IN TRANSFER'!F:F, "STOCK TRANSFER") - SUMIFS(SALES!H:H, SALES!E:E, B147) -> 8
A148: FF151 | B148: NIPPON FF151 FLOP CONTROL | C148: 1160 | D148: LTR | E148: =SUMIFS('STOCK IN TRANSFER'!G:G, 'STOCK IN TRANSFER'!E:E, B148, 'STOCK IN TRANSFER'!F:F, "STOCK IN") + SUMIFS('STOCK IN TRANSFER'!G:G, 'STOCK IN TRANSFER'!E:E, B148, 'STOCK IN TRANSFER'!F:F, "ADJUSTMENT (+)") - SUMIFS('STOCK IN TRANSFER'!G:G, 'STOCK IN TRANSFER'!E:E, B148, 'STOCK IN TRANSFER'!F:F, "ADJUSTMENT (-)") - SUMIFS('STOCK IN TRANSFER'!G:G, 'STOCK IN TRANSFER'!E:E, B148, 'STOCK IN TRANSFER'!F:F, "STOCK TRANSFER") - SUMIFS(SALES!H:H, SALES!E:E, B148) -> 1
A149: NXU1338-4L | B149: NIPPON EXTREME QDU YELLOW 4L | C149: 1630 | D149: GAL | E149: =SUMIFS('STOCK IN TRANSFER'!G:G, 'STOCK IN TRANSFER'!E:E, B149, 'STOCK IN TRANSFER'!F:F, "STOCK IN") + SUMIFS('STOCK IN TRANSFER'!G:G, 'STOCK IN TRANSFER'!E:E, B149, 'STOCK IN TRANSFER'!F:F, "ADJUSTMENT (+)") - SUMIFS('STOCK IN TRANSFER'!G:G, 'STOCK IN TRANSFER'!E:E, B149, 'STOCK IN TRANSFER'!F:F, "ADJUSTMENT (-)") - SUMIFS('STOCK IN TRANSFER'!G:G, 'STOCK IN TRANSFER'!E:E, B149, 'STOCK IN TRANSFER'!F:F, "STOCK TRANSFER") - SUMIFS(SALES!H:H, SALES!E:E, B149) -> 3
... A162: EPOXYTHNR-4L | B162: NIPPON EPOXY THINNER 4L | C162: 550 | D162: GAL/S | E162: =SUMIFS('STOCK IN TRANSFER'!G:G, 'STOCK IN TRANSFER'!E:E, B162, 'STOCK IN TRANSFER'!F:F, "STOCK IN") + SUMIFS('STOCK IN TRANSFER'!G:G, 'STOCK IN TRANSFER'!E:E, B162, 'STOCK IN TRANSFER'!F:F, "ADJUSTMENT (+)") - SUMIFS('STOCK IN TRANSFER'!G:G, 'STOCK IN TRANSFER'!E:E, B162, 'STOCK IN TRANSFER'!F:F, "ADJUSTMENT (-)") - SUMIFS('STOCK IN TRANSFER'!G:G, 'STOCK IN TRANSFER'!E:E, B162, 'STOCK IN TRANSFER'!F:F, "STOCK TRANSFER") - SUMIFS(SALES!H:H, SALES!E:E, B162) -> 0
A163: DCTBSG-5L | B163: NIPPON DOU CLASSIC TINT BASE SEMI-GLOSS 5L | D163: GAL | E163: =SUMIFS('STOCK IN TRANSFER'!G:G, 'STOCK IN TRANSFER'!E:E, B163, 'STOCK IN TRANSFER'!F:F, "STOCK IN") + SUMIFS('STOCK IN TRANSFER'!G:G, 'STOCK IN TRANSFER'!E:E, B163, 'STOCK IN TRANSFER'!F:F, "ADJUSTMENT (+)") - SUMIFS('STOCK IN TRANSFER'!G:G, 'STOCK IN TRANSFER'!E:E, B163, 'STOCK IN TRANSFER'!F:F, "ADJUSTMENT (-)") - SUMIFS('STOCK IN TRANSFER'!G:G, 'STOCK IN TRANSFER'!E:E, B163, 'STOCK IN TRANSFER'!F:F, "STOCK TRANSFER") - SUMIFS(SALES!H:H, SALES!E:E, B163) -> 0
A164: DCTBSG-1L | B164: NIPPON DOU CLASSIC TINT BASE SEMI-GLOSS 1L | D164: LITER | E164: =SUMIFS('STOCK IN TRANSFER'!G:G, 'STOCK IN TRANSFER'!E:E, B164, 'STOCK IN TRANSFER'!F:F, "STOCK IN") + SUMIFS('STOCK IN TRANSFER'!G:G, 'STOCK IN TRANSFER'!E:E, B164, 'STOCK IN TRANSFER'!F:F, "ADJUSTMENT (+)") - SUMIFS('STOCK IN TRANSFER'!G:G, 'STOCK IN TRANSFER'!E:E, B164, 'STOCK IN TRANSFER'!F:F, "ADJUSTMENT (-)") - SUMIFS('STOCK IN TRANSFER'!G:G, 'STOCK IN TRANSFER'!E:E, B164, 'STOCK IN TRANSFER'!F:F, "STOCK TRANSFER") - SUMIFS(SALES!H:H, SALES!E:E, B164) -> 0
A165: DCTBSG-15L | B165: NIPPON DOU CLASSIC TINT BASE SEMI-GLOSS 15L | D165: PAIL | E165: =SUMIFS('STOCK IN TRANSFER'!G:G, 'STOCK IN TRANSFER'!E:E, B165, 'STOCK IN TRANSFER'!F:F, "STOCK IN") + SUMIFS('STOCK IN TRANSFER'!G:G, 'STOCK IN TRANSFER'!E:E, B165, 'STOCK IN TRANSFER'!F:F, "ADJUSTMENT (+)") - SUMIFS('STOCK IN TRANSFER'!G:G, 'STOCK IN TRANSFER'!E:E, B165, 'STOCK IN TRANSFER'!F:F, "ADJUSTMENT (-)") - SUMIFS('STOCK IN TRANSFER'!G:G, 'STOCK IN TRANSFER'!E:E, B165, 'STOCK IN TRANSFER'!F:F, "STOCK TRANSFER") - SUMIFS(SALES!H:H, SALES!E:E, B165) -> 0
A166: DCSG715-1L | B166: NIPPON DOU CLASSIC SG WHITE 715 1L | C166: 186 | D166: LITER | E166: =SUMIFS('STOCK IN TRANSFER'!G:G, 'STOCK IN TRANSFER'!E:E, B166, 'STOCK IN TRANSFER'!F:F, "STOCK IN") + SUMIFS('STOCK IN TRANSFER'!G:G, 'STOCK IN TRANSFER'!E:E, B166, 'STOCK IN TRANSFER'!F:F, "ADJUSTMENT (+)") - SUMIFS('STOCK IN TRANSFER'!G:G, 'STOCK IN TRANSFER'!E:E, B166, 'STOCK IN TRANSFER'!F:F, "ADJUSTMENT (-)") - SUMIFS('STOCK IN TRANSFER'!G:G, 'STOCK IN TRANSFER'!E:E, B166, 'STOCK IN TRANSFER'!F:F, "STOCK TRANSFER") - SUMIFS(SALES!H:H, SALES!E:E, B166) -> 0
A167: DCSG715-15L | B167: NIPPON DOU CLASSIC SG WHITE 715 15L | C167: 2680 | D167: PAIL | E167: =SUMIFS('STOCK IN TRANSFER'!G:G, 'STOCK IN TRANSFER'!E:E, B167, 'STOCK IN TRANSFER'!F:F, "STOCK IN") + SUMIFS('STOCK IN TRANSFER'!G:G, 'STOCK IN TRANSFER'!E:E, B167, 'STOCK IN TRANSFER'!F:F, "ADJUSTMENT (+)") - SUMIFS('STOCK IN TRANSFER'!G:G, 'STOCK IN TRANSFER'!E:E, B167, 'STOCK IN TRANSFER'!F:F, "ADJUSTMENT (-)") - SUMIFS('STOCK IN TRANSFER'!G:G, 'STOCK IN TRANSFER'!E:E, B167, 'STOCK IN TRANSFER'!F:F, "STOCK TRANSFER") - SUMIFS(SALES!H:H, SALES!E:E, B167) -> 0
A168: 2045T-5L | B168: NIPPON DOU CLASSIC SG SMOKING GRAY 2045T 5L | D168: GAL/S | E168: =SUMIFS('STOCK IN TRANSFER'!G:G, 'STOCK IN TRANSFER'!E:E, B168, 'STOCK IN TRANSFER'!F:F, "STOCK IN") + SUMIFS('STOCK IN TRANSFER'!G:G, 'STOCK IN TRANSFER'!E:E, B168, 'STOCK IN TRANSFER'!F:F, "ADJUSTMENT (+)") - SUMIFS('STOCK IN TRANSFER'!G:G, 'STOCK IN TRANSFER'!E:E, B168, 'STOCK IN TRANSFER'!F:F, "ADJUSTMENT (-)") - SUMIFS('STOCK IN TRANSFER'!G:G, 'STOCK IN TRANSFER'!E:E, B168, 'STOCK IN TRANSFER'!F:F, "STOCK TRANSFER") - SUMIFS(SALES!H:H, SALES!E:E, B168) -> 0
A169: 2027P-5L | B169: NIPPON DOU CLASSIC SG GRAY SUIT 2027P 5L | D169: GAL/S | E169: =SUMIFS('STOCK IN TRANSFER'!G:G, 'STOCK IN TRANSFER'!E:E, B169, 'STOCK IN TRANSFER'!F:F, "STOCK IN") + SUMIFS('STOCK IN TRANSFER'!G:G, 'STOCK IN TRANSFER'!E:E, B169, 'STOCK IN TRANSFER'!F:F, "ADJUSTMENT (+)") - SUMIFS('STOCK IN TRANSFER'!G:G, 'STOCK IN TRANSFER'!E:E, B169, 'STOCK IN TRANSFER'!F:F, "ADJUSTMENT (-)") - SUMIFS('STOCK IN TRANSFER'!G:G, 'STOCK IN TRANSFER'!E:E, B169, 'STOCK IN TRANSFER'!F:F, "STOCK TRANSFER") - SUMIFS(SALES!H:H, SALES!E:E, B169) -> 0
A170: 2034P-5L | B170: NIPPON DOU CLASSIC SG ABACADABRA 2034P 5L | D170: GAL/S | E170: =SUMIFS('STOCK IN TRANSFER'!G:G, 'STOCK IN TRANSFER'!E:E, B170, 'STOCK IN TRANSFER'!F:F, "STOCK IN") + SUMIFS('STOCK IN TRANSFER'!G:G, 'STOCK IN TRANSFER'!E:E, B170, 'STOCK IN TRANSFER'!F:F, "ADJUSTMENT (+)") - SUMIFS('STOCK IN TRANSFER'!G:G, 'STOCK IN TRANSFER'!E:E, B170, 'STOCK IN TRANSFER'!F:F, "ADJUSTMENT (-)") - SUMIFS('STOCK IN TRANSFER'!G:G, 'STOCK IN TRANSFER'!E:E, B170, 'STOCK IN TRANSFER'!F:F, "STOCK TRANSFER") - SUMIFS(SALES!H:H, SALES!E:E, B170) -> 0
A171: DCSG715-5L | B171: NIPPON DOU CLASSIC SG 715 WHITE 5L | C171: 828 | D171: GAL | E171: =SUMIFS('STOCK IN TRANSFER'!G:G, 'STOCK IN TRANSFER'!E:E, B171, 'STOCK IN TRANSFER'!F:F, "STOCK IN") + SUMIFS('STOCK IN TRANSFER'!G:G, 'STOCK IN TRANSFER'!E:E, B171, 'STOCK IN TRANSFER'!F:F, "ADJUSTMENT (+)") - SUMIFS('STOCK IN TRANSFER'!G:G, 'STOCK IN TRANSFER'!E:E, B171, 'STOCK IN TRANSFER'!F:F, "ADJUSTMENT (-)") - SUMIFS('STOCK IN TRANSFER'!G:G, 'STOCK IN TRANSFER'!E:E, B171, 'STOCK IN TRANSFER'!F:F, "STOCK TRANSFER") - SUMIFS(SALES!H:H, SALES!E:E, B171) -> 0
A172: DCPBSG-5L | B172: NIPPON DOU CLASSIC PASTEL BASE SEMI-GLOSS 5L | D172: GAL | E172: =SUMIFS('STOCK IN TRANSFER'!G:G, 'STOCK IN TRANSFER'!E:E, B172, 'STOCK IN TRANSFER'!F:F, "STOCK IN") + SUMIFS('STOCK IN TRANSFER'!G:G, 'STOCK IN TRANSFER'!E:E, B172, 'STOCK IN TRANSFER'!F:F, "ADJUSTMENT (+)") - SUMIFS('STOCK IN TRANSFER'!G:G, 'STOCK IN TRANSFER'!E:E, B172, 'STOCK IN TRANSFER'!F:F, "ADJUSTMENT (-)") - SUMIFS('STOCK IN TRANSFER'!G:G, 'STOCK IN TRANSFER'!E:E, B172, 'STOCK IN TRANSFER'!F:F, "STOCK TRANSFER") - SUMIFS(SALES!H:H, SALES!E:E, B172) -> 0
A173: DCPBSG-1L | B173: NIPPON DOU CLASSIC PASTEL BASE SEMI-GLOSS 1L | D173: LITER | E173: =SUMIFS('STOCK IN TRANSFER'!G:G, 'STOCK IN TRANSFER'!E:E, B173, 'STOCK IN TRANSFER'!F:F, "STOCK IN") + SUMIFS('STOCK IN TRANSFER'!G:G, 'STOCK IN TRANSFER'!E:E, B173, 'STOCK IN TRANSFER'!F:F, "ADJUSTMENT (+)") - SUMIFS('STOCK IN TRANSFER'!G:G, 'STOCK IN TRANSFER'!E:E, B173, 'STOCK IN TRANSFER'!F:F, "ADJUSTMENT (-)") - SUMIFS('STOCK IN TRANSFER'!G:G, 'STOCK IN TRANSFER'!E:E, B173, 'STOCK IN TRANSFER'!F:F, "STOCK TRANSFER") - SUMIFS(SALES!H:H, SALES!E:E, B173) -> 0
A174: DCPBSG-15L | B174: NIPPON DOU CLASSIC PASTEL BASE SEMI-GLOSS 15L | D174: PAIL | E174: =SUMIFS('STOCK IN TRANSFER'!G:G, 'STOCK IN TRANSFER'!E:E, B174, 'STOCK IN TRANSFER'!F:F, "STOCK IN") + SUMIFS('STOCK IN TRANSFER'!G:G, 'STOCK IN TRANSFER'!E:E, B174, 'STOCK IN TRANSFER'!F:F, "ADJUSTMENT (+)") - SUMIFS('STOCK IN TRANSFER'!G:G, 'STOCK IN TRANSFER'!E:E, B174, 'STOCK IN TRANSFER'!F:F, "ADJUSTMENT (-)") - SUMIFS('STOCK IN TRANSFER'!G:G, 'STOCK IN TRANSFER'!E:E, B174, 'STOCK IN TRANSFER'!F:F, "STOCK TRANSFER") - SUMIFS(SALES!H:H, SALES!E:E, B174) -> 0
A175: DCF701-5L | B175: NIPPON DOU CLASSIC FLAT WHITE 701 5L | C175: 630 | D175: GAL | E175: =SUMIFS('STOCK IN TRANSFER'!G:G, 'STOCK IN TRANSFER'!E:E, B175, 'STOCK IN TRANSFER'!F:F, "STOCK IN") + SUMIFS('STOCK IN TRANSFER'!G:G, 'STOCK IN TRANSFER'!E:E, B175, 'STOCK IN TRANSFER'!F:F, "ADJUSTMENT (+)") - SUMIFS('STOCK IN TRANSFER'!G:G, 'STOCK IN TRANSFER'!E:E, B175, 'STOCK IN TRANSFER'!F:F, "ADJUSTMENT (-)") - SUMIFS('STOCK IN TRANSFER'!G:G, 'STOCK IN TRANSFER'!E:E, B175, 'STOCK IN TRANSFER'!F:F, "STOCK TRANSFER") - SUMIFS(SALES!H:H, SALES!E:E, B175) -> 0
A176: DCF701-1L | B176: NIPPON DOU CLASSIC FLAT WHITE 701 1L | C176: 165 | D176: LITER | E176: =SUMIFS('STOCK IN TRANSFER'!G:G, 'STOCK IN TRANSFER'!E:E, B176, 'STOCK IN TRANSFER'!F:F, "STOCK IN") + SUMIFS('STOCK IN TRANSFER'!G:G, 'STOCK IN TRANSFER'!E:E, B176, 'STOCK IN TRANSFER'!F:F, "ADJUSTMENT (+)") - SUMIFS('STOCK IN TRANSFER'!G:G, 'STOCK IN TRANSFER'!E:E, B176, 'STOCK IN TRANSFER'!F:F, "ADJUSTMENT (-)") - SUMIFS('STOCK IN TRANSFER'!G:G, 'STOCK IN TRANSFER'!E:E, B176, 'STOCK IN TRANSFER'!F:F, "STOCK TRANSFER") - SUMIFS(SALES!H:H, SALES!E:E, B176) -> 2
A177: DCF701-15L | B177: NIPPON DOU CLASSIC FLAT WHITE 701 15L | C177: 2130 | D177: PAIL | E177: =SUMIFS('STOCK IN TRANSFER'!G:G, 'STOCK IN TRANSFER'!E:E, B177, 'STOCK IN TRANSFER'!F:F, "STOCK IN") + SUMIFS('STOCK IN TRANSFER'!G:G, 'STOCK IN TRANSFER'!E:E, B177, 'STOCK IN TRANSFER'!F:F, "ADJUSTMENT (+)") - SUMIFS('STOCK IN TRANSFER'!G:G, 'STOCK IN TRANSFER'!E:E, B177, 'STOCK IN TRANSFER'!F:F, "ADJUSTMENT (-)") - SUMIFS('STOCK IN TRANSFER'!G:G, 'STOCK IN TRANSFER'!E:E, B177, 'STOCK IN TRANSFER'!F:F, "STOCK TRANSFER") - SUMIFS(SALES!H:H, SALES!E:E, B177) -> 4
A178: DCDBSG-5L | B178: NIPPON DOU CLASSIC DEEP BASE SEMI-GLOSS 5L | D178: GAL | E178: =SUMIFS('STOCK IN TRANSFER'!G:G, 'STOCK IN TRANSFER'!E:E, B178, 'STOCK IN TRANSFER'!F:F, "STOCK IN") + SUMIFS('STOCK IN TRANSFER'!G:G, 'STOCK IN TRANSFER'!E:E, B178, 'STOCK IN TRANSFER'!F:F, "ADJUSTMENT (+)") - SUMIFS('STOCK IN TRANSFER'!G:G, 'STOCK IN TRANSFER'!E:E, B178, 'STOCK IN TRANSFER'!F:F, "ADJUSTMENT (-)") - SUMIFS('STOCK IN TRANSFER'!G:G, 'STOCK IN TRANSFER'!E:E, B178, 'STOCK IN TRANSFER'!F:F, "STOCK TRANSFER") - SUMIFS(SALES!H:H, SALES!E:E, B178) -> 0
A179: DCDBSG-1L | B179: NIPPON DOU CLASSIC DEEP BASE SEMI-GLOSS 1L | D179: LITER | E179: =SUMIFS('STOCK IN TRANSFER'!G:G, 'STOCK IN TRANSFER'!E:E, B179, 'STOCK IN TRANSFER'!F:F, "STOCK IN") + SUMIFS('STOCK IN TRANSFER'!G:G, 'STOCK IN TRANSFER'!E:E, B179, 'STOCK IN TRANSFER'!F:F, "ADJUSTMENT (+)") - SUMIFS('STOCK IN TRANSFER'!G:G, 'STOCK IN TRANSFER'!E:E, B179, 'STOCK IN TRANSFER'!F:F, "ADJUSTMENT (-)") - SUMIFS('STOCK IN TRANSFER'!G:G, 'STOCK IN TRANSFER'!E:E, B179, 'STOCK IN TRANSFER'!F:F, "STOCK TRANSFER") - SUMIFS(SALES!H:H, SALES!E:E, B179) -> 0
A180: DCDBSG-15L | B180: NIPPON DOU CLASSIC DEEP BASE SEMI-GLOSS 15L | D180: PAIL | E180: =SUMIFS('STOCK IN TRANSFER'!G:G, 'STOCK IN TRANSFER'!E:E, B180, 'STOCK IN TRANSFER'!F:F, "STOCK IN") + SUMIFS('STOCK IN TRANSFER'!G:G, 'STOCK IN TRANSFER'!E:E, B180, 'STOCK IN TRANSFER'!F:F, "ADJUSTMENT (+)") - SUMIFS('STOCK IN TRANSFER'!G:G, 'STOCK IN TRANSFER'!E:E, B180, 'STOCK IN TRANSFER'!F:F, "ADJUSTMENT (-)") - SUMIFS('STOCK IN TRANSFER'!G:G, 'STOCK IN TRANSFER'!E:E, B180, 'STOCK IN TRANSFER'!F:F, "STOCK TRANSFER") - SUMIFS(SALES!H:H, SALES!E:E, B180) -> 0
A181: DCABSG-5L | B181: NIPPON DOU CLASSIC ACCENT BASE SEMI-GLOSS 5L | D181: GAL | E181: =SUMIFS('STOCK IN TRANSFER'!G:G, 'STOCK IN TRANSFER'!E:E, B181, 'STOCK IN TRANSFER'!F:F, "STOCK IN") + SUMIFS('STOCK IN TRANSFER'!G:G, 'STOCK IN TRANSFER'!E:E, B181, 'STOCK IN TRANSFER'!F:F, "ADJUSTMENT (+)") - SUMIFS('STOCK IN TRANSFER'!G:G, 'STOCK IN TRANSFER'!E:E, B181, 'STOCK IN TRANSFER'!F:F, "ADJUSTMENT (-)") - SUMIFS('STOCK IN TRANSFER'!G:G, 'STOCK IN TRANSFER'!E:E, B181, 'STOCK IN TRANSFER'!F:F, "STOCK TRANSFER") - SUMIFS(SALES!H:H, SALES!E:E, B181) -> 0
A182: DCABSG-1L | B182: NIPPON DOU CLASSIC ACCENT BASE SEMI-GLOSS 1L | D182: LITER | E182: =SUMIFS('STOCK IN TRANSFER'!G:G, 'STOCK IN TRANSFER'!E:E, B182, 'STOCK IN TRANSFER'!F:F, "STOCK IN") + SUMIFS('STOCK IN TRANSFER'!G:G, 'STOCK IN TRANSFER'!E:E, B182, 'STOCK IN TRANSFER'!F:F, "ADJUSTMENT (+)") - SUMIFS('STOCK IN TRANSFER'!G:G, 'STOCK IN TRANSFER'!E:E, B182, 'STOCK IN TRANSFER'!F:F, "ADJUSTMENT (-)") - SUMIFS('STOCK IN TRANSFER'!G:G, 'STOCK IN TRANSFER'!E:E, B182, 'STOCK IN TRANSFER'!F:F, "STOCK TRANSFER") - SUMIFS(SALES!H:H, SALES!E:E, B182) -> 0
A183: DCABSG-15L | B183: NIPPON DOU CLASSIC ACCENT BASE SEMI-GLOSS 15L | D183: PAIL | E183: =SUMIFS('STOCK IN TRANSFER'!G:G, 'STOCK IN TRANSFER'!E:E, B183, 'STOCK IN TRANSFER'!F:F, "STOCK IN") + SUMIFS('STOCK IN TRANSFER'!G:G, 'STOCK IN TRANSFER'!E:E, B183, 'STOCK IN TRANSFER'!F:F, "ADJUSTMENT (+)") - SUMIFS('STOCK IN TRANSFER'!G:G, 'STOCK IN TRANSFER'!E:E, B183, 'STOCK IN TRANSFER'!F:F, "ADJUSTMENT (-)") - SUMIFS('STOCK IN TRANSFER'!G:G, 'STOCK IN TRANSFER'!E:E, B183, 'STOCK IN TRANSFER'!F:F, "STOCK TRANSFER") - SUMIFS(SALES!H:H, SALES!E:E, B183) -> 0
A184: NCGVARNISH-LTR | B184: NIPPON CLEAR GLOSS VARNISH LITER | C184: 449 | D184: LTR | E184: =SUMIFS('STOCK IN TRANSFER'!G:G, 'STOCK IN TRANSFER'!E:E, B184, 'STOCK IN TRANSFER'!F:F, "STOCK IN") + SUMIFS('STOCK IN TRANSFER'!G:G, 'STOCK IN TRANSFER'!E:E, B184, 'STOCK IN TRANSFER'!F:F, "ADJUSTMENT (+)") - SUMIFS('STOCK IN TRANSFER'!G:G, 'STOCK IN TRANSFER'!E:E, B184, 'STOCK IN TRANSFER'!F:F, "ADJUSTMENT (-)") - SUMIFS('STOCK IN TRANSFER'!G:G, 'STOCK IN TRANSFER'!E:E, B184, 'STOCK IN TRANSFER'!F:F, "STOCK TRANSFER") - SUMIFS(SALES!H:H, SALES!E:E, B184) -> 1
A185: NCGVARNISH-GAL | B185: NIPPON CLEAR GLOSS VARNISH GAL | C185: 1460 | D185: GAL | E185: =SUMIFS('STOCK IN TRANSFER'!G:G, 'STOCK IN TRANSFER'!E:E, B185, 'STOCK IN TRANSFER'!F:F, "STOCK IN") + SUMIFS('STOCK IN TRANSFER'!G:G, 'STOCK IN TRANSFER'!E:E, B185, 'STOCK IN TRANSFER'!F:F, "ADJUSTMENT (+)") - SUMIFS('STOCK IN TRANSFER'!G:G, 'STOCK IN TRANSFER'!E:E, B185, 'STOCK IN TRANSFER'!F:F, "ADJUSTMENT (-)") - SUMIFS('STOCK IN TRANSFER'!G:G, 'STOCK IN TRANSFER'!E:E, B185, 'STOCK IN TRANSFER'!F:F, "STOCK TRANSFER") - SUMIFS(SALES!H:H, SALES!E:E, B185) -> 4
A186: NCGL-4L | B186: NIPPON CLEAR GLOSS LACQUER 4L | C186: 660 | D186: GAL | E186: =SUMIFS('STOCK IN TRANSFER'!G:G, 'STOCK IN TRANSFER'!E:E, B186, 'STOCK IN TRANSFER'!F:F, "STOCK IN") + SUMIFS('STOCK IN TRANSFER'!G:G, 'STOCK IN TRANSFER'!E:E, B186, 'STOCK IN TRANSFER'!F:F, "ADJUSTMENT (+)") - SUMIFS('STOCK IN TRANSFER'!G:G, 'STOCK IN TRANSFER'!E:E, B186, 'STOCK IN TRANSFER'!F:F, "ADJUSTMENT (-)") - SUMIFS('STOCK IN TRANSFER'!G:G, 'STOCK IN TRANSFER'!E:E, B186, 'STOCK IN TRANSFER'!F:F, "STOCK TRANSFER") - SUMIFS(SALES!H:H, SALES!E:E, B186) -> 4
A187: NAS-5G | B187: NIPPON ACRYLIC SKIMCOAT 5KG | C187: 402 | D187: 5KG | E187: =SUMIFS('STOCK IN TRANSFER'!G:G, 'STOCK IN TRANSFER'!E:E, B187, 'STOCK IN TRANSFER'!F:F, "STOCK IN") + SUMIFS('STOCK IN TRANSFER'!G:G, 'STOCK IN TRANSFER'!E:E, B187, 'STOCK IN TRANSFER'!F:F, "ADJUSTMENT (+)") - SUMIFS('STOCK IN TRANSFER'!G:G, 'STOCK IN TRANSFER'!E:E, B187, 'STOCK IN TRANSFER'!F:F, "ADJUSTMENT (-)") - SUMIFS('STOCK IN TRANSFER'!G:G, 'STOCK IN TRANSFER'!E:E, B187, 'STOCK IN TRANSFER'!F:F, "STOCK TRANSFER") - SUMIFS(SALES!H:H, SALES!E:E, B187) -> 7
A188: NAS535 | B188: NIPPON ACRYLIC GLOSS THINNER 4L | C188: 450 | D188: GAL/S | E188: =SUMIFS('STOCK IN TRANSFER'!G:G, 'STOCK IN TRANSFER'!E:E, B188, 'STOCK IN TRANSFER'!F:F, "STOCK IN") + SUMIFS('STOCK IN TRANSFER'!G:G, 'STOCK IN TRANSFER'!E:E, B188, 'STOCK IN TRANSFER'!F:F, "ADJUSTMENT (+)") - SUMIFS('STOCK IN TRANSFER'!G:G, 'STOCK IN TRANSFER'!E:E, B188, 'STOCK IN TRANSFER'!F:F, "ADJUSTMENT (-)") - SUMIFS('STOCK IN TRANSFER'!G:G, 'STOCK IN TRANSFER'!E:E, B188, 'STOCK IN TRANSFER'!F:F, "STOCK TRANSFER") - SUMIFS(SALES!H:H, SALES!E:E, B188) -> 13
A189: PNB-1L | B189: NIPPON 2K BINDER 1L | C189: 900 | D189: LITER | E189: =SUMIFS('STOCK IN TRANSFER'!G:G, 'STOCK IN TRANSFER'!E:E, B189, 'STOCK IN TRANSFER'!F:F, "STOCK IN") + SUMIFS('STOCK IN TRANSFER'!G:G, 'STOCK IN TRANSFER'!E:E, B189, 'STOCK IN TRANSFER'!F:F, "ADJUSTMENT (+)") - SUMIFS('STOCK IN TRANSFER'!G:G, 'STOCK IN TRANSFER'!E:E, B189, 'STOCK IN TRANSFER'!F:F, "ADJUSTMENT (-)") - SUMIFS('STOCK IN TRANSFER'!G:G, 'STOCK IN TRANSFER'!E:E, B189, 'STOCK IN TRANSFER'!F:F, "STOCK TRANSFER") - SUMIFS(SALES!H:H, SALES!E:E, B189) -> 0
A190: NPA1487 | B190: NIPPELAC ACE THALO GREEN 4L | C190: 1215 | D190: GAL | E190: =SUMIFS('STOCK IN TRANSFER'!G:G, 'STOCK IN TRANSFER'!E:E, B190, 'STOCK IN TRANSFER'!F:F, "STOCK IN") + SUMIFS('STOCK IN TRANSFER'!G:G, 'STOCK IN TRANSFER'!E:E, B190, 'STOCK IN TRANSFER'!F:F, "ADJUSTMENT (+)") - SUMIFS('STOCK IN TRANSFER'!G:G, 'STOCK IN TRANSFER'!E:E, B190, 'STOCK IN TRANSFER'!F:F, "ADJUSTMENT (-)") - SUMIFS('STOCK IN TRANSFER'!G:G, 'STOCK IN TRANSFER'!E:E, B190, 'STOCK IN TRANSFER'!F:F, "STOCK TRANSFER") - SUMIFS(SALES!H:H, SALES!E:E, B190) -> 6
A191: NPA1131 | B191: NIPPELAC ACE RED TRIPPLE 8 4L | C191: 1850 | D191: GAL | E191: =SUMIFS('STOCK IN TRANSFER'!G:G, 'STOCK IN TRANSFER'!E:E, B191, 'STOCK IN TRANSFER'!F:F, "STOCK IN") + SUMIFS('STOCK IN TRANSFER'!G:G, 'STOCK IN TRANSFER'!E:E, B191, 'STOCK IN TRANSFER'!F:F, "ADJUSTMENT (+)") - SUMIFS('STOCK IN TRANSFER'!G:G, 'STOCK IN TRANSFER'!E:E, B191, 'STOCK IN TRANSFER'!F:F, "ADJUSTMENT (-)") - SUMIFS('STOCK IN TRANSFER'!G:G, 'STOCK IN TRANSFER'!E:E, B191, 'STOCK IN TRANSFER'!F:F, "STOCK TRANSFER") - SUMIFS(SALES!H:H, SALES!E:E, B191) -> 8
A192: NPA1177 | B192: NIPPELAC ACE PERMANENT MAROON 4L | C192: 0 | D192: GAL | E192: =SUMIFS('STOCK IN TRANSFER'!G:G, 'STOCK IN TRANSFER'!E:E, B192, 'STOCK IN TRANSFER'!F:F, "STOCK IN") + SUMIFS('STOCK IN TRANSFER'!G:G, 'STOCK IN TRANSFER'!E:E, B192, 'STOCK IN TRANSFER'!F:F, "ADJUSTMENT (+)") - SUMIFS('STOCK IN TRANSFER'!G:G, 'STOCK IN TRANSFER'!E:E, B192, 'STOCK IN TRANSFER'!F:F, "ADJUSTMENT (-)") - SUMIFS('STOCK IN TRANSFER'!G:G, 'STOCK IN TRANSFER'!E:E, B192, 'STOCK IN TRANSFER'!F:F, "STOCK TRANSFER") - SUMIFS(SALES!H:H, SALES!E:E, B192) -> 0
A193: NPA1372 | B193: NIPPELAC ACE LEMON YELLOW 4L | C193: 1120 | D193: GAL | E193: =SUMIFS('STOCK IN TRANSFER'!G:G, 'STOCK IN TRANSFER'!E:E, B193, 'STOCK IN TRANSFER'!F:F, "STOCK IN") + SUMIFS('STOCK IN TRANSFER'!G:G, 'STOCK IN TRANSFER'!E:E, B193, 'STOCK IN TRANSFER'!F:F, "ADJUSTMENT (+)") - SUMIFS('STOCK IN TRANSFER'!G:G, 'STOCK IN TRANSFER'!E:E, B193, 'STOCK IN TRANSFER'!F:F, "ADJUSTMENT (-)") - SUMIFS('STOCK IN TRANSFER'!G:G, 'STOCK IN TRANSFER'!E:E, B193, 'STOCK IN TRANSFER'!F:F, "STOCK TRANSFER") - SUMIFS(SALES!H:H, SALES!E:E, B193) -> 4
A194: NPA1983 | B194: NIPPELAC ACE JET BLACK 4L | C194: 1050 | D194: GAL | E194: =SUMIFS('STOCK IN TRANSFER'!G:G, 'STOCK IN TRANSFER'!E:E, B194, 'STOCK IN TRANSFER'!F:F, "STOCK IN") + SUMIFS('STOCK IN TRANSFER'!G:G, 'STOCK IN TRANSFER'!E:E, B194, 'STOCK IN TRANSFER'!F:F, "ADJUSTMENT (+)") - SUMIFS('STOCK IN TRANSFER'!G:G, 'STOCK IN TRANSFER'!E:E, B194, 'STOCK IN TRANSFER'!F:F, "ADJUSTMENT (-)") - SUMIFS('STOCK IN TRANSFER'!G:G, 'STOCK IN TRANSFER'!E:E, B194, 'STOCK IN TRANSFER'!F:F, "STOCK TRANSFER") - SUMIFS(SALES!H:H, SALES!E:E, B194) -> 2
A195: NPA4021 | B195: NIPPELAC ACE BRIGHT WHITE 4L | C195: 1000 | D195: GAL | E195: =SUMIFS('STOCK IN TRANSFER'!G:G, 'STOCK IN TRANSFER'!E:E, B195, 'STOCK IN TRANSFER'!F:F, "STOCK IN") + SUMIFS('STOCK IN TRANSFER'!G:G, 'STOCK IN TRANSFER'!E:E, B195, 'STOCK IN TRANSFER'!F:F, "ADJUSTMENT (+)") - SUMIFS('STOCK IN TRANSFER'!G:G, 'STOCK IN TRANSFER'!E:E, B195, 'STOCK IN TRANSFER'!F:F, "ADJUSTMENT (-)") - SUMIFS('STOCK IN TRANSFER'!G:G, 'STOCK IN TRANSFER'!E:E, B195, 'STOCK IN TRANSFER'!F:F, "STOCK TRANSFER") - SUMIFS(SALES!H:H, SALES!E:E, B195) -> 12
... A321: NAT305 | B321: NAX NAT-305 TTC GREEN YELLOW 1L | C321: 1380 | D321: LITER | E321: =SUMIFS('STOCK IN TRANSFER'!G:G, 'STOCK IN TRANSFER'!E:E, B321, 'STOCK IN TRANSFER'!F:F, "STOCK IN") + SUMIFS('STOCK IN TRANSFER'!G:G, 'STOCK IN TRANSFER'!E:E, B321, 'STOCK IN TRANSFER'!F:F, "ADJUSTMENT (+)") - SUMIFS('STOCK IN TRANSFER'!G:G, 'STOCK IN TRANSFER'!E:E, B321, 'STOCK IN TRANSFER'!F:F, "ADJUSTMENT (-)") - SUMIFS('STOCK IN TRANSFER'!G:G, 'STOCK IN TRANSFER'!E:E, B321, 'STOCK IN TRANSFER'!F:F, "STOCK TRANSFER") - SUMIFS(SALES!H:H, SALES!E:E, B321) -> 4
A322: NAX2930 | B322: NAX NAT-2930 TTC QDU SASH BLACK 1L | D322: LITER | E322: =SUMIFS('STOCK IN TRANSFER'!G:G, 'STOCK IN TRANSFER'!E:E, B322, 'STOCK IN TRANSFER'!F:F, "STOCK IN") + SUMIFS('STOCK IN TRANSFER'!G:G, 'STOCK IN TRANSFER'!E:E, B322, 'STOCK IN TRANSFER'!F:F, "ADJUSTMENT (+)") - SUMIFS('STOCK IN TRANSFER'!G:G, 'STOCK IN TRANSFER'!E:E, B322, 'STOCK IN TRANSFER'!F:F, "ADJUSTMENT (-)") - SUMIFS('STOCK IN TRANSFER'!G:G, 'STOCK IN TRANSFER'!E:E, B322, 'STOCK IN TRANSFER'!F:F, "STOCK TRANSFER") - SUMIFS(SALES!H:H, SALES!E:E, B322) -> 0
A323: NAT210 | B323: NAX NAT-210 TTC SUPER ORANGE 1L | C323: 1511 | D323: LITER | E323: =SUMIFS('STOCK IN TRANSFER'!G:G, 'STOCK IN TRANSFER'!E:E, B323, 'STOCK IN TRANSFER'!F:F, "STOCK IN") + SUMIFS('STOCK IN TRANSFER'!G:G, 'STOCK IN TRANSFER'!E:E, B323, 'STOCK IN TRANSFER'!F:F, "ADJUSTMENT (+)") - SUMIFS('STOCK IN TRANSFER'!G:G, 'STOCK IN TRANSFER'!E:E, B323, 'STOCK IN TRANSFER'!F:F, "ADJUSTMENT (-)") - SUMIFS('STOCK IN TRANSFER'!G:G, 'STOCK IN TRANSFER'!E:E, B323, 'STOCK IN TRANSFER'!F:F, "STOCK TRANSFER") - SUMIFS(SALES!H:H, SALES!E:E, B323) -> 6
A324: NAT100-1L | B324: NAX NAT-1OO TTC WHITE 1L | C324: 425 | D324: LITER | E324: =SUMIFS('STOCK IN TRANSFER'!G:G, 'STOCK IN TRANSFER'!E:E, B324, 'STOCK IN TRANSFER'!F:F, "STOCK IN") + SUMIFS('STOCK IN TRANSFER'!G:G, 'STOCK IN TRANSFER'!E:E, B324, 'STOCK IN TRANSFER'!F:F, "ADJUSTMENT (+)") - SUMIFS('STOCK IN TRANSFER'!G:G, 'STOCK IN TRANSFER'!E:E, B324, 'STOCK IN TRANSFER'!F:F, "ADJUSTMENT (-)") - SUMIFS('STOCK IN TRANSFER'!G:G, 'STOCK IN TRANSFER'!E:E, B324, 'STOCK IN TRANSFER'!F:F, "STOCK TRANSFER") - SUMIFS(SALES!H:H, SALES!E:E, B324) -> 0
A325: NAT196 | B325: NAX NAT-196 TTC PURPLISH RED 1L | C325: 1125 | D325: LITER | E325: =SUMIFS('STOCK IN TRANSFER'!G:G, 'STOCK IN TRANSFER'!E:E, B325, 'STOCK IN TRANSFER'!F:F, "STOCK IN") + SUMIFS('STOCK IN TRANSFER'!G:G, 'STOCK IN TRANSFER'!E:E, B325, 'STOCK IN TRANSFER'!F:F, "ADJUSTMENT (+)") - SUMIFS('STOCK IN TRANSFER'!G:G, 'STOCK IN TRANSFER'!E:E, B325, 'STOCK IN TRANSFER'!F:F, "ADJUSTMENT (-)") - SUMIFS('STOCK IN TRANSFER'!G:G, 'STOCK IN TRANSFER'!E:E, B325, 'STOCK IN TRANSFER'!F:F, "STOCK TRANSFER") - SUMIFS(SALES!H:H, SALES!E:E, B325) -> 14
A326: NAT192 | B326: NAX NAT-192 TTC BRIGHT RED 1L | C326: 540 | D326: LITER | E326: =SUMIFS('STOCK IN TRANSFER'!G:G, 'STOCK IN TRANSFER'!E:E, B326, 'STOCK IN TRANSFER'!F:F, "STOCK IN") + SUMIFS('STOCK IN TRANSFER'!G:G, 'STOCK IN TRANSFER'!E:E, B326, 'STOCK IN TRANSFER'!F:F, "ADJUSTMENT (+)") - SUMIFS('STOCK IN TRANSFER'!G:G, 'STOCK IN TRANSFER'!E:E, B326, 'STOCK IN TRANSFER'!F:F, "ADJUSTMENT (-)") - SUMIFS('STOCK IN TRANSFER'!G:G, 'STOCK IN TRANSFER'!E:E, B326, 'STOCK IN TRANSFER'!F:F, "STOCK TRANSFER") - SUMIFS(SALES!H:H, SALES!E:E, B326) -> 3
A327: NAT190 | B327: NAX NAT-190 TTC IRON RED 1L | C327: 395 | D327: LITER | E327: =SUMIFS('STOCK IN TRANSFER'!G:G, 'STOCK IN TRANSFER'!E:E, B327, 'STOCK IN TRANSFER'!F:F, "STOCK IN") + SUMIFS('STOCK IN TRANSFER'!G:G, 'STOCK IN TRANSFER'!E:E, B327, 'STOCK IN TRANSFER'!F:F, "ADJUSTMENT (+)") - SUMIFS('STOCK IN TRANSFER'!G:G, 'STOCK IN TRANSFER'!E:E, B327, 'STOCK IN TRANSFER'!F:F, "ADJUSTMENT (-)") - SUMIFS('STOCK IN TRANSFER'!G:G, 'STOCK IN TRANSFER'!E:E, B327, 'STOCK IN TRANSFER'!F:F, "STOCK TRANSFER") - SUMIFS(SALES!H:H, SALES!E:E, B327) -> 5
A328: NAT180 | B328: NAX NAT-180 TTC STRAWBERRY RED 1L | C328: 895 | D328: LITER | E328: =SUMIFS('STOCK IN TRANSFER'!G:G, 'STOCK IN TRANSFER'!E:E, B328, 'STOCK IN TRANSFER'!F:F, "STOCK IN") + SUMIFS('STOCK IN TRANSFER'!G:G, 'STOCK IN TRANSFER'!E:E, B328, 'STOCK IN TRANSFER'!F:F, "ADJUSTMENT (+)") - SUMIFS('STOCK IN TRANSFER'!G:G, 'STOCK IN TRANSFER'!E:E, B328, 'STOCK IN TRANSFER'!F:F, "ADJUSTMENT (-)") - SUMIFS('STOCK IN TRANSFER'!G:G, 'STOCK IN TRANSFER'!E:E, B328, 'STOCK IN TRANSFER'!F:F, "STOCK TRANSFER") - SUMIFS(SALES!H:H, SALES!E:E, B328) -> 6
A329: NAT158 | B329: NAX NAT158 CINQUASIA VIOLET 1L | C329: 1310 | D329: LITER | E329: =SUMIFS('STOCK IN TRANSFER'!G:G, 'STOCK IN TRANSFER'!E:E, B329, 'STOCK IN TRANSFER'!F:F, "STOCK IN") + SUMIFS('STOCK IN TRANSFER'!G:G, 'STOCK IN TRANSFER'!E:E, B329, 'STOCK IN TRANSFER'!F:F, "ADJUSTMENT (+)") - SUMIFS('STOCK IN TRANSFER'!G:G, 'STOCK IN TRANSFER'!E:E, B329, 'STOCK IN TRANSFER'!F:F, "ADJUSTMENT (-)") - SUMIFS('STOCK IN TRANSFER'!G:G, 'STOCK IN TRANSFER'!E:E, B329, 'STOCK IN TRANSFER'!F:F, "STOCK TRANSFER") - SUMIFS(SALES!H:H, SALES!E:E, B329) -> 2
A330: NAT149 | B330: NAX NAT-149 TTC DARK MAROON 1L | C330: 1110 | D330: LITER | E330: =SUMIFS('STOCK IN TRANSFER'!G:G, 'STOCK IN TRANSFER'!E:E, B330, 'STOCK IN TRANSFER'!F:F, "STOCK IN") + SUMIFS('STOCK IN TRANSFER'!G:G, 'STOCK IN TRANSFER'!E:E, B330, 'STOCK IN TRANSFER'!F:F, "ADJUSTMENT (+)") - SUMIFS('STOCK IN TRANSFER'!G:G, 'STOCK IN TRANSFER'!E:E, B330, 'STOCK IN TRANSFER'!F:F, "ADJUSTMENT (-)") - SUMIFS('STOCK IN TRANSFER'!G:G, 'STOCK IN TRANSFER'!E:E, B330, 'STOCK IN TRANSFER'!F:F, "STOCK TRANSFER") - SUMIFS(SALES!H:H, SALES!E:E, B330) -> 10
A331: NAT147 | B331: NAX NAT-147 TTC THRENE RED 1L | C331: 1120 | D331: LITER | E331: =SUMIFS('STOCK IN TRANSFER'!G:G, 'STOCK IN TRANSFER'!E:E, B331, 'STOCK IN TRANSFER'!F:F, "STOCK IN") + SUMIFS('STOCK IN TRANSFER'!G:G, 'STOCK IN TRANSFER'!E:E, B331, 'STOCK IN TRANSFER'!F:F, "ADJUSTMENT (+)") - SUMIFS('STOCK IN TRANSFER'!G:G, 'STOCK IN TRANSFER'!E:E, B331, 'STOCK IN TRANSFER'!F:F, "ADJUSTMENT (-)") - SUMIFS('STOCK IN TRANSFER'!G:G, 'STOCK IN TRANSFER'!E:E, B331, 'STOCK IN TRANSFER'!F:F, "STOCK TRANSFER") - SUMIFS(SALES!H:H, SALES!E:E, B331) -> 7
...

Sheet SALES
A1: DATE | B1: INVOICE NO. | C1: CUSTOMER'S NAME | D1: ITEM CODE | E1: DESCRIPTION | F1: COLOR CODE | G1: PAYMENT TYPE | H1: QTY | I1: UNIT | J1: UNIT PRICE | K1: TOTAL AMOUNT | L1: REMARKS
A2: 46113 | B2: SI-001253 | C2: RB CONSTRUCTION SUPPLY | D2: EXTREMEMIX-1L | E2: {=IF(D2="", "", XLOOKUP(D2, 'MASTER ITEM LIST'!A:A, 'MASTER ITEM LIST'!B:B, ""))} -> EXTREME QDU MIXING 1L | F2: EXTREME YELLOW | G2: CASH | H2: 3 | I2: {=IFERROR(XLOOKUP(D2,'MASTER ITEM LIST'!A:A,'MASTER ITEM LIST'!D:D), "")} -> LITER | J2: 750 | K2: =IF(H2="", "", H2*J2) -> 2250 | L2: PAID
A3: 46113 | B3: SI-001253 | C3: RB CONSTRUCTION SUPPLY | D3: PGJB-4L | E3: {=IF(D3="", "", XLOOKUP(D3, 'MASTER ITEM LIST'!A:A, 'MASTER ITEM LIST'!B:B, ""))} -> POLYGLOSS PU JET BLACK 4L | F3: REPACK | G3: CASH | H3: 0.125 | I3: {=IFERROR(XLOOKUP(D3,'MASTER ITEM LIST'!A:A,'MASTER ITEM LIST'!D:D), "")} -> GALON | J3: 3200 | K3: =IF(H3="", "", H3*J3) -> 400 | L3: PAID
A4: 46113 | B4: SI-001253 | C4: RB CONSTRUCTION SUPPLY | D4: NAX108 | E4: {=IF(D4="", "", XLOOKUP(D4, 'MASTER ITEM LIST'!A:A, 'MASTER ITEM LIST'!B:B, ""))} -> NAX 108 CERAMIC 2K CLEAR WITH HARDENER 1L | G4: CASH | H4: 3 | I4: {=IFERROR(XLOOKUP(D4,'MASTER ITEM LIST'!A:A,'MASTER ITEM LIST'!D:D), "")} -> LITER | J4: 700 | K4: =IF(H4="", "", H4*J4) -> 2100 | L4: PAID
A5: 46113 | B5: SI-001253 | C5: RB CONSTRUCTION SUPPLY | D5: DOITH-4L | E5: {=IF(D5="", "", XLOOKUP(D5, 'MASTER ITEM LIST'!A:A, 'MASTER ITEM LIST'!B:B, ""))} -> DO IT URETHANE THINNER 4L | G5: CASH | H5: 1.5 | I5: {=IFERROR(XLOOKUP(D5,'MASTER ITEM LIST'!A:A,'MASTER ITEM LIST'!D:D), "")} -> GAL/S | J5: 720 | K5: =IF(H5="", "", H5*J5) -> 1080 | L5: PAID
A6: 46113 | B6: SI-001253 | C6: RB CONSTRUCTION SUPPLY | D6: MSC | E6: {=IF(D6="", "", XLOOKUP(D6, 'MASTER ITEM LIST'!A:A, 'MASTER ITEM LIST'!B:B, ""))} -> OLD NEWS | G6: CASH | H6: 1 | I6: {=IFERROR(XLOOKUP(D6,'MASTER ITEM LIST'!A:A,'MASTER ITEM LIST'!D:D), "")} -> KG | J6: 100 | K6: =IF(H6="", "", H6*J6) -> 100 | L6: PAID
A7: 46113 | B7: SI-001252 | C7: JCK | D7: NXU1965-4L | E7: {=IF(D7="", "", XLOOKUP(D7, 'MASTER ITEM LIST'!A:A, 'MASTER ITEM LIST'!B:B, ""))} -> NIPPON EXTREME QDU BLACK 4L | F7: REPACK | G7: CASH | H7: 0.125 | I7: {=IFERROR(XLOOKUP(D7,'MASTER ITEM LIST'!A:A,'MASTER ITEM LIST'!D:D), "")} -> GAL | J7: 2800 | K7: =IF(H7="", "", H7*J7) -> 350 | L7: PAID
A8: 46113 | B8: SI-001252 | C8: JCK | D8: CRO-MT1/2 | E8: {=IF(D8="", "", XLOOKUP(D8, 'MASTER ITEM LIST'!A:A, 'MASTER ITEM LIST'!B:B, ""))} -> CROCO MASKING TAPE 1/2 12MM (1X96) | G8: CASH | H8: 3 | I8: {=IFERROR(XLOOKUP(D8,'MASTER ITEM LIST'!A:A,'MASTER ITEM LIST'!D:D), "")} -> PC/S | J8: 25 | K8: =IF(H8="", "", H8*J8) -> 75 | L8: PAID
A9: 46114 | B9: SI-001255 | C9: JEK | D9: NAX108 | E9: {=IF(D9="", "", XLOOKUP(D9, 'MASTER ITEM LIST'!A:A, 'MASTER ITEM LIST'!B:B, ""))} -> NAX 108 CERAMIC 2K CLEAR WITH HARDENER 1L | F9: REPACK | G9: CASH | H9: 0.5 | I9: {=IFERROR(XLOOKUP(D9,'MASTER ITEM LIST'!A:A,'MASTER ITEM LIST'!D:D), "")} -> LITER | J9: 740 | K9: =IF(H9="", "", H9*J9) -> 370 | L9: PAID
A10: 46114 | B10: SI-001254 | C10: BUKIDNON AUTOCARS | D10: NAT990-4L | E10: {=IF(D10="", "", XLOOKUP(D10, 'MASTER ITEM LIST'!A:A, 'MASTER ITEM LIST'!B:B, ""))} -> NAX NAT-990 TTC BLACK 4L | F10: REPACK | G10: CASH | H10: 0.5 | I10: {=IFERROR(XLOOKUP(D10,'MASTER ITEM LIST'!A:A,'MASTER ITEM LIST'!D:D), "")} -> GAL | J10: 4800 | K10: =IF(H10="", "", H10*J10) -> 2400 | L10: PAID
A11: 46118 | B11: SI-001256 | C11: WINDILL | D11: B1490-1L | E11: {=IF(D11="", "", XLOOKUP(D11, 'MASTER ITEM LIST'!A:A, 'MASTER ITEM LIST'!B:B, ""))} -> BOYSEN LTC LAMP BLACK 1L | G11: CASH | H11: 4 | I11: {=IFERROR(XLOOKUP(D11,'MASTER ITEM LIST'!A:A,'MASTER ITEM LIST'!D:D), "")} -> LITER | J11: 240 | K11: =IF(H11="", "", H11*J11) -> 960 | L11: PAID
A12: 46118 | B12: SI-001256 | C12: WINDILL | D12: RSW-4L | E12: {=IF(D12="", "", XLOOKUP(D12, 'MASTER ITEM LIST'!A:A, 'MASTER ITEM LIST'!B:B, ""))} -> RAIN OR SHINE WHITE 4L | G12: CASH | H12: 1 | I12: {=IFERROR(XLOOKUP(D12,'MASTER ITEM LIST'!A:A,'MASTER ITEM LIST'!D:D), "")} -> GALON | J12: 880 | K12: =IF(H12="", "", H12*J12) -> 880 | L12: PAID
A13: 46118 | B13: SI-001256 | C13: WINDILL | D13: 2B-#4 | E13: {=IF(D13="", "", XLOOKUP(D13, 'MASTER ITEM LIST'!A:A, 'MASTER ITEM LIST'!B:B, ""))} -> 2B PAINT ROLLER #4 | G13: CASH | H13: 2 | I13: {=IFERROR(XLOOKUP(D13,'MASTER ITEM LIST'!A:A,'MASTER ITEM LIST'!D:D), "")} -> PC/S | J13: 65 | K13: =IF(H13="", "", H13*J13) -> 130 | L13: PAID
A14: 46118 | B14: SI-001256 | C14: WINDILL | D14: 2B-#7 | E14: {=IF(D14="", "", XLOOKUP(D14, 'MASTER ITEM LIST'!A:A, 'MASTER ITEM LIST'!B:B, ""))} -> 2B PAINT ROLLER #7 | G14: CASH | H14: 1 | I14: {=IFERROR(XLOOKUP(D14,'MASTER ITEM LIST'!A:A,'MASTER ITEM LIST'!D:D), "")} -> PC/S | J14: 90 | K14: =IF(H14="", "", H14*J14) -> 90 | L14: PAID
A15: 46118 | B15: SI-001256 | C15: WINDILL | D15: EA120 | E15: {=IF(D15="", "", XLOOKUP(D15, 'MASTER ITEM LIST'!A:A, 'MASTER ITEM LIST'!B:B, ""))} -> EAGLE SANDPAPER #120 | G15: CASH | H15: 2 | I15: {=IFERROR(XLOOKUP(D15,'MASTER ITEM LIST'!A:A,'MASTER ITEM LIST'!D:D), "")} -> PC/S | J15: 25 | K15: =IF(H15="", "", H15*J15) -> 50 | L15: PAID
A16: 46118 | B16: SI-001256 | C16: WINDILL | D16: DPB-1 1/2 | E16: {=IF(D16="", "", XLOOKUP(D16, 'MASTER ITEM LIST'!A:A, 'MASTER ITEM LIST'!B:B, ""))} -> DRAGONFLY PAINT BRUSH #1 1/2 | G16: CASH | H16: 2 | I16: {=IFERROR(XLOOKUP(D16,'MASTER ITEM LIST'!A:A,'MASTER ITEM LIST'!D:D), "")} -> PC/S | J16: 40 | K16: =IF(H16="", "", H16*J16) -> 80 | L16: PAID
A17: 46118 | B17: SI-001256 | C17: WINDILL | D17: PUTTYKNI #4 | E17: {=IF(D17="", "", XLOOKUP(D17, 'MASTER ITEM LIST'!A:A, 'MASTER ITEM LIST'!B:B, ""))} -> JAPAN PUTTY KNIFE #4 | G17: CASH | H17: 2 | I17: {=IFERROR(XLOOKUP(D17,'MASTER ITEM LIST'!A:A,'MASTER ITEM LIST'!D:D), "")} -> PC/S | J17: 25 | K17: =IF(H17="", "", H17*J17) -> 50 | L17: PAID
A18: 46118 | B18: SI-001256 | C18: WINDILL | D18: EA120 | E18: {=IF(D18="", "", XLOOKUP(D18, 'MASTER ITEM LIST'!A:A, 'MASTER ITEM LIST'!B:B, ""))} -> EAGLE SANDPAPER #120 | G18: CASH | H18: 2 | I18: {=IFERROR(XLOOKUP(D18,'MASTER ITEM LIST'!A:A,'MASTER ITEM LIST'!D:D), "")} -> PC/S | J18: 25 | K18: =IF(H18="", "", H18*J18) -> 50 | L18: PAID
A19: 46118 | B19: SI-001256 | C19: WINDILL | D19: CRO-MT3/4 | E19: {=IF(D19="", "", XLOOKUP(D19, 'MASTER ITEM LIST'!A:A, 'MASTER ITEM LIST'!B:B, ""))} -> CROCO MASKING TAPE 3/4 18MM (1X64) | G19: CASH | H19: 2 | I19: {=IFERROR(XLOOKUP(D19,'MASTER ITEM LIST'!A:A,'MASTER ITEM LIST'!D:D), "")} -> PC/S | J19: 35 | K19: =IF(H19="", "", H19*J19) -> 70 | L19: PAID
A20: 46119 | B20: SI-001257 | C20: ALVIN | D20: NCGVARNISH-GAL | E20: {=IF(D20="", "", XLOOKUP(D20, 'MASTER ITEM LIST'!A:A, 'MASTER ITEM LIST'!B:B, ""))} -> NIPPON CLEAR GLOSS VARNISH GAL | G20: CASH | H20: 1 | I20: {=IFERROR(XLOOKUP(D20,'MASTER ITEM LIST'!A:A,'MASTER ITEM LIST'!D:D), "")} -> GAL | J20: 1800 | K20: =IF(H20="", "", H20*J20) -> 1800 | L20: PAID
A21: 46120 | B21: SI-001261 | C21: JUNDAPS | D21: CRO-MT3/4 | E21: {=IF(D21="", "", XLOOKUP(D21, 'MASTER ITEM LIST'!A:A, 'MASTER ITEM LIST'!B:B, ""))} -> CROCO MASKING TAPE 3/4 18MM (1X64) | G21: CASH | H21: 2 | I21: {=IFERROR(XLOOKUP(D21,'MASTER ITEM LIST'!A:A,'MASTER ITEM LIST'!D:D), "")} -> PC/S | J21: 35 | K21: =IF(H21="", "", H21*J21) -> 70 | L21: PAID
A22: 46120 | B22: SI-001261 | C22: JUNDAPS | D22: TOBF-4L | E22: {=IF(D22="", "", XLOOKUP(D22, 'MASTER ITEM LIST'!A:A, 'MASTER ITEM LIST'!B:B, ""))} -> TIMEOUT BODY FILLER WITH HARDENER 4L | G22: CASH | H22: 1 | I22: {=IFERROR(XLOOKUP(D22,'MASTER ITEM LIST'!A:A,'MASTER ITEM LIST'!D:D), "")} -> GAL | J22: 710 | K22: =IF(H22="", "", H22*J22) -> 710 | L22: PAID
A23: 46120 | B23: SI-001261 | C23: JUNDAPS | D23: NAX141 | E23: {=IF(D23="", "", XLOOKUP(D23, 'MASTER ITEM LIST'!A:A, 'MASTER ITEM LIST'!B:B, ""))} -> NAX 141 NAX MAXIMA URETHANE FD CLEAR WITH HARDENER 1L | G23: CASH | H23: 4 | I23: {=IFERROR(XLOOKUP(D23,'MASTER ITEM LIST'!A:A,'MASTER ITEM LIST'!D:D), "")} -> LITER | J23: 580 | K23: =IF(H23="", "", H23*J23) -> 2320 | L23: PAID
A24: 46120 | B24: SI-001261 | C24: JUNDAPS | D24: NAXQDUMIX-1L | E24: {=IF(D24="", "", XLOOKUP(D24, 'MASTER ITEM LIST'!A:A, 'MASTER ITEM LIST'!B:B, ""))} -> NAX QDU MIX 1L | F24: QDU BLUE | G24: CASH | H24: 2 | I24: {=IFERROR(XLOOKUP(D24,'MASTER ITEM LIST'!A:A,'MASTER ITEM LIST'!D:D), "")} -> LITER | J24: 800 | K24: =IF(H24="", "", H24*J24) -> 1600 | L24: PAID
A25: 46120 | B25: SI-001261 | C25: JUNDAPS | D25: NAXQDUMIX-1L | E25: {=IF(D25="", "", XLOOKUP(D25, 'MASTER ITEM LIST'!A:A, 'MASTER ITEM LIST'!B:B, ""))} -> NAX QDU MIX 1L | F25: QDU YELLOW | G25: CASH | H25: 1 | I25: {=IFERROR(XLOOKUP(D25,'MASTER ITEM LIST'!A:A,'MASTER ITEM LIST'!D:D), "")} -> LITER | J25: 700 | K25: =IF(H25="", "", H25*J25) -> 700 | L25: PAID
A26: 46120 | B26: SI-001261 | C26: JUNDAPS | D26: NAXQDUMIX-1L | E26: {=IF(D26="", "", XLOOKUP(D26, 'MASTER ITEM LIST'!A:A, 'MASTER ITEM LIST'!B:B, ""))} -> NAX QDU MIX 1L | F26: QDU GREEN | G26: CASH | H26: 0.25 | I26: {=IFERROR(XLOOKUP(D26,'MASTER ITEM LIST'!A:A,'MASTER ITEM LIST'!D:D), "")} -> LITER | J26: 800 | K26: =IF(H26="", "", H26*J26) -> 200 | L26: PAID
A27: 46120 | B27: SI-001260 | C27: JUNDAPS | D27: EA100 | E27: {=IF(D27="", "", XLOOKUP(D27, 'MASTER ITEM LIST'!A:A, 'MASTER ITEM LIST'!B:B, ""))} -> SAND PAPER #100 | G27: CASH | H27: 3 | I27: {=IFERROR(XLOOKUP(D27,'MASTER ITEM LIST'!A:A,'MASTER ITEM LIST'!D:D), "")} -> PC/S | J27: 40 | K27: =IF(H27="", "", H27*J27) -> 120 | L27: PAID
A28: 46120 | B28: SI-001260 | C28: JUNDAPS | D28: EA120 | E28: {=IF(D28="", "", XLOOKUP(D28, 'MASTER ITEM LIST'!A:A, 'MASTER ITEM LIST'!B:B, ""))} -> EAGLE SANDPAPER #120 | G28: CASH | H28: 3 | I28: {=IFERROR(XLOOKUP(D28,'MASTER ITEM LIST'!A:A,'MASTER ITEM LIST'!D:D), "")} -> PC/S | J28: 25 | K28: =IF(H28="", "", H28*J28) -> 75 | L28: PAID
A29: 46120 | B29: SI-001260 | C29: JUNDAPS | D29: ea1500 | E29: {=IF(D29="", "", XLOOKUP(D29, 'MASTER ITEM LIST'!A:A, 'MASTER ITEM LIST'!B:B, ""))} -> EAGLE SANDPAPER #1500 | G29: CASH | H29: 1 | I29: {=IFERROR(XLOOKUP(D29,'MASTER ITEM LIST'!A:A,'MASTER ITEM LIST'!D:D), "")} -> PC/S | J29: 35 | K29: =IF(H29="", "", H29*J29) -> 35 | L29: PAID
A30: 46120 | B30: SI-001260 | C30: JUNDAPS | D30: EA2000 | E30: {=IF(D30="", "", XLOOKUP(D30, 'MASTER ITEM LIST'!A:A, 'MASTER ITEM LIST'!B:B, ""))} -> EAGLE SANDPAPER #2000 | G30: CASH | H30: 1 | I30: {=IFERROR(XLOOKUP(D30,'MASTER ITEM LIST'!A:A,'MASTER ITEM LIST'!D:D), "")} -> PC/S | J30: 35 | K30: =IF(H30="", "", H30*J30) -> 35 | L30: PAID
A31: 46120 | B31: SI-001260 | C31: JUNDAPS | D31: MSC | E31: {=IF(D31="", "", XLOOKUP(D31, 'MASTER ITEM LIST'!A:A, 'MASTER ITEM LIST'!B:B, ""))} -> OLD NEWS | G31: CASH | H31: 1 | I31: {=IFERROR(XLOOKUP(D31,'MASTER ITEM LIST'!A:A,'MASTER ITEM LIST'!D:D), "")} -> KG | J31: 100 | K31: =IF(H31="", "", H31*J31) -> 100 | L31: PAID
A32: 46120 | B32: SI-001260 | C32: JUNDAPS | D32: DOITH-4L | E32: {=IF(D32="", "", XLOOKUP(D32, 'MASTER ITEM LIST'!A:A, 'MASTER ITEM LIST'!B:B, ""))} -> DO IT URETHANE THINNER 4L | G32: CASH | H32: 2 | I32: {=IFERROR(XLOOKUP(D32,'MASTER ITEM LIST'!A:A,'MASTER ITEM LIST'!D:D), "")} -> GAL/S | J32: 710 | K32: =IF(H32="", "", H32*J32) -> 1420 | L32: PAID
A33: 46120 | B33: SI-001258 | C33: ELECTROKIM | D33: NP9200 | E33: {=IF(D33="", "", XLOOKUP(D33, 'MASTER ITEM LIST'!A:A, 'MASTER ITEM LIST'!B:B, ""))} -> NAX PREMILA NP9200 2K CLEAR WITH HARDENER 1L | G33: CASH | H33: 1 | I33: {=IFERROR(XLOOKUP(D33,'MASTER ITEM LIST'!A:A,'MASTER ITEM LIST'!D:D), "")} -> LITER | J33: 1350 | K33: =IF(H33="", "", H33*J33) -> 1350 | L33: PAID
A34: 46120 | B34: SI-001259 | C34: APARESE | D34: PREMILAMIX-1L | E34: {=IF(D34="", "", XLOOKUP(D34, 'MASTER ITEM LIST'!A:A, 'MASTER ITEM LIST'!B:B, ""))} -> PREMILA MIXING 1L | F34: CODE: U25 SILVER | G34: CASH | H34: 0.2 | I34: {=IFERROR(XLOOKUP(D34,'MASTER ITEM LIST'!A:A,'MASTER ITEM LIST'!D:D), "")} -> LITER | J34: 2400 | K34: =IF(H34="", "", H34*J34) -> 480 | L34: PAID
A35: 46121 | B35: SI-001262 | C35: BUKIDNON AUTOCARS | D35: NAX108 | E35: {=IF(D35="", "", XLOOKUP(D35, 'MASTER ITEM LIST'!A:A, 'MASTER ITEM LIST'!B:B, ""))} -> NAX 108 CERAMIC 2K CLEAR WITH HARDENER 1L | G35: CASH | H35: 12 | I35: {=IFERROR(XLOOKUP(D35,'MASTER ITEM LIST'!A:A,'MASTER ITEM LIST'!D:D), "")} -> LITER | J35: 680 | K35: =IF(H35="", "", H35*J35) -> 8160 | L35: PAID
A36: 46121 | B36: SI-001262 | C36: BUKIDNON AUTOCARS | D36: PRI3634 | E36: {=IF(D36="", "", XLOOKUP(D36, 'MASTER ITEM LIST'!A:A, 'MASTER ITEM LIST'!B:B, ""))} -> NAX ALPHA HB SPRAY FILLER GRAY WITH HARDENER 1L | G36: CASH | H36: 12 | I36: {=IFERROR(XLOOKUP(D36,'MASTER ITEM LIST'!A:A,'MASTER ITEM LIST'!D:D), "")} -> LITER | J36: 580 | K36: =IF(H36="", "", H36*J36) -> 6960 | L36: PAID
A37: 46121 | B37: SI-001262 | C37: BUKIDNON AUTOCARS | D37: PGJB-4L | E37: {=IF(D37="", "", XLOOKUP(D37, 'MASTER ITEM LIST'!A:A, 'MASTER ITEM LIST'!B:B, ""))} -> POLYGLOSS PU JET BLACK 4L | G37: CASH | H37: 1 | I37: {=IFERROR(XLOOKUP(D37,'MASTER ITEM LIST'!A:A,'MASTER ITEM LIST'!D:D), "")} -> GALON | J37: 2600 | K37: =IF(H37="", "", H37*J37) -> 2600 | L37: PAID
A38: 46121 | B38: SI-001262 | C38: BUKIDNON AUTOCARS | D38: PGW-4L | E38: {=IF(D38="", "", XLOOKUP(D38, 'MASTER ITEM LIST'!A:A, 'MASTER ITEM LIST'!B:B, ""))} -> POLYGLOSS PU WHITE 4L | G38: CASH | H38: 1 | I38: {=IFERROR(XLOOKUP(D38,'MASTER ITEM LIST'!A:A,'MASTER ITEM LIST'!D:D), "")} -> GALON | J38: 2400 | K38: =IF(H38="", "", H38*J38) -> 2400 | L38: PAID
A39: 46121 | B39: SI-001262 | C39: BUKIDNON AUTOCARS | D39: DOMBF-4L | E39: {=IF(D39="", "", XLOOKUP(D39, 'MASTER ITEM LIST'!A:A, 'MASTER ITEM LIST'!B:B, ""))} -> DOMINO BODY FILTER WITH HARDENER 4L | G39: CASH | H39: 3 | I39: {=IFERROR(XLOOKUP(D39,'MASTER ITEM LIST'!A:A,'MASTER ITEM LIST'!D:D), "")} -> GAL | J39: 615 | K39: =IF(H39="", "", H39*J39) -> 1845 | L39: PAID
A40: 46121 | B40: SI-001263 | C40: BUKIDNON AUTOCARS | D40: POLYGTHIN-4L | E40: {=IF(D40="", "", XLOOKUP(D40, 'MASTER ITEM LIST'!A:A, 'MASTER ITEM LIST'!B:B, ""))} -> POLYGLOSS URETHANE THINNER 4L | G40: CASH | H40: 6 | I40: {=IFERROR(XLOOKUP(D40,'MASTER ITEM LIST'!A:A,'MASTER ITEM LIST'!D:D), "")} -> GALON | J40: 800 | K40: =IF(H40="", "", H40*J40) -> 4800 | L40: PAID
A41: 46122 | B41: SI-001265 | C41: RITCHIE NATHALIE | D41: DPB-4 | E41: {=IF(D41="", "", XLOOKUP(D41, 'MASTER ITEM LIST'!A:A, 'MASTER ITEM LIST'!B:B, ""))} -> DRAGONFLY PAINT BRUSH #4 | G41: CASH | H41: 3 | I41: {=IFERROR(XLOOKUP(D41,'MASTER ITEM LIST'!A:A,'MASTER ITEM LIST'!D:D), "")} -> PC/S | J41: 120 | K41: =IF(H41="", "", H41*J41) -> 360 | L41: PAID
A42: 46122 | B42: SI-001264 | C42: RONEL | D42: NAXQDUMIX-1L | E42: {=IF(D42="", "", XLOOKUP(D42, 'MASTER ITEM LIST'!A:A, 'MASTER ITEM LIST'!B:B, ""))} -> NAX QDU MIX 1L | F42: QDU ORANGE | G42: CASH | H42: 0.5 | I42: {=IFERROR(XLOOKUP(D42,'MASTER ITEM LIST'!A:A,'MASTER ITEM LIST'!D:D), "")} -> LITER | J42: 760 | K42: =IF(H42="", "", H42*J42) -> 380 | L42: PAID
A43: 46123 | B43: SI-001267 | C43: RONIE | D43: UNOLT-4L | E43: {=IF(D43="", "", XLOOKUP(D43, 'MASTER ITEM LIST'!A:A, 'MASTER ITEM LIST'!B:B, ""))} -> UNO LACQUER THINNER 4L | F43: REPACK | G43: CASH | H43: 0.5 | I43: {=IFERROR(XLOOKUP(D43,'MASTER ITEM LIST'!A:A,'MASTER ITEM LIST'!D:D), "")} -> GAL/S | J43: 600 | K43: =IF(H43="", "", H43*J43) -> 300 | L43: PAID
A44: 46123 | B44: SI-001266 | C44: ZYNERGIA | D44: EA120 | E44: {=IF(D44="", "", XLOOKUP(D44, 'MASTER ITEM LIST'!A:A, 'MASTER ITEM LIST'!B:B, ""))} -> EAGLE SANDPAPER #120 | G44: CASH | H44: 20 | I44: {=IFERROR(XLOOKUP(D44,'MASTER ITEM LIST'!A:A,'MASTER ITEM LIST'!D:D), "")} -> PC/S | J44: 25 | K44: =IF(H44="", "", H44*J44) -> 500 | L44: PAID
A45: 46126 | B45: SI-001270 | C45: APARESE | D45: PREMILAMIX-1L | E45: {=IF(D45="", "", XLOOKUP(D45, 'MASTER ITEM LIST'!A:A, 'MASTER ITEM LIST'!B:B, ""))} -> PREMILA MIXING 1L | F45: CODE: 6W4 | G45: CASH | H45: 0.2 | I45: {=IFERROR(XLOOKUP(D45,'MASTER ITEM LIST'!A:A,'MASTER ITEM LIST'!D:D), "")} -> LITER | J45: 2600 | K45: =IF(H45="", "", H45*J45) -> 520 | L45: PAID
A46: 46126 | B46: SI-001269 | C46: APARESE | D46: PREMILAMIX-1L | E46: {=IF(D46="", "", XLOOKUP(D46, 'MASTER ITEM LIST'!A:A, 'MASTER ITEM LIST'!B:B, ""))} -> PREMILA MIXING 1L | F46: CODE: W54 PEARL | G46: CASH | H46: 0.3 | I46: {=IFERROR(XLOOKUP(D46,'MASTER ITEM LIST'!A:A,'MASTER ITEM LIST'!D:D), "")} -> LITER | J46: 2600 | K46: =IF(H46="", "", H46*J46) -> 780 | L46: PAID
A47: 46126 | B47: SI-001269 | C47: APARESE | D47: PREMILAMIX-1L | E47: {=IF(D47="", "", XLOOKUP(D47, 'MASTER ITEM LIST'!A:A, 'MASTER ITEM LIST'!B:B, ""))} -> PREMILA MIXING 1L | F47: CODE: W54 WHITE | G47: CASH | H47: 0.3 | I47: {=IFERROR(XLOOKUP(D47,'MASTER ITEM LIST'!A:A,'MASTER ITEM LIST'!D:D), "")} -> LITER | J47: 1900 | K47: =IF(H47="", "", H47*J47) -> 570 | L47: PAID
A48: 46126 | B48: SI-001269 | C48: APARESE | D48: NAT100-4L | E48: {=IF(D48="", "", XLOOKUP(D48, 'MASTER ITEM LIST'!A:A, 'MASTER ITEM LIST'!B:B, ""))} -> NAX NAT-100 TTC WHITE 4L | F48: REPACK | G48: CASH | H48: 0.0625 | I48: {=IFERROR(XLOOKUP(D48,'MASTER ITEM LIST'!A:A,'MASTER ITEM LIST'!D:D), "")} -> GAL | J48: 2880 | K48: =IF(H48="", "", H48*J48) -> 180 | L48: PAID
A49: 46126 | B49: SI-001269 | C49: APARESE | D49: DOITH-4L | E49: {=IF(D49="", "", XLOOKUP(D49, 'MASTER ITEM LIST'!A:A, 'MASTER ITEM LIST'!B:B, ""))} -> DO IT URETHANE THINNER 4L | G49: CASH | H49: 2 | I49: {=IFERROR(XLOOKUP(D49,'MASTER ITEM LIST'!A:A,'MASTER ITEM LIST'!D:D), "")} -> GAL/S | J49: 700 | K49: =IF(H49="", "", H49*J49) -> 1400 | L49: PAID
A50: 46126 | B50: SI-001268 | C50: TABANAN | D50: CUMIFS-60 | E50: {=IF(D50="", "", XLOOKUP(D50, 'MASTER ITEM LIST'!A:A, 'MASTER ITEM LIST'!B:B, ""))} -> CUMI SUPREME FLOOR SANDING 60 | G50: CASH | H50: 1 | I50: {=IFERROR(XLOOKUP(D50,'MASTER ITEM LIST'!A:A,'MASTER ITEM LIST'!D:D), "")} -> FT | J50: 95 | K50: =IF(H50="", "", H50*J50) -> 95 | L50: PAID
A51: 46126 | B51: SI-001268 | C51: TABANAN | D51: PREMILAMIX-1L | E51: {=IF(D51="", "", XLOOKUP(D51, 'MASTER ITEM LIST'!A:A, 'MASTER ITEM LIST'!B:B, ""))} -> PREMILA MIXING 1L | F51: CODE: 3T6 RED | G51: CASH | H51: 0.125 | I51: {=IFERROR(XLOOKUP(D51,'MASTER ITEM LIST'!A:A,'MASTER ITEM LIST'!D:D), "")} -> LITER | J51: 2880 | K51: =IF(H51="", "", H51*J51) -> 360 | L51: PAID
A52: 46128 | B52: SI-001272 | C52: BUKIDNON AUTOCARS | D52: EA1200 | E52: {=IF(D52="", "", XLOOKUP(D52, 'MASTER ITEM LIST'!A:A, 'MASTER ITEM LIST'!B:B, ""))} -> EAGLE SANDPAPER #1200 | G52: CASH | H52: 5 | I52: {=IFERROR(XLOOKUP(D52,'MASTER ITEM LIST'!A:A,'MASTER ITEM LIST'!D:D), "")} -> PC/S | J52: 25 | K52: =IF(H52="", "", H52*J52) -> 125 | L52: PAID
A53: 46128 | B53: SI-001271 | C53: CMU | D53: PLQDB-4L | E53: {=IF(D53="", "", XLOOKUP(D53, 'MASTER ITEM LIST'!A:A, 'MASTER ITEM LIST'!B:B, ""))} -> PLATONE QDE BLACK 4L | F53: REPACK | G53: CASH | H53: 0.25 | I53: {=IFERROR(XLOOKUP(D53,'MASTER ITEM LIST'!A:A,'MASTER ITEM LIST'!D:D), "")} -> GAL | J53: 920 | K53: =IF(H53="", "", H53*J53) -> 230 | L53: PAID
A54: 46129 | B54: SI-001277 | C54: JENNIE | D54: PLYZGBLK-48 | E54: {=IF(D54="", "", XLOOKUP(D54, 'MASTER ITEM LIST'!A:A, 'MASTER ITEM LIST'!B:B, ""))} -> PYLOX LAZER GLOSS BLACK 48 | G54: CASH | H54: 1 | I54: {=IFERROR(XLOOKUP(D54,'MASTER ITEM LIST'!A:A,'MASTER ITEM LIST'!D:D), "")} -> CAN | J54: 140 | K54: =IF(H54="", "", H54*J54) -> 140 | L54: PAID
A55: 46129 | B55: SI-001277 | C55: JENNIE | D55: EA120 | E55: {=IF(D55="", "", XLOOKUP(D55, 'MASTER ITEM LIST'!A:A, 'MASTER ITEM LIST'!B:B, ""))} -> EAGLE SANDPAPER #120 | G55: CASH | H55: 1 | I55: {=IFERROR(XLOOKUP(D55,'MASTER ITEM LIST'!A:A,'MASTER ITEM LIST'!D:D), "")} -> PC/S | J55: 40 | K55: =IF(H55="", "", H55*J55) -> 40 | L55: PAID
A56: 46129 | B56: SI-001276 | C56: DC GARRAGE | D56: NAXQDUMIX-1L | E56: {=IF(D56="", "", XLOOKUP(D56, 'MASTER ITEM LIST'!A:A, 'MASTER ITEM LIST'!B:B, ""))} -> NAX QDU MIX 1L | F56: NAX SILVER | G56: CASH | H56: 0.5 | I56: {=IFERROR(XLOOKUP(D56,'MASTER ITEM LIST'!A:A,'MASTER ITEM LIST'!D:D), "")} -> LITER | J56: 1000 | K56: =IF(H56="", "", H56*J56) -> 500 | L56: PAID
A57: 46129 | B57: SI-001276 | C57: DC GARRAGE | D57: NAT990-4L | E57: {=IF(D57="", "", XLOOKUP(D57, 'MASTER ITEM LIST'!A:A, 'MASTER ITEM LIST'!B:B, ""))} -> NAX NAT-990 TTC BLACK 4L | G57: CASH | H57: 0.125 | I57: {=IFERROR(XLOOKUP(D57,'MASTER ITEM LIST'!A:A,'MASTER ITEM LIST'!D:D), "")} -> GAL | J57: 4000 | K57: =IF(H57="", "", H57*J57) -> 500 | L57: PAID
A58: 46129 | B58: SI-001275 | C58: BUKIDNON AUTOCARS | D58: MSC | E58: {=IF(D58="", "", XLOOKUP(D58, 'MASTER ITEM LIST'!A:A, 'MASTER ITEM LIST'!B:B, ""))} -> OLD NEWS | G58: CASH | H58: 2 | I58: {=IFERROR(XLOOKUP(D58,'MASTER ITEM LIST'!A:A,'MASTER ITEM LIST'!D:D), "")} -> KG | J58: 100 | K58: =IF(H58="", "", H58*J58) -> 200 | L58: PAID
A59: 46129 | B59: SI-001274 | C59: HAROLD | D59: LATEXMIX-1L | E59: {=IF(D59="", "", XLOOKUP(D59, 'MASTER ITEM LIST'!A:A, 'MASTER ITEM LIST'!B:B, ""))} -> LATEX NP, ALPHA CHROMA, DAVIES, BOYSEN, WC 1L | F59: LATEX GREEN | G59: CASH | H59: 0.25 | I59: {=IFERROR(XLOOKUP(D59,'MASTER ITEM LIST'!A:A,'MASTER ITEM LIST'!D:D), "")} -> LITER | J59: 340 | K59: =IF(H59="", "", H59*J59) -> 85 | L59: PAID
A60: 46129 | B60: SI-001274 | C60: HAROLD | D60: LATEXMIX-1L | E60: {=IF(D60="", "", XLOOKUP(D60, 'MASTER ITEM LIST'!A:A, 'MASTER ITEM LIST'!B:B, ""))} -> LATEX NP, ALPHA CHROMA, DAVIES, BOYSEN, WC 1L | F60: LATEX YELLOW | G60: CASH | H60: 0.25 | I60: {=IFERROR(XLOOKUP(D60,'MASTER ITEM LIST'!A:A,'MASTER ITEM LIST'!D:D), "")} -> LITER | J60: 340 | K60: =IF(H60="", "", H60*J60) -> 85 | L60: PAID
A61: 46129 | B61: SI-001274 | C61: HAROLD | D61: 2B-PB#1 | E61: {=IF(D61="", "", XLOOKUP(D61, 'MASTER ITEM LIST'!A:A, 'MASTER ITEM LIST'!B:B, ""))} -> PAINT BRUSH 2B #1 | G61: CASH | H61: 2 | I61: {=IFERROR(XLOOKUP(D61,'MASTER ITEM LIST'!A:A,'MASTER ITEM LIST'!D:D), "")} -> PC/S | J61: 25 | K61: =IF(H61="", "", H61*J61) -> 50 | L61: PAID
A62: 46129 | B62: SI-001273 | C62: RUBIE | D62: EPOXYTHNR-4L | E62: {=IF(D62="", "", XLOOKUP(D62, 'MASTER ITEM LIST'!A:A, 'MASTER ITEM LIST'!B:B, ""))} -> NIPPON EPOXY THINNER 4L | G62: CASH | H62: 0.5 | I62: {=IFERROR(XLOOKUP(D62,'MASTER ITEM LIST'!A:A,'MASTER ITEM LIST'!D:D), "")} -> GAL/S | J62: 720 | K62: =IF(H62="", "", H62*J62) -> 360 | L62: PAID
A63: 46130 | B63: SI-001280 | C63: ESTRADA | D63: HS-1L | E63: {=IF(D63="", "", XLOOKUP(D63, 'MASTER ITEM LIST'!A:A, 'MASTER ITEM LIST'!B:B, ""))} -> NIPPON HS FILLER 1L | G63: CASH | H63: 1 | I63: {=IFERROR(XLOOKUP(D63,'MASTER ITEM LIST'!A:A,'MASTER ITEM LIST'!D:D), "")} -> LITER | J63: 800 | K63: =IF(H63="", "", H63*J63) -> 800 | L63: PAID
A64: 46130 | B64: SI-001279 | C64: ESTRADA | D64: NAXQDUMIX-1L | E64: {=IF(D64="", "", XLOOKUP(D64, 'MASTER ITEM LIST'!A:A, 'MASTER ITEM LIST'!B:B, ""))} -> NAX QDU MIX 1L | F64: NAX QDU BEIGE | G64: CASH | H64: 2 | I64: {=IFERROR(XLOOKUP(D64,'MASTER ITEM LIST'!A:A,'MASTER ITEM LIST'!D:D), "")} -> LITER | J64: 1500 | K64: =IF(H64="", "", H64*J64) -> 3000 | L64: PAID
A65: 46130 | B65: SI-001278 | C65: ESTRADA | D65: NAX21 | E65: {=IF(D65="", "", XLOOKUP(D65, 'MASTER ITEM LIST'!A:A, 'MASTER ITEM LIST'!B:B, ""))} -> NAX NAX21 URETHANE HAEDENER | G65: CASH | H65: 2 | I65: {=IFERROR(XLOOKUP(D65,'MASTER ITEM LIST'!A:A,'MASTER ITEM LIST'!D:D), "")} -> CANS | J65: 240 | K65: =IF(H65="", "", H65*J65) -> 480 | L65: PAID
A66: 46130 | B66: SI-001278 | C66: ESTRADA | D66: NP9700 | E66: {=IF(D66="", "", XLOOKUP(D66, 'MASTER ITEM LIST'!A:A, 'MASTER ITEM LIST'!B:B, ""))} -> NAX PREMILA NP9700 HS 2K CLEAR WITH HARDENER 1L | G66: CASH | H66: 2 | I66: {=IFERROR(XLOOKUP(D66,'MASTER ITEM LIST'!A:A,'MASTER ITEM LIST'!D:D), "")} -> LITER | J66: 1550 | K66: =IF(H66="", "", H66*J66) -> 3100 | L66: PAID
A67: 46130 | B67: SI-001278 | C67: ESTRADA | D67: CRO-MT3/4 | E67: {=IF(D67="", "", XLOOKUP(D67, 'MASTER ITEM LIST'!A:A, 'MASTER ITEM LIST'!B:B, ""))} -> CROCO MASKING TAPE 3/4 18MM (1X64) | G67: CASH | H67: 5 | I67: {=IFERROR(XLOOKUP(D67,'MASTER ITEM LIST'!A:A,'MASTER ITEM LIST'!D:D), "")} -> PC/S | J67: 35 | K67: =IF(H67="", "", H67*J67) -> 175 | L67: PAID
A68: 46130 | B68: SI-001278 | C68: ESTRADA | D68: EA100 | E68: {=IF(D68="", "", XLOOKUP(D68, 'MASTER ITEM LIST'!A:A, 'MASTER ITEM LIST'!B:B, ""))} -> SAND PAPER #100 | G68: CASH | H68: 2 | I68: {=IFERROR(XLOOKUP(D68,'MASTER ITEM LIST'!A:A,'MASTER ITEM LIST'!D:D), "")} -> PC/S | J68: 40 | K68: =IF(H68="", "", H68*J68) -> 80 | L68: PAID
A69: 46130 | B69: SI-001278 | C69: ESTRADA | D69: EA320 | E69: {=IF(D69="", "", XLOOKUP(D69, 'MASTER ITEM LIST'!A:A, 'MASTER ITEM LIST'!B:B, ""))} -> EAGLE SAND PAPER #320 | G69: CASH | H69: 5 | I69: {=IFERROR(XLOOKUP(D69,'MASTER ITEM LIST'!A:A,'MASTER ITEM LIST'!D:D), "")} -> PCS | J69: 25 | K69: =IF(H69="", "", H69*J69) -> 125 | L69: PAID
A70: 46130 | B70: SI-001278 | C70: ESTRADA | D70: EA600 | E70: {=IF(D70="", "", XLOOKUP(D70, 'MASTER ITEM LIST'!A:A, 'MASTER ITEM LIST'!B:B, ""))} -> EAGLE SANDPAPER #600 | G70: CASH | H70: 5 | I70: {=IFERROR(XLOOKUP(D70,'MASTER ITEM LIST'!A:A,'MASTER ITEM LIST'!D:D), "")} -> PCS | J70: 25 | K70: =IF(H70="", "", H70*J70) -> 125 | L70: PAID
A71: 46130 | B71: SI-001278 | C71: ESTRADA | D71: MSC | E71: {=IF(D71="", "", XLOOKUP(D71, 'MASTER ITEM LIST'!A:A, 'MASTER ITEM LIST'!B:B, ""))} -> OLD NEWS | G71: CASH | H71: 0.5 | I71: {=IFERROR(XLOOKUP(D71,'MASTER ITEM LIST'!A:A,'MASTER ITEM LIST'!D:D), "")} -> KG | J71: 100 | K71: =IF(H71="", "", H71*J71) -> 50 | L71: PAID
A72: 46132 | B72: SI-001283 | C72: VANITY | D72: PLYZGBLK-48 | E72: {=IF(D72="", "", XLOOKUP(D72, 'MASTER ITEM LIST'!A:A, 'MASTER ITEM LIST'!B:B, ""))} -> PYLOX LAZER GLOSS BLACK 48 | G72: CASH | H72: 1 | I72: {=IFERROR(XLOOKUP(D72,'MASTER ITEM LIST'!A:A,'MASTER ITEM LIST'!D:D), "")} -> CAN | J72: 145 | K72: =IF(H72="", "", H72*J72) -> 145 | L72: PAID
A73: 46132 | B73: SI-001282 | C73: HAROLD | D73: LATEXMIX-1L | E73: {=IF(D73="", "", XLOOKUP(D73, 'MASTER ITEM LIST'!A:A, 'MASTER ITEM LIST'!B:B, ""))} -> LATEX NP, ALPHA CHROMA, DAVIES, BOYSEN, WC 1L | F73: REPACK | G73: CASH | H73: 0.25 | I73: {=IFERROR(XLOOKUP(D73,'MASTER ITEM LIST'!A:A,'MASTER ITEM LIST'!D:D), "")} -> LITER | J73: 280 | K73: =IF(H73="", "", H73*J73) -> 70 | L73: PAID
A74: 46132 | B74: SI-001281 | C74: JULIET TON | D74: DCSG715-5L | E74: {=IF(D74="", "", XLOOKUP(D74, 'MASTER ITEM LIST'!A:A, 'MASTER ITEM LIST'!B:B, ""))} -> NIPPON DOU CLASSIC SG 715 WHITE 5L | G74: CASH | H74: 1 | I74: {=IFERROR(XLOOKUP(D74,'MASTER ITEM LIST'!A:A,'MASTER ITEM LIST'!D:D), "")} -> GAL | J74: 1100 | K74: =IF(H74="", "", H74*J74) -> 1100 | L74: PAID
A75: 46133 | B75: SI-001285 | C75: BORDZ | D75: ROS-629-4L | E75: {=IF(D75="", "", XLOOKUP(D75, 'MASTER ITEM LIST'!A:A, 'MASTER ITEM LIST'!B:B, ""))} -> RAIN OR SHINE ROS-629 TULIPS 4L | G75: CASH | H75: 1 | I75: {=IFERROR(XLOOKUP(D75,'MASTER ITEM LIST'!A:A,'MASTER ITEM LIST'!D:D), "")} -> GALON | J75: 880 | K75: =IF(H75="", "", H75*J75) -> 880 | L75: PAID
A76: 46133 | B76: SI-001285 | C76: BORDZ | D76: 2B-#7 | E76: {=IF(D76="", "", XLOOKUP(D76, 'MASTER ITEM LIST'!A:A, 'MASTER ITEM LIST'!B:B, ""))} -> 2B PAINT ROLLER #7 | G76: CASH | H76: 1 | I76: {=IFERROR(XLOOKUP(D76,'MASTER ITEM LIST'!A:A,'MASTER ITEM LIST'!D:D), "")} -> PC/S | J76: 85 | K76: =IF(H76="", "", H76*J76) -> 85 | L76: PAID
A77: 46133 | B77: SI-001284 | C77: RUBY | D77: EPOXYTHNR-4L | E77: {=IF(D77="", "", XLOOKUP(D77, 'MASTER ITEM LIST'!A:A, 'MASTER ITEM LIST'!B:B, ""))} -> NIPPON EPOXY THINNER 4L | G77: CASH | H77: 1 | I77: {=IFERROR(XLOOKUP(D77,'MASTER ITEM LIST'!A:A,'MASTER ITEM LIST'!D:D), "")} -> GAL/S | J77: 700 | K77: =IF(H77="", "", H77*J77) -> 700 | L77: PAID
A78: 46134 | B78: SI-001286 | C78: APARESE | D78: NAX108 | E78: {=IF(D78="", "", XLOOKUP(D78, 'MASTER ITEM LIST'!A:A, 'MASTER ITEM LIST'!B:B, ""))} -> NAX 108 CERAMIC 2K CLEAR WITH HARDENER 1L | G78: CASH | H78: 2 | I78: {=IFERROR(XLOOKUP(D78,'MASTER ITEM LIST'!A:A,'MASTER ITEM LIST'!D:D), "")} -> LITER | J78: 680 | K78: =IF(H78="", "", H78*J78) -> 1360 | L78: PAID
A79: 46134 | B79: SI-001286 | C79: APARESE | D79: PREMILAMIX-1L | E79: {=IF(D79="", "", XLOOKUP(D79, 'MASTER ITEM LIST'!A:A, 'MASTER ITEM LIST'!B:B, ""))} -> PREMILA MIXING 1L | F79: COLOR: ZHL RED | G79: CASH | H79: 0.4 | I79: {=IFERROR(XLOOKUP(D79,'MASTER ITEM LIST'!A:A,'MASTER ITEM LIST'!D:D), "")} -> LITER | J79: 2900 | K79: =IF(H79="", "", H79*J79) -> 1160 | L79: PAID
A80: 46134 | B80: SI-001287 | C80: BUKIDNON AUTOCARS | D80: NAXQDUMIX-1L | E80: {=IF(D80="", "", XLOOKUP(D80, 'MASTER ITEM LIST'!A:A, 'MASTER ITEM LIST'!B:B, ""))} -> NAX QDU MIX 1L | F80: NAX PEAL BLUE MICA | G80: CASH | H80: 0.125 | I80: {=IFERROR(XLOOKUP(D80,'MASTER ITEM LIST'!A:A,'MASTER ITEM LIST'!D:D), "")} -> LITER | J80: 1920 | K80: =IF(H80="", "", H80*J80) -> 240 | L80: PAID
A81: 46134 | B81: SI-001287 | C81: BUKIDNON AUTOCARS | D81: NAXQDUMIX-1L | E81: {=IF(D81="", "", XLOOKUP(D81, 'MASTER ITEM LIST'!A:A, 'MASTER ITEM LIST'!B:B, ""))} -> NAX QDU MIX 1L | F81: NAX PEARL WHITE MICA | G81: CASH | H81: 0.125 | I81: {=IFERROR(XLOOKUP(D81,'MASTER ITEM LIST'!A:A,'MASTER ITEM LIST'!D:D), "")} -> LITER | J81: 1680 | K81: =IF(H81="", "", H81*J81) -> 210 | L81: PAID
A82: 46134 | B82: SI-001287 | C82: BUKIDNON AUTOCARS | D82: CRO-MT1/2 | E82: {=IF(D82="", "", XLOOKUP(D82, 'MASTER ITEM LIST'!A:A, 'MASTER ITEM LIST'!B:B, ""))} -> CROCO MASKING TAPE 1/2 12MM (1X96) | G82: CASH | H82: 48 | I82: {=IFERROR(XLOOKUP(D82,'MASTER ITEM LIST'!A:A,'MASTER ITEM LIST'!D:D), "")} -> PC/S | J82: 25 | K82: =IF(H82="", "", H82*J82) -> 1200 | L82: PAID
A83: 46134 | B83: SI-001287 | C83: BUKIDNON AUTOCARS | D83: MSC | E83: {=IF(D83="", "", XLOOKUP(D83, 'MASTER ITEM LIST'!A:A, 'MASTER ITEM LIST'!B:B, ""))} -> OLD NEWS | G83: CASH | H83: 1 | I83: {=IFERROR(XLOOKUP(D83,'MASTER ITEM LIST'!A:A,'MASTER ITEM LIST'!D:D), "")} -> KG | J83: 100 | K83: =IF(H83="", "", H83*J83) -> 100 | L83: PAID
A84: 46135 | B84: SI-001288 | C84: CRYSTAL | D84: CUMIFS-60 | E84: {=IF(D84="", "", XLOOKUP(D84, 'MASTER ITEM LIST'!A:A, 'MASTER ITEM LIST'!B:B, ""))} -> CUMI SUPREME FLOOR SANDING 60 | G84: CASH | H84: 10 | I84: {=IFERROR(XLOOKUP(D84,'MASTER ITEM LIST'!A:A,'MASTER ITEM LIST'!D:D), "")} -> FT | J84: 95 | K84: =IF(H84="", "", H84*J84) -> 950 | L84: PAID
A85: 46136 | B85: SI-001292 | C85: RONIE | D85: DOMBF-4L | E85: {=IF(D85="", "", XLOOKUP(D85, 'MASTER ITEM LIST'!A:A, 'MASTER ITEM LIST'!B:B, ""))} -> DOMINO BODY FILTER WITH HARDENER 4L | G85: CASH | H85: 1 | I85: {=IFERROR(XLOOKUP(D85,'MASTER ITEM LIST'!A:A,'MASTER ITEM LIST'!D:D), "")} -> GAL | J85: 615 | K85: =IF(H85="", "", H85*J85) -> 615 | L85: PAID
A86: 46136 | B86: SI-001291 | C86: ALIGSAO | D86: NAX108 | E86: {=IF(D86="", "", XLOOKUP(D86, 'MASTER ITEM LIST'!A:A, 'MASTER ITEM LIST'!B:B, ""))} -> NAX 108 CERAMIC 2K CLEAR WITH HARDENER 1L | G86: CASH | H86: 1 | I86: {=IFERROR(XLOOKUP(D86,'MASTER ITEM LIST'!A:A,'MASTER ITEM LIST'!D:D), "")} -> LITER | J86: 700 | K86: =IF(H86="", "", H86*J86) -> 700 | L86: PAID
A87: 46136 | B87: SI-001291 | C87: ALIGSAO | D87: PREMILAMIX-1L | E87: {=IF(D87="", "", XLOOKUP(D87, 'MASTER ITEM LIST'!A:A, 'MASTER ITEM LIST'!B:B, ""))} -> PREMILA MIXING 1L | F87: CODE: 8T7 BLUE STREAK | G87: CASH | H87: 1 | I87: {=IFERROR(XLOOKUP(D87,'MASTER ITEM LIST'!A:A,'MASTER ITEM LIST'!D:D), "")} -> LITER | J87: 2700 | K87: =IF(H87="", "", H87*J87) -> 2700 | L87: PAID
A88: 46136 | B88: SI-001290 | C88: ALIGSAO | D88: EA1500 | E88: {=IF(D88="", "", XLOOKUP(D88, 'MASTER ITEM LIST'!A:A, 'MASTER ITEM LIST'!B:B, ""))} -> EAGLE SANDPAPER #1500 | G88: CASH | H88: 10 | I88: {=IFERROR(XLOOKUP(D88,'MASTER ITEM LIST'!A:A,'MASTER ITEM LIST'!D:D), "")} -> PC/S | J88: 35 | K88: =IF(H88="", "", H88*J88) -> 350 | L88: PAID
A89: 46136 | B89: SI-001290 | C89: ALIGSAO | D89: EA2000 | E89: {=IF(D89="", "", XLOOKUP(D89, 'MASTER ITEM LIST'!A:A, 'MASTER ITEM LIST'!B:B, ""))} -> EAGLE SANDPAPER #2000 | G89: CASH | H89: 10 | I89: {=IFERROR(XLOOKUP(D89,'MASTER ITEM LIST'!A:A,'MASTER ITEM LIST'!D:D), "")} -> PC/S | J89: 35 | K89: =IF(H89="", "", H89*J89) -> 350 | L89: PAID
A90: 46136 | B90: SI-001290 | C90: ALIGSAO | D90: MSC | E90: {=IF(D90="", "", XLOOKUP(D90, 'MASTER ITEM LIST'!A:A, 'MASTER ITEM LIST'!B:B, ""))} -> OLD NEWS | G90: CASH | H90: 3 | I90: {=IFERROR(XLOOKUP(D90,'MASTER ITEM LIST'!A:A,'MASTER ITEM LIST'!D:D), "")} -> KG | J90: 100 | K90: =IF(H90="", "", H90*J90) -> 300 | L90: PAID
A91: 46136 | B91: SI-001290 | C91: ALIGSAO | D91: CRO-MT3/4 | E91: {=IF(D91="", "", XLOOKUP(D91, 'MASTER ITEM LIST'!A:A, 'MASTER ITEM LIST'!B:B, ""))} -> CROCO MASKING TAPE 3/4 18MM (1X64) | G91: CASH | H91: 8 | I91: {=IFERROR(XLOOKUP(D91,'MASTER ITEM LIST'!A:A,'MASTER ITEM LIST'!D:D), "")} -> PC/S | J91: 35 | K91: =IF(H91="", "", H91*J91) -> 280 | L91: PAID
A92: 46136 | B92: SI-001290 | C92: ALIGSAO | D92: ROBRC-1KG | E92: {=IF(D92="", "", XLOOKUP(D92, 'MASTER ITEM LIST'!A:A, 'MASTER ITEM LIST'!B:B, ""))} -> ROBERLO RUBBING COMPOUND 1KG | G92: CASH | H92: 1 | I92: {=IFERROR(XLOOKUP(D92,'MASTER ITEM LIST'!A:A,'MASTER ITEM LIST'!D:D), "")} -> KG | J92: 1000 | K92: =IF(H92="", "", H92*J92) -> 1000 | L92: PAID
A93: 46136 | B93: SI-001290 | C93: ALIGSAO | D93: FRANELLA | E93: {=IF(D93="", "", XLOOKUP(D93, 'MASTER ITEM LIST'!A:A, 'MASTER ITEM LIST'!B:B, ""))} -> FRANELLA CLOTH 1YARD | G93: CASH | H93: 5 | I93: {=IFERROR(XLOOKUP(D93,'MASTER ITEM LIST'!A:A,'MASTER ITEM LIST'!D:D), "")} -> 1YRD | J93: 100 | K93: =IF(H93="", "", H93*J93) -> 500 | L93: PAID
A94: 46136 | B94: SI-001289 | C94: ALIGSAO | D94: DOMBF-4L | E94: {=IF(D94="", "", XLOOKUP(D94, 'MASTER ITEM LIST'!A:A, 'MASTER ITEM LIST'!B:B, ""))} -> DOMINO BODY FILTER WITH HARDENER 4L | G94: CASH | H94: 1 | I94: {=IFERROR(XLOOKUP(D94,'MASTER ITEM LIST'!A:A,'MASTER ITEM LIST'!D:D), "")} -> GAL | J94: 615 | K94: =IF(H94="", "", H94*J94) -> 615 | L94: PAID
A95: 46136 | B95: SI-001289 | C95: ALIGSAO | D95: EA120 | E95: {=IF(D95="", "", XLOOKUP(D95, 'MASTER ITEM LIST'!A:A, 'MASTER ITEM LIST'!B:B, ""))} -> EAGLE SANDPAPER #120 | G95: CASH | H95: 15 | I95: {=IFERROR(XLOOKUP(D95,'MASTER ITEM LIST'!A:A,'MASTER ITEM LIST'!D:D), "")} -> PC/S | J95: 25 | K95: =IF(H95="", "", H95*J95) -> 375 | L95: PAID
A96: 46136 | B96: SI-001289 | C96: ALIGSAO | D96: EA240 | E96: {=IF(D96="", "", XLOOKUP(D96, 'MASTER ITEM LIST'!A:A, 'MASTER ITEM LIST'!B:B, ""))} -> EAGLE SANDPAPER #240 | G96: CASH | H96: 10 | I96: {=IFERROR(XLOOKUP(D96,'MASTER ITEM LIST'!A:A,'MASTER ITEM LIST'!D:D), "")} -> PC/S | J96: 25 | K96: =IF(H96="", "", H96*J96) -> 250 | L96: PAID
A97: 46136 | B97: SI-001289 | C97: ALIGSAO | D97: EA400 | E97: {=IF(D97="", "", XLOOKUP(D97, 'MASTER ITEM LIST'!A:A, 'MASTER ITEM LIST'!B:B, ""))} -> EAGLE SANDPAPER #400 | G97: CASH | H97: 10 | I97: {=IFERROR(XLOOKUP(D97,'MASTER ITEM LIST'!A:A,'MASTER ITEM LIST'!D:D), "")} -> PC/S | J97: 25 | K97: =IF(H97="", "", H97*J97) -> 250 | L97: PAID
A98: 46136 | B98: SI-001289 | C98: ALIGSAO | D98: EA800 | E98: {=IF(D98="", "", XLOOKUP(D98, 'MASTER ITEM LIST'!A:A, 'MASTER ITEM LIST'!B:B, ""))} -> EAGLE SANDPAPER #800 | G98: CASH | H98: 10 | I98: {=IFERROR(XLOOKUP(D98,'MASTER ITEM LIST'!A:A,'MASTER ITEM LIST'!D:D), "")} -> PC/S | J98: 25 | K98: =IF(H98="", "", H98*J98) -> 250 | L98: PAID
A99: 46136 | B99: SI-001289 | C99: ALIGSAO | D99: EA1200 | E99: {=IF(D99="", "", XLOOKUP(D99, 'MASTER ITEM LIST'!A:A, 'MASTER ITEM LIST'!B:B, ""))} -> EAGLE SANDPAPER #1200 | G99: CASH | H99: 10 | I99: {=IFERROR(XLOOKUP(D99,'MASTER ITEM LIST'!A:A,'MASTER ITEM LIST'!D:D), "")} -> PC/S | J99: 25 | K99: =IF(H99="", "", H99*J99) -> 250 | L99: PAID
... A103: 46139 | B103: SI-001297 | C103: BUKIDNON AUTOCARS | D103: EA1200 | E103: {=IF(D103="", "", XLOOKUP(D103, 'MASTER ITEM LIST'!A:A, 'MASTER ITEM LIST'!B:B, ""))} -> EAGLE SANDPAPER #1200 | G103: CASH | H103: 4 | I103: {=IFERROR(XLOOKUP(D103,'MASTER ITEM LIST'!A:A,'MASTER ITEM LIST'!D:D), "")} -> PC/S | J103: 25 | K103: =IF(H103="", "", H103*J103) -> 100 | L103: PAID
...

Sheet STOCK IN  TRANSFER
A1: DATE | B1: REF. NO. | C1: SUPPLIER | D1: ITEM CODE | E1: DESCRIPTION | F1: TYPE | G1: QTY | H1: UNIT | I1: UNIT PRICE | J1: TOTAL AMOUNT
A2: 25/04/0226 | B2: CSI-03664 | C2: APC DISTRIBUTION - VALENCIA | D2: 2B-PB-2 | E2: {=IF(D2="", "", XLOOKUP(D2, 'MASTER ITEM LIST'!A:A, 'MASTER ITEM LIST'!B:B, ""))} -> 2B PAINT BRUSH #2 | F2: STOCK IN | G2: 12 | H2: {=IFERROR(XLOOKUP(D2,'MASTER ITEM LIST'!A:A,'MASTER ITEM LIST'!D:D), "")} -> PC/S | I2: 30.5 | J2: =IF(G2="", "",G2*I2) -> 366
A3: 46112 | C3: INVENTORY - MARCH 31, 2026 | D3: MT904 | E3: {=IF(D3="", "", XLOOKUP(D3, 'MASTER ITEM LIST'!A:A, 'MASTER ITEM LIST'!B:B, ""))} -> NAX PREMILA MT904 SHADOWN GREEN 1L | F3: STOCK IN | G3: 3 | H3: {=IFERROR(XLOOKUP(D3,'MASTER ITEM LIST'!A:A,'MASTER ITEM LIST'!D:D), "")} -> LTR/S | I3: 1593 | J3: =IF(G3="", "",G3*I3) -> 4779
A4: 46112 | C4: INVENTORY - MARCH 31, 2026 | D4: MT903 | E4: {=IF(D4="", "", XLOOKUP(D4, 'MASTER ITEM LIST'!A:A, 'MASTER ITEM LIST'!B:B, ""))} -> NAX PREMILA MT903 SUN GREEN 1L | F4: STOCK IN | G4: 3 | H4: {=IFERROR(XLOOKUP(D4,'MASTER ITEM LIST'!A:A,'MASTER ITEM LIST'!D:D), "")} -> LTR/S | I4: 1561 | J4: =IF(G4="", "",G4*I4) -> 4683
A5: 46112 | C5: INVENTORY - MARCH 31, 2026 | D5: MT902 | E5: {=IF(D5="", "", XLOOKUP(D5, 'MASTER ITEM LIST'!A:A, 'MASTER ITEM LIST'!B:B, ""))} -> NAX PREMILA MT902 GRASS GREEN 1L | F5: STOCK IN | G5: 3 | H5: {=IFERROR(XLOOKUP(D5,'MASTER ITEM LIST'!A:A,'MASTER ITEM LIST'!D:D), "")} -> LTR/S | I5: 1593 | J5: =IF(G5="", "",G5*I5) -> 4779
A6: 46112 | C6: INVENTORY - MARCH 31, 2026 | D6: MT807 | E6: {=IF(D6="", "", XLOOKUP(D6, 'MASTER ITEM LIST'!A:A, 'MASTER ITEM LIST'!B:B, ""))} -> NAX PREMILA MT807 VACANCE BLUE 1L | F6: STOCK IN | G6: 3 | H6: {=IFERROR(XLOOKUP(D6,'MASTER ITEM LIST'!A:A,'MASTER ITEM LIST'!D:D), "")} -> LTR/S | I6: 1593 | J6: =IF(G6="", "",G6*I6) -> 4779
A7: 46112 | C7: INVENTORY - MARCH 31, 2026 | D7: MT806 | E7: {=IF(D7="", "", XLOOKUP(D7, 'MASTER ITEM LIST'!A:A, 'MASTER ITEM LIST'!B:B, ""))} -> NAX PREMILA MT806 HERMES BLUE 1L | F7: STOCK IN | G7: 2 | H7: {=IFERROR(XLOOKUP(D7,'MASTER ITEM LIST'!A:A,'MASTER ITEM LIST'!D:D), "")} -> LTR/S | I7: 1593 | J7: =IF(G7="", "",G7*I7) -> 3186
A8: 46112 | C8: INVENTORY - MARCH 31, 2026 | D8: MT805 | E8: {=IF(D8="", "", XLOOKUP(D8, 'MASTER ITEM LIST'!A:A, 'MASTER ITEM LIST'!B:B, ""))} -> NAX PREMILA MT805 CUSTOM BLUE 1L | F8: STOCK IN | G8: 1 | H8: {=IFERROR(XLOOKUP(D8,'MASTER ITEM LIST'!A:A,'MASTER ITEM LIST'!D:D), "")} -> LTR/S | I8: 1593 | J8: =IF(G8="", "",G8*I8) -> 1593
A9: 46112 | C9: INVENTORY - MARCH 31, 2026 | D9: MT804 | E9: {=IF(D9="", "", XLOOKUP(D9, 'MASTER ITEM LIST'!A:A, 'MASTER ITEM LIST'!B:B, ""))} -> NAX PREMILA MT804 ORIENT BLUE 1L | F9: STOCK IN | G9: 1 | H9: {=IFERROR(XLOOKUP(D9,'MASTER ITEM LIST'!A:A,'MASTER ITEM LIST'!D:D), "")} -> LTR/S | I9: 1593 | J9: =IF(G9="", "",G9*I9) -> 1593
A10: 46112 | C10: INVENTORY - MARCH 31, 2026 | D10: MT803 | E10: {=IF(D10="", "", XLOOKUP(D10, 'MASTER ITEM LIST'!A:A, 'MASTER ITEM LIST'!B:B, ""))} -> NAX PREMILA MT803 FRESH BLUE 1L | F10: STOCK IN | G10: 2 | H10: {=IFERROR(XLOOKUP(D10,'MASTER ITEM LIST'!A:A,'MASTER ITEM LIST'!D:D), "")} -> LTR/S | I10: 1593 | J10: =IF(G10="", "",G10*I10) -> 3186
A11: 46112 | C11: INVENTORY - MARCH 31, 2026 | D11: MT801 | E11: {=IF(D11="", "", XLOOKUP(D11, 'MASTER ITEM LIST'!A:A, 'MASTER ITEM LIST'!B:B, ""))} -> NAX PREMILA MT801 CYANINE BLUE 1L | F11: STOCK IN | G11: 3 | H11: {=IFERROR(XLOOKUP(D11,'MASTER ITEM LIST'!A:A,'MASTER ITEM LIST'!D:D), "")} -> LTR/S | I11: 1593 | J11: =IF(G11="", "",G11*I11) -> 4779
A12: 46112 | C12: INVENTORY - MARCH 31, 2026 | D12: MT705 | E12: {=IF(D12="", "", XLOOKUP(D12, 'MASTER ITEM LIST'!A:A, 'MASTER ITEM LIST'!B:B, ""))} -> NAX PREMILA MT705 FLORA VIOLET 1L | F12: STOCK IN | G12: 4 | H12: {=IFERROR(XLOOKUP(D12,'MASTER ITEM LIST'!A:A,'MASTER ITEM LIST'!D:D), "")} -> LTR/S | I12: 1896 | J12: =IF(G12="", "",G12*I12) -> 7584
A13: 46112 | C13: INVENTORY - MARCH 31, 2026 | D13: MT704 | E13: {=IF(D13="", "", XLOOKUP(D13, 'MASTER ITEM LIST'!A:A, 'MASTER ITEM LIST'!B:B, ""))} -> NAX PREMILA MT704 FINE VIOLET 1L | F13: STOCK IN | G13: 3 | H13: {=IFERROR(XLOOKUP(D13,'MASTER ITEM LIST'!A:A,'MASTER ITEM LIST'!D:D), "")} -> LTR/S | I13: 1593 | J13: =IF(G13="", "",G13*I13) -> 4779
A14: 46112 | C14: INVENTORY - MARCH 31, 2026 | D14: MT607 | E14: {=IF(D14="", "", XLOOKUP(D14, 'MASTER ITEM LIST'!A:A, 'MASTER ITEM LIST'!B:B, ""))} -> NAX PREMILA MT607 AUTUMN RED 1L | F14: STOCK IN | G14: 1 | H14: {=IFERROR(XLOOKUP(D14,'MASTER ITEM LIST'!A:A,'MASTER ITEM LIST'!D:D), "")} -> LTR/S | I14: 2048 | J14: =IF(G14="", "",G14*I14) -> 2048
... A341: 46127 | C341: TRANSFER TO MIXING AREA | D341: PNB100 | E341: {=IF(D341="", "", XLOOKUP(D341, 'MASTER ITEM LIST'!A:A, 'MASTER ITEM LIST'!B:B, ""))} -> NAX PREMILA NB100 B/C BINDER 4L | F341: ADJUSTMENT (-) | G341: 1 | H341: {=IFERROR(XLOOKUP(D341,'MASTER ITEM LIST'!A:A,'MASTER ITEM LIST'!D:D), "")} -> GAL | I341: 2100 | J341: =IF(G341="", "",G341*I341) -> 2100
A342: 46128 | B342: CSI-03653 | C342: APC DISTRIBUTION - VALENCIA | D342: DOMBF-1L | E342: {=IF(D342="", "", XLOOKUP(D342, 'MASTER ITEM LIST'!A:A, 'MASTER ITEM LIST'!B:B, ""))} -> DOMINO BODY FILTER WITH HARDENER 1L | F342: STOCK IN | G342: 12 | H342: {=IFERROR(XLOOKUP(D342,'MASTER ITEM LIST'!A:A,'MASTER ITEM LIST'!D:D), "")} -> LITER | I342: 150 | J342: =IF(G342="", "",G342*I342) -> 1800
A343: 46128 | B343: CSI-03653 | C343: APC DISTRIBUTION - VALENCIA | D343: CRO-MT3/4 | E343: {=IF(D343="", "", XLOOKUP(D343, 'MASTER ITEM LIST'!A:A, 'MASTER ITEM LIST'!B:B, ""))} -> CROCO MASKING TAPE 3/4 18MM (1X64) | F343: STOCK IN | G343: 64 | H343: {=IFERROR(XLOOKUP(D343,'MASTER ITEM LIST'!A:A,'MASTER ITEM LIST'!D:D), "")} -> PC/S | I343: 23.59 | J343: =IF(G343="", "",G343*I343) -> 1509.76
A344: 46128 | B344: CSI-03653 | C344: APC DISTRIBUTION - VALENCIA | D344: GLAZERB-4L | E344: {=IF(D344="", "", XLOOKUP(D344, 'MASTER ITEM LIST'!A:A, 'MASTER ITEM LIST'!B:B, ""))} -> GLAZER AUTOMOTIVE ENAMEL BLACK 4L | F344: STOCK IN | G344: 1 | H344: {=IFERROR(XLOOKUP(D344,'MASTER ITEM LIST'!A:A,'MASTER ITEM LIST'!D:D), "")} -> GALON | I344: 855 | J344: =IF(G344="", "",G344*I344) -> 855
A345: 46128 | B345: CSI-03653 | C345: APC DISTRIBUTION - VALENCIA | D345: NXU4075-4L | E345: {=IF(D345="", "", XLOOKUP(D345, 'MASTER ITEM LIST'!A:A, 'MASTER ITEM LIST'!B:B, ""))} -> NIPPON EXTREME QDU WHITE 4L | F345: STOCK IN | G345: 3 | H345: {=IFERROR(XLOOKUP(D345,'MASTER ITEM LIST'!A:A,'MASTER ITEM LIST'!D:D), "")} -> GAL | I345: 1550 | J345: =IF(G345="", "",G345*I345) -> 4650
A346: 46128 | B346: CSI-03653 | C346: APC DISTRIBUTION - VALENCIA | D346: NXU7391-4L | E346: {=IF(D346="", "", XLOOKUP(D346, 'MASTER ITEM LIST'!A:A, 'MASTER ITEM LIST'!B:B, ""))} -> NIPPON EXTREME QDU SILVER 4L | F346: STOCK IN | G346: 1 | H346: {=IFERROR(XLOOKUP(D346,'MASTER ITEM LIST'!A:A,'MASTER ITEM LIST'!D:D), "")} -> GAL | I346: 1493 | J346: =IF(G346="", "",G346*I346) -> 1493
A347: 46128 | B347: CSI-03653 | C347: APC DISTRIBUTION - VALENCIA | D347: ROS-739 | E347: {=IF(D347="", "", XLOOKUP(D347, 'MASTER ITEM LIST'!A:A, 'MASTER ITEM LIST'!B:B, ""))} -> COCONUT ELASTOMERIC WATER FROOFING PAINT ROS-739 RAIN OR SHINE 4L | F347: STOCK IN | G347: 1 | H347: {=IFERROR(XLOOKUP(D347,'MASTER ITEM LIST'!A:A,'MASTER ITEM LIST'!D:D), "")} -> 4L | I347: 695 | J347: =IF(G347="", "",G347*I347) -> 695
A348: 46128 | B348: CSI-03653 | C348: APC DISTRIBUTION - VALENCIA | D348: PG888-4L | E348: {=IF(D348="", "", XLOOKUP(D348, 'MASTER ITEM LIST'!A:A, 'MASTER ITEM LIST'!B:B, ""))} -> POLYGLOSS PU 888 RED 4L | F348: STOCK IN | G348: 1 | H348: {=IFERROR(XLOOKUP(D348,'MASTER ITEM LIST'!A:A,'MASTER ITEM LIST'!D:D), "")} -> GALON | I348: 2448 | J348: =IF(G348="", "",G348*I348) -> 2448
A349: 46128 | B349: CSI-03653 | C349: APC DISTRIBUTION - VALENCIA | D349: PGW-4L | E349: {=IF(D349="", "", XLOOKUP(D349, 'MASTER ITEM LIST'!A:A, 'MASTER ITEM LIST'!B:B, ""))} -> POLYGLOSS PU WHITE 4L | F349: STOCK IN | G349: 2 | H349: {=IFERROR(XLOOKUP(D349,'MASTER ITEM LIST'!A:A,'MASTER ITEM LIST'!D:D), "")} -> GALON | I349: 1730 | J349: =IF(G349="", "",G349*I349) -> 3460
A350: 46128 | B350: CSI-03653 | C350: APC DISTRIBUTION - VALENCIA | D350: PGJB-4L | E350: {=IF(D350="", "", XLOOKUP(D350, 'MASTER ITEM LIST'!A:A, 'MASTER ITEM LIST'!B:B, ""))} -> POLYGLOSS PU JET BLACK 4L | F350: STOCK IN | G350: 1 | H350: {=IFERROR(XLOOKUP(D350,'MASTER ITEM LIST'!A:A,'MASTER ITEM LIST'!D:D), "")} -> GALON | I350: 1830 | J350: =IF(G350="", "",G350*I350) -> 1830
A351: 46128 | B351: CSI-03653 | C351: APC DISTRIBUTION - VALENCIA | D351: EA2000 | E351: {=IF(D351="", "", XLOOKUP(D351, 'MASTER ITEM LIST'!A:A, 'MASTER ITEM LIST'!B:B, ""))} -> EAGLE SANDPAPER #2000 | F351: STOCK IN | G351: 100 | H351: {=IFERROR(XLOOKUP(D351,'MASTER ITEM LIST'!A:A,'MASTER ITEM LIST'!D:D), "")} -> PC/S | I351: 28 | J351: =IF(G351="", "",G351*I351) -> 2800
A352: 46128 | B352: CSI-03654 | C352: APC DISTRIBUTION - VALENCIA | D352: NP9200 | E352: {=IF(D352="", "", XLOOKUP(D352, 'MASTER ITEM LIST'!A:A, 'MASTER ITEM LIST'!B:B, ""))} -> NAX PREMILA NP9200 2K CLEAR WITH HARDENER 1L | F352: STOCK IN | G352: 12 | H352: {=IFERROR(XLOOKUP(D352,'MASTER ITEM LIST'!A:A,'MASTER ITEM LIST'!D:D), "")} -> LITER | I352: 920 | J352: =IF(G352="", "",G352*I352) -> 11040
A353: 46128 | B353: CSI-03654 | C353: APC DISTRIBUTION - VALENCIA | D353: DOITH-4L | E353: {=IF(D353="", "", XLOOKUP(D353, 'MASTER ITEM LIST'!A:A, 'MASTER ITEM LIST'!B:B, ""))} -> DO IT URETHANE THINNER 4L | F353: STOCK IN | G353: 12 | H353: {=IFERROR(XLOOKUP(D353,'MASTER ITEM LIST'!A:A,'MASTER ITEM LIST'!D:D), "")} -> GAL/S | I353: 590 | J353: =IF(G353="", "",G353*I353) -> 7080
... A361: 46129 | B361: CSI-03656 | C361: APC DISTRIBUTION - VALENCIA | D361: POLYGTHIN-4L | E361: {=IF(D361="", "", XLOOKUP(D361, 'MASTER ITEM LIST'!A:A, 'MASTER ITEM LIST'!B:B, ""))} -> POLYGLOSS URETHANE THINNER 4L | F361: STOCK IN | G361: 6 | H361: {=IFERROR(XLOOKUP(D361,'MASTER ITEM LIST'!A:A,'MASTER ITEM LIST'!D:D), "")} -> GALON | I361: 650 | J361: =IF(G361="", "",G361*I361) -> 3900
A362: 46130 | C362: TRANSFER TO MIXING AREA | D362: NAT719-4L | E362: {=IF(D362="", "", XLOOKUP(D362, 'MASTER ITEM LIST'!A:A, 'MASTER ITEM LIST'!B:B, ""))} -> NAX NAT-719 TTC COARSE SILVER 4L | F362: ADJUSTMENT (-) | G362: 1 | H362: {=IFERROR(XLOOKUP(D362,'MASTER ITEM LIST'!A:A,'MASTER ITEM LIST'!D:D), "")} -> GAL | I362: 2325 | J362: =IF(G362="", "",G362*I362) -> 2325
A363: 46130 | C363: TRANSFER TO MIXING AREA | D363: NAT192 | E363: {=IF(D363="", "", XLOOKUP(D363, 'MASTER ITEM LIST'!A:A, 'MASTER ITEM LIST'!B:B, ""))} -> NAX NAT-192 TTC BRIGHT RED 1L | F363: ADJUSTMENT (-) | G363: 1 | H363: {=IFERROR(XLOOKUP(D363,'MASTER ITEM LIST'!A:A,'MASTER ITEM LIST'!D:D), "")} -> LITER | I363: 540 | J363: =IF(G363="", "",G363*I363) -> 540
A364: 46130 | C364: TRANSFER TO MIXING AREA | D364: NAT320 | E364: {=IF(D364="", "", XLOOKUP(D364, 'MASTER ITEM LIST'!A:A, 'MASTER ITEM LIST'!B:B, ""))} -> NAX NAT-320 TTC GOLD YELLOW 1L | F364: ADJUSTMENT (-) | G364: 1 | H364: {=IFERROR(XLOOKUP(D364,'MASTER ITEM LIST'!A:A,'MASTER ITEM LIST'!D:D), "")} -> LITER | I364: 425 | J364: =IF(G364="", "",G364*I364) -> 425
A365: 46130 | C365: TRANSFER TO MIXING AREA | D365: CRO-MT1 | E365: {=IF(D365="", "", XLOOKUP(D365, 'MASTER ITEM LIST'!A:A, 'MASTER ITEM LIST'!B:B, ""))} -> CROCO MASKING TAPE #1 | F365: ADJUSTMENT (-) | G365: 1 | H365: {=IFERROR(XLOOKUP(D365,'MASTER ITEM LIST'!A:A,'MASTER ITEM LIST'!D:D), "")} -> PCS | I365: 32 | J365: =IF(G365="", "",G365*I365) -> 32
A366: 46132 | C366: TRANSFER TO MIXING AREA | D366: WCPOD | E366: {=IF(D366="", "", XLOOKUP(D366, 'MASTER ITEM LIST'!A:A, 'MASTER ITEM LIST'!B:B, ""))} -> WASTE COTTON POD | F366: ADJUSTMENT (-) | G366: 1 | H366: {=IFERROR(XLOOKUP(D366,'MASTER ITEM LIST'!A:A,'MASTER ITEM LIST'!D:D), "")} -> KL | I366: 70 | J366: =IF(G366="", "",G366*I366) -> 70
A367: 46132 | C367: TRANSFER TO MIXING AREA | D367: PNB100 | E367: {=IF(D367="", "", XLOOKUP(D367, 'MASTER ITEM LIST'!A:A, 'MASTER ITEM LIST'!B:B, ""))} -> NAX PREMILA NB100 B/C BINDER 4L | F367: ADJUSTMENT (-) | G367: 1 | H367: {=IFERROR(XLOOKUP(D367,'MASTER ITEM LIST'!A:A,'MASTER ITEM LIST'!D:D), "")} -> GAL | I367: 2100 | J367: =IF(G367="", "",G367*I367) -> 2100
A368: 46133 | C368: TRANSFER TO MIXING AREA | D368: DV400-WHITE-4L | E368: {=IF(D368="", "", XLOOKUP(D368, 'MASTER ITEM LIST'!A:A, 'MASTER ITEM LIST'!B:B, ""))} -> DAVIES QDE WHITE 4L | F368: ADJUSTMENT (-) | G368: 1 | H368: {=IFERROR(XLOOKUP(D368,'MASTER ITEM LIST'!A:A,'MASTER ITEM LIST'!D:D), "")} -> GALON | I368: 820 | J368: =IF(G368="", "",G368*I368) -> 820
A369: 46134 | C369: TRANSFER TO MIXING AREA | D369: NAX10100 | E369: {=IF(D369="", "", XLOOKUP(D369, 'MASTER ITEM LIST'!A:A, 'MASTER ITEM LIST'!B:B, ""))} -> NAX NAT-10100 NH-585 PEARL WHITE MICA 1L | F369: ADJUSTMENT (-) | G369: 1 | H369: {=IFERROR(XLOOKUP(D369,'MASTER ITEM LIST'!A:A,'MASTER ITEM LIST'!D:D), "")} -> LITER | I369: 675 | J369: =IF(G369="", "",G369*I369) -> 675
A370: 46134 | C370: TRANSFER TO MIXING AREA | D370: NXU1965-4L | E370: {=IF(D370="", "", XLOOKUP(D370, 'MASTER ITEM LIST'!A:A, 'MASTER ITEM LIST'!B:B, ""))} -> NIPPON EXTREME QDU BLACK 4L | F370: ADJUSTMENT (-) | G370: 1 | H370: {=IFERROR(XLOOKUP(D370,'MASTER ITEM LIST'!A:A,'MASTER ITEM LIST'!D:D), "")} -> GAL | I370: 1485 | J370: =IF(G370="", "",G370*I370) -> 1485
A371: 46135 | C371: TRANSFER TO MIXING AREA | D371: PNB100 | E371: {=IF(D371="", "", XLOOKUP(D371, 'MASTER ITEM LIST'!A:A, 'MASTER ITEM LIST'!B:B, ""))} -> NAX PREMILA NB100 B/C BINDER 4L | F371: ADJUSTMENT (-) | G371: 1 | H371: {=IFERROR(XLOOKUP(D371,'MASTER ITEM LIST'!A:A,'MASTER ITEM LIST'!D:D), "")} -> GAL | I371: 2100 | J371: =IF(G371="", "",G371*I371) -> 2100
A372: 46137 | B372: CSI-03664 | C372: APC DISTRIBUTION - VALENCIA | D372: DOMBF-1L | E372: {=IF(D372="", "", XLOOKUP(D372, 'MASTER ITEM LIST'!A:A, 'MASTER ITEM LIST'!B:B, ""))} -> DOMINO BODY FILTER WITH HARDENER 1L | F372: STOCK IN | G372: 12 | H372: {=IFERROR(XLOOKUP(D372,'MASTER ITEM LIST'!A:A,'MASTER ITEM LIST'!D:D), "")} -> LITER | I372: 160 | J372: =IF(G372="", "",G372*I372) -> 1920
A373: 46137 | B373: CSI-03664 | C373: APC DISTRIBUTION - VALENCIA | D373: HS-1L | E373: {=IF(D373="", "", XLOOKUP(D373, 'MASTER ITEM LIST'!A:A, 'MASTER ITEM LIST'!B:B, ""))} -> NIPPON HS FILLER 1L | F373: STOCK IN | G373: 12 | H373: {=IFERROR(XLOOKUP(D373,'MASTER ITEM LIST'!A:A,'MASTER ITEM LIST'!D:D), "")} -> LITER | I373: 720 | J373: =IF(G373="", "",G373*I373) -> 8640
A374: 46137 | B374: CSI-03664 | C374: APC DISTRIBUTION - VALENCIA | D374: NXU7391-4L | E374: {=IF(D374="", "", XLOOKUP(D374, 'MASTER ITEM LIST'!A:A, 'MASTER ITEM LIST'!B:B, ""))} -> NIPPON EXTREME QDU SILVER 4L | F374: STOCK IN | G374: 1 | H374: {=IFERROR(XLOOKUP(D374,'MASTER ITEM LIST'!A:A,'MASTER ITEM LIST'!D:D), "")} -> GAL | I374: 2000 | J374: =IF(G374="", "",G374*I374) -> 2000
A375: 46137 | B375: CSI-03664 | C375: APC DISTRIBUTION - VALENCIA | D375: NXU1965-4L | E375: {=IF(D375="", "", XLOOKUP(D375, 'MASTER ITEM LIST'!A:A, 'MASTER ITEM LIST'!B:B, ""))} -> NIPPON EXTREME QDU BLACK 4L | F375: STOCK IN | G375: 2 | H375: {=IFERROR(XLOOKUP(D375,'MASTER ITEM LIST'!A:A,'MASTER ITEM LIST'!D:D), "")} -> GAL | I375: 1850 | J375: =IF(G375="", "",G375*I375) -> 3700
A376: 46137 | B376: CSI-03664 | C376: APC DISTRIBUTION - VALENCIA | D376: POLYGTHIN-4L | E376: {=IF(D376="", "", XLOOKUP(D376, 'MASTER ITEM LIST'!A:A, 'MASTER ITEM LIST'!B:B, ""))} -> POLYGLOSS URETHANE THINNER 4L | F376: STOCK IN | G376: 2 | H376: {=IFERROR(XLOOKUP(D376,'MASTER ITEM LIST'!A:A,'MASTER ITEM LIST'!D:D), "")} -> GALON | I376: 650 | J376: =IF(G376="", "",G376*I376) -> 1300
A377: 46137 | B377: CSI-03664 | C377: APC DISTRIBUTION - VALENCIA | D377: ROS-SG-4L | E377: {=IF(D377="", "", XLOOKUP(D377, 'MASTER ITEM LIST'!A:A, 'MASTER ITEM LIST'!B:B, ""))} -> RAIN OR SHINE STONE GRAY 4L | F377: STOCK IN | G377: 1 | H377: {=IFERROR(XLOOKUP(D377,'MASTER ITEM LIST'!A:A,'MASTER ITEM LIST'!D:D), "")} -> GALON | I377: 665 | J377: =IF(G377="", "",G377*I377) -> 665
A378: 46137 | B378: CSI-03664 | C378: APC DISTRIBUTION - VALENCIA | D378: NAX301 | E378: {=IF(D378="", "", XLOOKUP(D378, 'MASTER ITEM LIST'!A:A, 'MASTER ITEM LIST'!B:B, ""))} -> NAX 301 NAX QDU FLAT CLEAR WITH HARDENER 1L | F378: STOCK IN | G378: 2 | H378: {=IFERROR(XLOOKUP(D378,'MASTER ITEM LIST'!A:A,'MASTER ITEM LIST'!D:D), "")} -> LITER | I378: 900 | J378: =IF(G378="", "",G378*I378) -> 1800
A379: 46137 | B379: CSI-03664 | C379: APC DISTRIBUTION - VALENCIA | D379: ROS-629-4L | E379: {=IF(D379="", "", XLOOKUP(D379, 'MASTER ITEM LIST'!A:A, 'MASTER ITEM LIST'!B:B, ""))} -> RAIN OR SHINE ROS-629 TULIPS 4L | F379: STOCK IN | G379: 2 | H379: {=IFERROR(XLOOKUP(D379,'MASTER ITEM LIST'!A:A,'MASTER ITEM LIST'!D:D), "")} -> GALON | I379: 665 | J379: =IF(G379="", "",G379*I379) -> 1330
A380: 46137 | B380: CSI-03664 | C380: APC DISTRIBUTION - VALENCIA | D380: PLYZGBLK-48 | E380: {=IF(D380="", "", XLOOKUP(D380, 'MASTER ITEM LIST'!A:A, 'MASTER ITEM LIST'!B:B, ""))} -> PYLOX LAZER GLOSS BLACK 48 | F380: STOCK IN | G380: 12 | H380: {=IFERROR(XLOOKUP(D380,'MASTER ITEM LIST'!A:A,'MASTER ITEM LIST'!D:D), "")} -> CAN | I380: 95 | J380: =IF(G380="", "",G380*I380) -> 1140
A381: 46139 | C381: TRANSFER TO MIXING AREA | D381: PNB100 | E381: {=IF(D381="", "", XLOOKUP(D381, 'MASTER ITEM LIST'!A:A, 'MASTER ITEM LIST'!B:B, ""))} -> NAX PREMILA NB100 B/C BINDER 4L | F381: ADJUSTMENT (-) | G381: 1 | H381: {=IFERROR(XLOOKUP(D381,'MASTER ITEM LIST'!A:A,'MASTER ITEM LIST'!D:D), "")} -> GAL | I381: 2100 | J381: =IF(G381="", "",G381*I381) -> 2100
A382: 46141 | C382: TRANSFER TO MIXING AREA | D382: PLQDB-4L | E382: {=IF(D382="", "", XLOOKUP(D382, 'MASTER ITEM LIST'!A:A, 'MASTER ITEM LIST'!B:B, ""))} -> PLATONE QDE BLACK 4L | F382: ADJUSTMENT (-) | G382: 1 | H382: {=IFERROR(XLOOKUP(D382,'MASTER ITEM LIST'!A:A,'MASTER ITEM LIST'!D:D), "")} -> GAL | I382: 661 | J382: =IF(G382="", "",G382*I382) -> 661
A383: 46141 | C383: TRANSFER TO MIXING AREA | D383: MT203 | E383: {=IF(D383="", "", XLOOKUP(D383, 'MASTER ITEM LIST'!A:A, 'MASTER ITEM LIST'!B:B, ""))} -> NAX PREMILA MT203 DEEP BLACK 1L | F383: ADJUSTMENT (-) | G383: 1 | H383: {=IFERROR(XLOOKUP(D383,'MASTER ITEM LIST'!A:A,'MASTER ITEM LIST'!D:D), "")} -> LTR/S | I383: 1668 | J383: =IF(G383="", "",G383*I383) -> 1668
A384: 46141 | C384: TRANSFER TO MIXING AREA | D384: NAT1159 | E384: {=IF(D384="", "", XLOOKUP(D384, 'MASTER ITEM LIST'!A:A, 'MASTER ITEM LIST'!B:B, ""))} -> NAX NAT-1159 TTC MEDIUM RUSSET MICA 1L | F384: ADJUSTMENT (-) | G384: 1 | H384: {=IFERROR(XLOOKUP(D384,'MASTER ITEM LIST'!A:A,'MASTER ITEM LIST'!D:D), "")} -> LITER | I384: 780 | J384: =IF(G384="", "",G384*I384) -> 780
A385: 46141 | C385: TRANSFER TO MIXING AREA | D385: NAT320 | E385: {=IF(D385="", "", XLOOKUP(D385, 'MASTER ITEM LIST'!A:A, 'MASTER ITEM LIST'!B:B, ""))} -> NAX NAT-320 TTC GOLD YELLOW 1L | F385: ADJUSTMENT (-) | G385: 1 | H385: {=IFERROR(XLOOKUP(D385,'MASTER ITEM LIST'!A:A,'MASTER ITEM LIST'!D:D), "")} -> LITER | I385: 425 | J385: =IF(G385="", "",G385*I385) -> 425
A386: 46141 | C386: TRANSFER TO MIXING AREA | D386: NAT1164 | E386: {=IF(D386="", "", XLOOKUP(D386, 'MASTER ITEM LIST'!A:A, 'MASTER ITEM LIST'!B:B, ""))} -> NAX NAT-1164 TTC BRIGHT GOLD MICA 1L | F386: ADJUSTMENT (-) | G386: 1 | H386: {=IFERROR(XLOOKUP(D386,'MASTER ITEM LIST'!A:A,'MASTER ITEM LIST'!D:D), "")} -> LITER | I386: 640 | J386: =IF(G386="", "",G386*I386) -> 640
A387: 46142 | C387: TRANSFER TO MIXING AREA | D387: NAT990-4L | E387: {=IF(D387="", "", XLOOKUP(D387, 'MASTER ITEM LIST'!A:A, 'MASTER ITEM LIST'!B:B, ""))} -> NAX NAT-990 TTC BLACK 4L | F387: ADJUSTMENT (-) | G387: 1 | H387: {=IFERROR(XLOOKUP(D387,'MASTER ITEM LIST'!A:A,'MASTER ITEM LIST'!D:D), "")} -> GAL | I387: 1518 | J387: =IF(G387="", "",G387*I387) -> 1518
A388: 46146 | C388: TRANSFER TO MIXING AREA | D388: CRO-MT1 | E388: {=IF(D388="", "", XLOOKUP(D388, 'MASTER ITEM LIST'!A:A, 'MASTER ITEM LIST'!B:B, ""))} -> CROCO MASKING TAPE #1 | F388: ADJUSTMENT (-) | G388: 1 | H388: {=IFERROR(XLOOKUP(D388,'MASTER ITEM LIST'!A:A,'MASTER ITEM LIST'!D:D), "")} -> PCS | I388: 32 | J388: =IF(G388="", "",G388*I388) -> 32
A389: 46146 | C389: TRANSFER TO MIXING AREA | D389: POLY- BT-ALUM-4L | E389: {=IF(D389="", "", XLOOKUP(D389, 'MASTER ITEM LIST'!A:A, 'MASTER ITEM LIST'!B:B, ""))} -> POLYGLOSS-BRIGHT ALUMINUM 4L | F389: ADJUSTMENT (-) | G389: 1 | H389: {=IFERROR(XLOOKUP(D389,'MASTER ITEM LIST'!A:A,'MASTER ITEM LIST'!D:D), "")} -> GALON | I389: 1950 | J389: =IF(G389="", "",G389*I389) -> 1950
A390: 46147 | C390: TRANSFER TO MIXING AREA | D390: PNB100 | E390: {=IF(D390="", "", XLOOKUP(D390, 'MASTER ITEM LIST'!A:A, 'MASTER ITEM LIST'!B:B, ""))} -> NAX PREMILA NB100 B/C BINDER 4L | F390: ADJUSTMENT (-) | G390: 1 | H390: {=IFERROR(XLOOKUP(D390,'MASTER ITEM LIST'!A:A,'MASTER ITEM LIST'!D:D), "")} -> GAL | I390: 2100 | J390: =IF(G390="", "",G390*I390) -> 2100
A391: 46147 | C391: TRANSFER TO MIXING AREA | D391: POLYGTHIN-4L | E391: {=IF(D391="", "", XLOOKUP(D391, 'MASTER ITEM LIST'!A:A, 'MASTER ITEM LIST'!B:B, ""))} -> POLYGLOSS URETHANE THINNER 4L | F391: ADJUSTMENT (-) | G391: 1 | H391: {=IFERROR(XLOOKUP(D391,'MASTER ITEM LIST'!A:A,'MASTER ITEM LIST'!D:D), "")} -> GALON | I391: 675 | J391: =IF(G391="", "",G391*I391) -> 675
A392: 46148 | C392: TRANSFER TO MIXING AREA | D392: CRO-MT1 | E392: {=IF(D392="", "", XLOOKUP(D392, 'MASTER ITEM LIST'!A:A, 'MASTER ITEM LIST'!B:B, ""))} -> CROCO MASKING TAPE #1 | F392: ADJUSTMENT (-) | G392: 1 | H392: {=IFERROR(XLOOKUP(D392,'MASTER ITEM LIST'!A:A,'MASTER ITEM LIST'!D:D), "")} -> PCS | I392: 32 | J392: =IF(G392="", "",G392*I392) -> 32
... A396: 46150 | C396: TRANSFER TO MIXING AREA | D396: NXU1338-4L | E396: {=IF(D396="", "", XLOOKUP(D396, 'MASTER ITEM LIST'!A:A, 'MASTER ITEM LIST'!B:B, ""))} -> NIPPON EXTREME QDU YELLOW 4L | F396: ADJUSTMENT (-) | G396: 1 | H396: {=IFERROR(XLOOKUP(D396,'MASTER ITEM LIST'!A:A,'MASTER ITEM LIST'!D:D), "")} -> GAL | I396: 1630 | J396: =IF(G396="", "",G396*I396) -> 1630
A397: 46150 | C397: TRANSFER TO MIXING AREA | D397: NAT100-4L | E397: {=IF(D397="", "", XLOOKUP(D397, 'MASTER ITEM LIST'!A:A, 'MASTER ITEM LIST'!B:B, ""))} -> NAX NAT-100 TTC WHITE 4L | F397: ADJUSTMENT (-) | G397: 2 | H397: {=IFERROR(XLOOKUP(D397,'MASTER ITEM LIST'!A:A,'MASTER ITEM LIST'!D:D), "")} -> GAL | J397: =IF(G397="", "",G397*I397) -> 0
A398: 46151 | B398: CSI-03680 | C398: APC DISTRIBUTION - VALENCIA | D398: NAT1159 | E398: {=IF(D398="", "", XLOOKUP(D398, 'MASTER ITEM LIST'!A:A, 'MASTER ITEM LIST'!B:B, ""))} -> NAX NAT-1159 TTC MEDIUM RUSSET MICA 1L | F398: STOCK IN | G398: 2 | H398: {=IFERROR(XLOOKUP(D398,'MASTER ITEM LIST'!A:A,'MASTER ITEM LIST'!D:D), "")} -> LITER | I398: 1120 | J398: =IF(G398="", "",G398*I398) -> 2240
A399: 46151 | B399: CSI-03680 | C399: APC DISTRIBUTION - VALENCIA | D399: FF151 | E399: {=IF(D399="", "", XLOOKUP(D399, 'MASTER ITEM LIST'!A:A, 'MASTER ITEM LIST'!B:B, ""))} -> NIPPON FF151 FLOP CONTROL | F399: STOCK IN | G399: 1 | H399: {=IFERROR(XLOOKUP(D399,'MASTER ITEM LIST'!A:A,'MASTER ITEM LIST'!D:D), "")} -> LTR | I399: 1600 | J399: =IF(G399="", "",G399*I399) -> 1600
A400: 46151 | B400: CSI-03680 | C400: APC DISTRIBUTION - VALENCIA | D400: NAX108 | E400: {=IF(D400="", "", XLOOKUP(D400, 'MASTER ITEM LIST'!A:A, 'MASTER ITEM LIST'!B:B, ""))} -> NAX 108 CERAMIC 2K CLEAR WITH HARDENER 1L | F400: STOCK IN | G400: 12 | H400: {=IFERROR(XLOOKUP(D400,'MASTER ITEM LIST'!A:A,'MASTER ITEM LIST'!D:D), "")} -> LITER | I400: 600 | J400: =IF(G400="", "",G400*I400) -> 7200
A401: 46151 | B401: CSI-03680 | C401: APC DISTRIBUTION - VALENCIA | D401: NP9200 | E401: {=IF(D401="", "", XLOOKUP(D401, 'MASTER ITEM LIST'!A:A, 'MASTER ITEM LIST'!B:B, ""))} -> NAX PREMILA NP9200 2K CLEAR WITH HARDENER 1L | F401: STOCK IN | G401: 12 | H401: {=IFERROR(XLOOKUP(D401,'MASTER ITEM LIST'!A:A,'MASTER ITEM LIST'!D:D), "")} -> LITER | I401: 1150 | J401: =IF(G401="", "",G401*I401) -> 13800
A402: 46151 | B402: CSI-03680 | C402: APC DISTRIBUTION - VALENCIA | D402: WEBER | E402: {=IF(D402="", "", XLOOKUP(D402, 'MASTER ITEM LIST'!A:A, 'MASTER ITEM LIST'!B:B, ""))} -> SPRAY GUN F-75G WEBER | F402: STOCK IN | G402: 1 | H402: {=IFERROR(XLOOKUP(D402,'MASTER ITEM LIST'!A:A,'MASTER ITEM LIST'!D:D), "")} -> SET | I402: 700 | J402: =IF(G402="", "",G402*I402) -> 700
A403: 46151 | B403: CSI-03680 | C403: APC DISTRIBUTION - VALENCIA | D403: CRO-MT1 | E403: {=IF(D403="", "", XLOOKUP(D403, 'MASTER ITEM LIST'!A:A, 'MASTER ITEM LIST'!B:B, ""))} -> CROCO MASKING TAPE #1 | F403: STOCK IN | G403: 48 | H403: {=IFERROR(XLOOKUP(D403,'MASTER ITEM LIST'!A:A,'MASTER ITEM LIST'!D:D), "")} -> PCS | I403: 31 | J403: =IF(G403="", "",G403*I403) -> 1488
A404: 46151 | B404: CSI-03680 | C404: APC DISTRIBUTION - VALENCIA | D404: POLY- BT-ALUM-4L | E404: {=IF(D404="", "", XLOOKUP(D404, 'MASTER ITEM LIST'!A:A, 'MASTER ITEM LIST'!B:B, ""))} -> POLYGLOSS-BRIGHT ALUMINUM 4L | F404: STOCK IN | G404: 1 | H404: {=IFERROR(XLOOKUP(D404,'MASTER ITEM LIST'!A:A,'MASTER ITEM LIST'!D:D), "")} -> GALON | I404: 2050 | J404: =IF(G404="", "",G404*I404) -> 2050
A405: 46151 | B405: CSI-03680 | C405: APC DISTRIBUTION - VALENCIA | D405: NAX301 | E405: {=IF(D405="", "", XLOOKUP(D405, 'MASTER ITEM LIST'!A:A, 'MASTER ITEM LIST'!B:B, ""))} -> NAX 301 NAX QDU FLAT CLEAR WITH HARDENER 1L | F405: STOCK IN | G405: 1 | H405: {=IFERROR(XLOOKUP(D405,'MASTER ITEM LIST'!A:A,'MASTER ITEM LIST'!D:D), "")} -> LITER | I405: 900 | J405: =IF(G405="", "",G405*I405) -> 900
A406: 46151 | B406: CSI-03680 | C406: APC DISTRIBUTION - VALENCIA | D406: PNB100 | E406: {=IF(D406="", "", XLOOKUP(D406, 'MASTER ITEM LIST'!A:A, 'MASTER ITEM LIST'!B:B, ""))} -> NAX PREMILA NB100 B/C BINDER 4L | F406: STOCK IN | G406: 4 | H406: {=IFERROR(XLOOKUP(D406,'MASTER ITEM LIST'!A:A,'MASTER ITEM LIST'!D:D), "")} -> GAL | I406: 2165 | J406: =IF(G406="", "",G406*I406) -> 8660
A407: 46151 | B407: CSI-03680 | C407: APC DISTRIBUTION - VALENCIA | D407: PG888-4L | E407: {=IF(D407="", "", XLOOKUP(D407, 'MASTER ITEM LIST'!A:A, 'MASTER ITEM LIST'!B:B, ""))} -> POLYGLOSS PU 888 RED 4L | F407: STOCK IN | G407: 1 | H407: {=IFERROR(XLOOKUP(D407,'MASTER ITEM LIST'!A:A,'MASTER ITEM LIST'!D:D), "")} -> GALON | I407: 2600 | J407: =IF(G407="", "",G407*I407) -> 2600
A408: 46153 | B408: CSI-03681 | C408: APC DISTRIBUTION - VALENCIA | D408: ROBRC-1KG | E408: {=IF(D408="", "", XLOOKUP(D408, 'MASTER ITEM LIST'!A:A, 'MASTER ITEM LIST'!B:B, ""))} -> ROBERLO RUBBING COMPOUND 1KG | F408: STOCK IN | G408: 6 | H408: {=IFERROR(XLOOKUP(D408,'MASTER ITEM LIST'!A:A,'MASTER ITEM LIST'!D:D), "")} -> KG | I408: 780 | J408: =IF(G408="", "",G408*I408) -> 4680
A409: 46153 | B409: CSI-03681 | C409: APC DISTRIBUTION - VALENCIA | D409: NXU7391-4L | E409: {=IF(D409="", "", XLOOKUP(D409, 'MASTER ITEM LIST'!A:A, 'MASTER ITEM LIST'!B:B, ""))} -> NIPPON EXTREME QDU SILVER 4L | F409: STOCK IN | G409: 4 | H409: {=IFERROR(XLOOKUP(D409,'MASTER ITEM LIST'!A:A,'MASTER ITEM LIST'!D:D), "")} -> GAL | I409: 2000 | J409: =IF(G409="", "",G409*I409) -> 8000
... A420: 46153 | B420: CSI-03682 | C420: APC DISTRIBUTION - VALENCIA | D420: SOB757 | E420: {=IF(D420="", "", XLOOKUP(D420, 'MASTER ITEM LIST'!A:A, 'MASTER ITEM LIST'!B:B, ""))} -> NAX SOB757 HIGH GRADE URETHANE THINNER 4L | F420: STOCK IN | G420: 20 | H420: {=IFERROR(XLOOKUP(D420,'MASTER ITEM LIST'!A:A,'MASTER ITEM LIST'!D:D), "")} -> GAL | I420: 650 | J420: =IF(G420="", "",G420*I420) -> 13000
A421: 46154 | C421: TRANSFER TO MIXING AREA | D421: PNB100 | E421: {=IF(D421="", "", XLOOKUP(D421, 'MASTER ITEM LIST'!A:A, 'MASTER ITEM LIST'!B:B, ""))} -> NAX PREMILA NB100 B/C BINDER 4L | F421: ADJUSTMENT (-) | G421: 1 | H421: {=IFERROR(XLOOKUP(D421,'MASTER ITEM LIST'!A:A,'MASTER ITEM LIST'!D:D), "")} -> GAL | I421: 2100 | J421: =IF(G421="", "",G421*I421) -> 2100
A422: 46154 | C422: TRANSFER TO MIXING AREA | D422: CRO-MT1 | E422: {=IF(D422="", "", XLOOKUP(D422, 'MASTER ITEM LIST'!A:A, 'MASTER ITEM LIST'!B:B, ""))} -> CROCO MASKING TAPE #1 | F422: ADJUSTMENT (-) | G422: 1 | H422: {=IFERROR(XLOOKUP(D422,'MASTER ITEM LIST'!A:A,'MASTER ITEM LIST'!D:D), "")} -> PCS | I422: 32 | J422: =IF(G422="", "",G422*I422) -> 32
A423: 46154 | C423: TRANSFER TO MIXING AREA | D423: MT607 | E423: {=IF(D423="", "", XLOOKUP(D423, 'MASTER ITEM LIST'!A:A, 'MASTER ITEM LIST'!B:B, ""))} -> NAX PREMILA MT607 AUTUMN RED 1L | F423: ADJUSTMENT (-) | G423: 1 | H423: {=IFERROR(XLOOKUP(D423,'MASTER ITEM LIST'!A:A,'MASTER ITEM LIST'!D:D), "")} -> LTR/S | I423: 2048 | J423: =IF(G423="", "",G423*I423) -> 2048
A424: 46154 | C424: TRANSFER TO MIXING AREA | D424: NXU1338-4L | E424: {=IF(D424="", "", XLOOKUP(D424, 'MASTER ITEM LIST'!A:A, 'MASTER ITEM LIST'!B:B, ""))} -> NIPPON EXTREME QDU YELLOW 4L | F424: ADJUSTMENT (-) | G424: 1 | H424: {=IFERROR(XLOOKUP(D424,'MASTER ITEM LIST'!A:A,'MASTER ITEM LIST'!D:D), "")} -> GAL | I424: 1630 | J424: =IF(G424="", "",G424*I424) -> 1630
A425: 46154 | C425: TRANSFER TO MIXING AREA | D425: NXU4406-4L | E425: {=IF(D425="", "", XLOOKUP(D425, 'MASTER ITEM LIST'!A:A, 'MASTER ITEM LIST'!B:B, ""))} -> NIPPON EXTREME QDU GREEN 4L | F425: ADJUSTMENT (-) | G425: 1 | H425: {=IFERROR(XLOOKUP(D425,'MASTER ITEM LIST'!A:A,'MASTER ITEM LIST'!D:D), "")} -> GAL | I425: 1630 | J425: =IF(G425="", "",G425*I425) -> 1630
A426: 46155 | C426: TRANSFER TO MIXING AREA | D426: NXU1587-4L | E426: {=IF(D426="", "", XLOOKUP(D426, 'MASTER ITEM LIST'!A:A, 'MASTER ITEM LIST'!B:B, ""))} -> NIPPON EXTREME QDU BLUE 4L | F426: ADJUSTMENT (-) | G426: 1 | H426: {=IFERROR(XLOOKUP(D426,'MASTER ITEM LIST'!A:A,'MASTER ITEM LIST'!D:D), "")} -> GAL | I426: 1630 | J426: =IF(G426="", "",G426*I426) -> 1630
A427: 46155 | C427: TRANSFER TO MIXING AREA | D427: NXU1965-4L | E427: {=IF(D427="", "", XLOOKUP(D427, 'MASTER ITEM LIST'!A:A, 'MASTER ITEM LIST'!B:B, ""))} -> NIPPON EXTREME QDU BLACK 4L | F427: ADJUSTMENT (-) | G427: 1 | H427: {=IFERROR(XLOOKUP(D427,'MASTER ITEM LIST'!A:A,'MASTER ITEM LIST'!D:D), "")} -> GAL | I427: 1485 | J427: =IF(G427="", "",G427*I427) -> 1485
A428: 46155 | C428: TRANSFER TO MIXING AREA | D428: NXU7391-4L | E428: {=IF(D428="", "", XLOOKUP(D428, 'MASTER ITEM LIST'!A:A, 'MASTER ITEM LIST'!B:B, ""))} -> NIPPON EXTREME QDU SILVER 4L | F428: ADJUSTMENT (-) | G428: 1 | H428: {=IFERROR(XLOOKUP(D428,'MASTER ITEM LIST'!A:A,'MASTER ITEM LIST'!D:D), "")} -> GAL | I428: 1485 | J428: =IF(G428="", "",G428*I428) -> 1485
A429: 46157 | C429: TRANSFER TO MIXING AREA | D429: MT100-1L | E429: {=IF(D429="", "", XLOOKUP(D429, 'MASTER ITEM LIST'!A:A, 'MASTER ITEM LIST'!B:B, ""))} -> NAX PREMILA MT100 WHITE HS 1L | F429: ADJUSTMENT (-) | G429: 1 | H429: {=IFERROR(XLOOKUP(D429,'MASTER ITEM LIST'!A:A,'MASTER ITEM LIST'!D:D), "")} -> LTR/S | I429: 1090 | J429: =IF(G429="", "",G429*I429) -> 1090
A430: 46157 | C430: TRANSFER TO MIXING AREA | D430: MT136 | E430: {=IF(D430="", "", XLOOKUP(D430, 'MASTER ITEM LIST'!A:A, 'MASTER ITEM LIST'!B:B, ""))} -> NAX PREMILA MT136 METALLIC ORANGE 1L | F430: ADJUSTMENT (-) | G430: 1 | H430: {=IFERROR(XLOOKUP(D430,'MASTER ITEM LIST'!A:A,'MASTER ITEM LIST'!D:D), "")} -> LTR/S | I430: 5050 | J430: =IF(G430="", "",G430*I430) -> 5050
A431: 46157 | C431: TRANSFER TO MIXING AREA | D431: PNB100 | E431: {=IF(D431="", "", XLOOKUP(D431, 'MASTER ITEM LIST'!A:A, 'MASTER ITEM LIST'!B:B, ""))} -> NAX PREMILA NB100 B/C BINDER 4L | F431: ADJUSTMENT (-) | G431: 1 | H431: {=IFERROR(XLOOKUP(D431,'MASTER ITEM LIST'!A:A,'MASTER ITEM LIST'!D:D), "")} -> GAL | I431: 2100 | J431: =IF(G431="", "",G431*I431) -> 2100
A432: 46157 | C432: TRANSFER TO MIXING AREA | D432: MT202-1L | E432: {=IF(D432="", "", XLOOKUP(D432, 'MASTER ITEM LIST'!A:A, 'MASTER ITEM LIST'!B:B, ""))} -> NAX PREMILA MT202 TINTING BLACK NP 1L | F432: ADJUSTMENT (-) | G432: 1 | H432: {=IFERROR(XLOOKUP(D432,'MASTER ITEM LIST'!A:A,'MASTER ITEM LIST'!D:D), "")} -> LTR/S | I432: 1090 | J432: =IF(G432="", "",G432*I432) -> 1090
... A458: 46174 | C458: TRANSFER TO MIXING AREA | D458: BSQDEW-GAL | E458: {=IF(D458="", "", XLOOKUP(D458, 'MASTER ITEM LIST'!A:A, 'MASTER ITEM LIST'!B:B, ""))} -> BOYSEN QDE WHITE GAL | F458: ADJUSTMENT (-) | G458: 1 | H458: {=IFERROR(XLOOKUP(D458,'MASTER ITEM LIST'!A:A,'MASTER ITEM LIST'!D:D), "")} -> GAL | I458: 834 | J458: =IF(G458="", "",G458*I458) -> 834
A459: 46175 | B459: CSI-004053 | C459: APC DISTRIBUTION - VALENCIA | D459: ROS-367 | E459: {=IF(D459="", "", XLOOKUP(D459, 'MASTER ITEM LIST'!A:A, 'MASTER ITEM LIST'!B:B, ""))} -> CANDY TUFF ROS-367 RAIN OR SHINE 4L | F459: STOCK IN | G459: 2 | H459: {=IFERROR(XLOOKUP(D459,'MASTER ITEM LIST'!A:A,'MASTER ITEM LIST'!D:D), "")} -> 4L | I459: 650 | J459: =IF(G459="", "",G459*I459) -> 1300
A460: 46175 | B460: CSI-004053 | C460: APC DISTRIBUTION - VALENCIA | D460: PRI3634 | E460: {=IF(D460="", "", XLOOKUP(D460, 'MASTER ITEM LIST'!A:A, 'MASTER ITEM LIST'!B:B, ""))} -> NAX ALPHA HB SPRAY FILLER GRAY WITH HARDENER 1L | F460: STOCK IN | G460: 12 | H460: {=IFERROR(XLOOKUP(D460,'MASTER ITEM LIST'!A:A,'MASTER ITEM LIST'!D:D), "")} -> LITER | I460: 500 | J460: =IF(G460="", "",G460*I460) -> 6000
A461: 46175 | B461: CSI-004053 | C461: APC DISTRIBUTION - VALENCIA | D461: NXU4406-4L | E461: {=IF(D461="", "", XLOOKUP(D461, 'MASTER ITEM LIST'!A:A, 'MASTER ITEM LIST'!B:B, ""))} -> NIPPON EXTREME QDU GREEN 4L | F461: STOCK IN | G461: 1 | H461: {=IFERROR(XLOOKUP(D461,'MASTER ITEM LIST'!A:A,'MASTER ITEM LIST'!D:D), "")} -> GAL | I461: 2000 | J461: =IF(G461="", "",G461*I461) -> 2000
A462: 46175 | B462: CSI-004053 | C462: APC DISTRIBUTION - VALENCIA | D462: NXU1587-4L | E462: {=IF(D462="", "", XLOOKUP(D462, 'MASTER ITEM LIST'!A:A, 'MASTER ITEM LIST'!B:B, ""))} -> NIPPON EXTREME QDU BLUE 4L | F462: STOCK IN | G462: 1 | H462: {=IFERROR(XLOOKUP(D462,'MASTER ITEM LIST'!A:A,'MASTER ITEM LIST'!D:D), "")} -> GAL | I462: 2000 | J462: =IF(G462="", "",G462*I462) -> 2000
A463: 46175 | B463: CSI-004053 | C463: APC DISTRIBUTION - VALENCIA | D463: MEG3602-4L | E463: {=IF(D463="", "", XLOOKUP(D463, 'MASTER ITEM LIST'!A:A, 'MASTER ITEM LIST'!B:B, ""))} -> METALGUARD EPOXY PRIMER GRAY WITH HARDENER 4L | F463: STOCK IN | G463: 1 | H463: {=IFERROR(XLOOKUP(D463,'MASTER ITEM LIST'!A:A,'MASTER ITEM LIST'!D:D), "")} -> GAL | I463: 1000 | J463: =IF(G463="", "",G463*I463) -> 1000
A464: 46175 | B464: CSI-004053 | C464: APC DISTRIBUTION - VALENCIA | D464: MT202-1L | E464: {=IF(D464="", "", XLOOKUP(D464, 'MASTER ITEM LIST'!A:A, 'MASTER ITEM LIST'!B:B, ""))} -> NAX PREMILA MT202 TINTING BLACK NP 1L | F464: STOCK IN | G464: 2 | H464: {=IFERROR(XLOOKUP(D464,'MASTER ITEM LIST'!A:A,'MASTER ITEM LIST'!D:D), "")} -> LTR/S | I464: 1450 | J464: =IF(G464="", "",G464*I464) -> 2900
A465: 46175 | B465: CSI-004053 | C465: APC DISTRIBUTION - VALENCIA | D465: PWTCO-2133 | E465: {=IF(D465="", "", XLOOKUP(D465, 'MASTER ITEM LIST'!A:A, 'MASTER ITEM LIST'!B:B, ""))} -> BULLETIN RED TINTING COLOR PWTCO-2133 1/4L PREMIUM WELCOAT | F465: STOCK IN | G465: 4 | H465: {=IFERROR(XLOOKUP(D465,'MASTER ITEM LIST'!A:A,'MASTER ITEM LIST'!D:D), "")} -> 1/4L | I465: 100 | J465: =IF(G465="", "",G465*I465) -> 400
A466: 46175 | B466: CSI-004053 | C466: APC DISTRIBUTION - VALENCIA | D466: ROS-TEMP-4L | E466: {=IF(D466="", "", XLOOKUP(D466, 'MASTER ITEM LIST'!A:A, 'MASTER ITEM LIST'!B:B, ""))} -> RAIN OR SHINE-TEMPTATION 4L | F466: STOCK IN | G466: 5 | H466: {=IFERROR(XLOOKUP(D466,'MASTER ITEM LIST'!A:A,'MASTER ITEM LIST'!D:D), "")} -> GALON | I466: 650 | J466: =IF(G466="", "",G466*I466) -> 3250
A467: 46175 | B467: CSI-004053 | C467: APC DISTRIBUTION - VALENCIA | D467: ROS- UH SO RED -4L | E467: {=IF(D467="", "", XLOOKUP(D467, 'MASTER ITEM LIST'!A:A, 'MASTER ITEM LIST'!B:B, ""))} -> RAIN OR SHINE- UH SO RED 4L | F467: STOCK IN | G467: 2 | H467: {=IFERROR(XLOOKUP(D467,'MASTER ITEM LIST'!A:A,'MASTER ITEM LIST'!D:D), "")} -> GALON | I467: 650 | J467: =IF(G467="", "",G467*I467) -> 1300
A468: 46175 | B468: CSI-004053 | C468: APC DISTRIBUTION - VALENCIA | D468: ROS- HAPPY DAYS-4L | E468: {=IF(D468="", "", XLOOKUP(D468, 'MASTER ITEM LIST'!A:A, 'MASTER ITEM LIST'!B:B, ""))} -> RAIN OR SHINE- HAPPY DAYS 4L | F468: STOCK IN | G468: 3 | H468: {=IFERROR(XLOOKUP(D468,'MASTER ITEM LIST'!A:A,'MASTER ITEM LIST'!D:D), "")} -> GALON | I468: 650 | J468: =IF(G468="", "",G468*I468) -> 1950
A469: 46175 | B469: CSI-004054 | C469: APC DISTRIBUTION - VALENCIA | D469: ROS-SG-4L | E469: {=IF(D469="", "", XLOOKUP(D469, 'MASTER ITEM LIST'!A:A, 'MASTER ITEM LIST'!B:B, ""))} -> RAIN OR SHINE STONE GRAY 4L | F469: STOCK IN | G469: 1 | H469: {=IFERROR(XLOOKUP(D469,'MASTER ITEM LIST'!A:A,'MASTER ITEM LIST'!D:D), "")} -> GALON | I469: 650 | J469: =IF(G469="", "",G469*I469) -> 650
A470: 46175 | B470: CSI-004054 | C470: APC DISTRIBUTION - VALENCIA | D470: PWTCO-6133 | E470: {=IF(D470="", "", XLOOKUP(D470, 'MASTER ITEM LIST'!A:A, 'MASTER ITEM LIST'!B:B, ""))} -> BURNT SIENNA TINTING COLOR PWTCO-6133 1/4L PREMIUM WELCOAT | F470: STOCK IN | G470: 1 | H470: {=IFERROR(XLOOKUP(D470,'MASTER ITEM LIST'!A:A,'MASTER ITEM LIST'!D:D), "")} -> 1/4L | I470: 100 | J470: =IF(G470="", "",G470*I470) -> 100
... A481: 46175 | B481: CSI-004055 | C481: APC DISTRIBUTION - VALENCIA | D481: 2B-PB#1 | E481: {=IF(D481="", "", XLOOKUP(D481, 'MASTER ITEM LIST'!A:A, 'MASTER ITEM LIST'!B:B, ""))} -> PAINT BRUSH 2B #1 | F481: STOCK IN | G481: 12 | H481: {=IFERROR(XLOOKUP(D481,'MASTER ITEM LIST'!A:A,'MASTER ITEM LIST'!D:D), "")} -> PC/S | I481: 18 | J481: =IF(G481="", "",G481*I481) -> 216
...

Sheet INVENTORY REPORT
A1: ITEM CODE | B1: DESCRIPTION | C1: COST | D1: UNIT | E1: AVAILABLE STOCKS | F1: STOCK OUT | G1: STOCK IN
A2: =IFERROR(__xludf.DUMMYFUNCTION("FILTER('MASTER ITEM LIST'!A2:E1296, 'MASTER ITEM LIST'!A2:A1296 <> """")"),"ROS-633") -> ROS-633 | B2: =IFERROR(__xludf.DUMMYFUNCTION("""COMPUTED_VALUE"""),"RAIN OR SHINE CHOCOLATE BROWN 4L") -> RAIN OR SHINE CHOCOLATE BROWN 4L | C2: =IFERROR(__xludf.DUMMYFUNCTION("""COMPUTED_VALUE"""),665.0) -> 665 | D2: =IFERROR(__xludf.DUMMYFUNCTION("""COMPUTED_VALUE"""),"GALON") -> GALON | E2: =IFERROR(__xludf.DUMMYFUNCTION("""COMPUTED_VALUE"""),0.0) -> 0 | F2: =SUMIF(SALES!D:D, A2, SALES!H:H) + SUMIFS('STOCK IN TRANSFER'!G:G, 'STOCK IN TRANSFER'!D:D, A2, 'STOCK IN TRANSFER'!F:F, "TRANSFER") + SUMIFS('STOCK IN TRANSFER'!G:G, 'STOCK IN TRANSFER'!D:D, A2, 'STOCK IN TRANSFER'!F:F, "ADJUSTMENT (-)") -> 0.25 | G2: =SUMIFS('STOCK IN TRANSFER'!G:G, 'STOCK IN TRANSFER'!D:D, A2, 'STOCK IN TRANSFER'!F:F, "STOCK IN") + SUMIFS('STOCK IN TRANSFER'!G:G, 'STOCK IN TRANSFER'!D:D, A2, 'STOCK IN TRANSFER'!F:F, "ADJUSTMENT (+)") -> 0.25
A3: =IFERROR(__xludf.DUMMYFUNCTION("""COMPUTED_VALUE"""),"ROSCB-1L") -> ROSCB-1L | B3: =IFERROR(__xludf.DUMMYFUNCTION("""COMPUTED_VALUE"""),"RAIN OR SHINE CHOCOLATE BROWN 1L") -> RAIN OR SHINE CHOCOLATE BROWN 1L | C3: =IFERROR(__xludf.DUMMYFUNCTION("""COMPUTED_VALUE"""),0.0) -> 0 | D3: =IFERROR(__xludf.DUMMYFUNCTION("""COMPUTED_VALUE"""),"LITER") -> LITER | E3: =IFERROR(__xludf.DUMMYFUNCTION("""COMPUTED_VALUE"""),0.0) -> 0 | F3: =SUMIF(SALES!D:D, A3, SALES!H:H) + SUMIFS('STOCK IN TRANSFER'!G:G, 'STOCK IN TRANSFER'!D:D, A3, 'STOCK IN TRANSFER'!F:F, "TRANSFER") + SUMIFS('STOCK IN TRANSFER'!G:G, 'STOCK IN TRANSFER'!D:D, A3, 'STOCK IN TRANSFER'!F:F, "ADJUSTMENT (-)") -> 1 | G3: =SUMIFS('STOCK IN TRANSFER'!G:G, 'STOCK IN TRANSFER'!D:D, A3, 'STOCK IN TRANSFER'!F:F, "STOCK IN") + SUMIFS('STOCK IN TRANSFER'!G:G, 'STOCK IN TRANSFER'!D:D, A3, 'STOCK IN TRANSFER'!F:F, "ADJUSTMENT (+)") -> 1
A4: =IFERROR(__xludf.DUMMYFUNCTION("""COMPUTED_VALUE"""),"ROS-701") -> ROS-701 | B4: =IFERROR(__xludf.DUMMYFUNCTION("""COMPUTED_VALUE"""),"RAIN OR SHINE BAGUIO GREEN 4L") -> RAIN OR SHINE BAGUIO GREEN 4L | C4: =IFERROR(__xludf.DUMMYFUNCTION("""COMPUTED_VALUE"""),665.0) -> 665 | D4: =IFERROR(__xludf.DUMMYFUNCTION("""COMPUTED_VALUE"""),"GALON") -> GALON | E4: =IFERROR(__xludf.DUMMYFUNCTION("""COMPUTED_VALUE"""),0.0) -> 0 | F4: =SUMIF(SALES!D:D, A4, SALES!H:H) + SUMIFS('STOCK IN TRANSFER'!G:G, 'STOCK IN TRANSFER'!D:D, A4, 'STOCK IN TRANSFER'!F:F, "TRANSFER") + SUMIFS('STOCK IN TRANSFER'!G:G, 'STOCK IN TRANSFER'!D:D, A4, 'STOCK IN TRANSFER'!F:F, "ADJUSTMENT (-)") -> 6 | G4: =SUMIFS('STOCK IN TRANSFER'!G:G, 'STOCK IN TRANSFER'!D:D, A4, 'STOCK IN TRANSFER'!F:F, "STOCK IN") + SUMIFS('STOCK IN TRANSFER'!G:G, 'STOCK IN TRANSFER'!D:D, A4, 'STOCK IN TRANSFER'!F:F, "ADJUSTMENT (+)") -> 6
A5: =IFERROR(__xludf.DUMMYFUNCTION("""COMPUTED_VALUE"""),"POLYGTHIN-4L") -> POLYGTHIN-4L | B5: =IFERROR(__xludf.DUMMYFUNCTION("""COMPUTED_VALUE"""),"POLYGLOSS URETHANE THINNER 4L") -> POLYGLOSS URETHANE THINNER 4L | C5: =IFERROR(__xludf.DUMMYFUNCTION("""COMPUTED_VALUE"""),675.0) -> 675 | D5: =IFERROR(__xludf.DUMMYFUNCTION("""COMPUTED_VALUE"""),"GALON") -> GALON | E5: =IFERROR(__xludf.DUMMYFUNCTION("""COMPUTED_VALUE"""),0.0) -> 0 | F5: =SUMIF(SALES!D:D, A5, SALES!H:H) + SUMIFS('STOCK IN TRANSFER'!G:G, 'STOCK IN TRANSFER'!D:D, A5, 'STOCK IN TRANSFER'!F:F, "TRANSFER") + SUMIFS('STOCK IN TRANSFER'!G:G, 'STOCK IN TRANSFER'!D:D, A5, 'STOCK IN TRANSFER'!F:F, "ADJUSTMENT (-)") -> 9.75 | G5: =SUMIFS('STOCK IN TRANSFER'!G:G, 'STOCK IN TRANSFER'!D:D, A5, 'STOCK IN TRANSFER'!F:F, "STOCK IN") + SUMIFS('STOCK IN TRANSFER'!G:G, 'STOCK IN TRANSFER'!D:D, A5, 'STOCK IN TRANSFER'!F:F, "ADJUSTMENT (+)") -> 9.75
A6: =IFERROR(__xludf.DUMMYFUNCTION("""COMPUTED_VALUE"""),"PGTB-4L") -> PGTB-4L | B6: =IFERROR(__xludf.DUMMYFUNCTION("""COMPUTED_VALUE"""),"POLYGLOSS PU PHTHALO BLUE 4L") -> POLYGLOSS PU PHTHALO BLUE 4L | C6: =IFERROR(__xludf.DUMMYFUNCTION("""COMPUTED_VALUE"""),1883.0) -> 1883 | D6: =IFERROR(__xludf.DUMMYFUNCTION("""COMPUTED_VALUE"""),"GALON") -> GALON | E6: =IFERROR(__xludf.DUMMYFUNCTION("""COMPUTED_VALUE"""),0.0) -> 0 | F6: =SUMIF(SALES!D:D, A6, SALES!H:H) + SUMIFS('STOCK IN TRANSFER'!G:G, 'STOCK IN TRANSFER'!D:D, A6, 'STOCK IN TRANSFER'!F:F, "TRANSFER") + SUMIFS('STOCK IN TRANSFER'!G:G, 'STOCK IN TRANSFER'!D:D, A6, 'STOCK IN TRANSFER'!F:F, "ADJUSTMENT (-)") -> 0.25 | G6: =SUMIFS('STOCK IN TRANSFER'!G:G, 'STOCK IN TRANSFER'!D:D, A6, 'STOCK IN TRANSFER'!F:F, "STOCK IN") + SUMIFS('STOCK IN TRANSFER'!G:G, 'STOCK IN TRANSFER'!D:D, A6, 'STOCK IN TRANSFER'!F:F, "ADJUSTMENT (+)") -> 0.25
A7: =IFERROR(__xludf.DUMMYFUNCTION("""COMPUTED_VALUE"""),"PGMF-4L") -> PGMF-4L | B7: =IFERROR(__xludf.DUMMYFUNCTION("""COMPUTED_VALUE"""),"POLYGLOSS PU MICA RED FINE 4L") -> POLYGLOSS PU MICA RED FINE 4L | C7: =IFERROR(__xludf.DUMMYFUNCTION("""COMPUTED_VALUE"""),2822.0) -> 2822 | D7: =IFERROR(__xludf.DUMMYFUNCTION("""COMPUTED_VALUE"""),"GALON") -> GALON | E7: =IFERROR(__xludf.DUMMYFUNCTION("""COMPUTED_VALUE"""),0.0) -> 0 | F7: =SUMIF(SALES!D:D, A7, SALES!H:H) + SUMIFS('STOCK IN TRANSFER'!G:G, 'STOCK IN TRANSFER'!D:D, A7, 'STOCK IN TRANSFER'!F:F, "TRANSFER") + SUMIFS('STOCK IN TRANSFER'!G:G, 'STOCK IN TRANSFER'!D:D, A7, 'STOCK IN TRANSFER'!F:F, "ADJUSTMENT (-)") -> 0.5 | G7: =SUMIFS('STOCK IN TRANSFER'!G:G, 'STOCK IN TRANSFER'!D:D, A7, 'STOCK IN TRANSFER'!F:F, "STOCK IN") + SUMIFS('STOCK IN TRANSFER'!G:G, 'STOCK IN TRANSFER'!D:D, A7, 'STOCK IN TRANSFER'!F:F, "ADJUSTMENT (+)") -> 0.5
A8: =IFERROR(__xludf.DUMMYFUNCTION("""COMPUTED_VALUE"""),"PGMC-4L") -> PGMC-4L | B8: =IFERROR(__xludf.DUMMYFUNCTION("""COMPUTED_VALUE"""),"POLYGLOSS PU METALLIC COARSE 4L") -> POLYGLOSS PU METALLIC COARSE 4L | C8: =IFERROR(__xludf.DUMMYFUNCTION("""COMPUTED_VALUE"""),1743.0) -> 1743 | D8: =IFERROR(__xludf.DUMMYFUNCTION("""COMPUTED_VALUE"""),"GALON") -> GALON | E8: =IFERROR(__xludf.DUMMYFUNCTION("""COMPUTED_VALUE"""),0.0) -> 0 | F8: =SUMIF(SALES!D:D, A8, SALES!H:H) + SUMIFS('STOCK IN TRANSFER'!G:G, 'STOCK IN TRANSFER'!D:D, A8, 'STOCK IN TRANSFER'!F:F, "TRANSFER") + SUMIFS('STOCK IN TRANSFER'!G:G, 'STOCK IN TRANSFER'!D:D, A8, 'STOCK IN TRANSFER'!F:F, "ADJUSTMENT (-)") -> 1.0625 | G8: =SUMIFS('STOCK IN TRANSFER'!G:G, 'STOCK IN TRANSFER'!D:D, A8, 'STOCK IN TRANSFER'!F:F, "STOCK IN") + SUMIFS('STOCK IN TRANSFER'!G:G, 'STOCK IN TRANSFER'!D:D, A8, 'STOCK IN TRANSFER'!F:F, "ADJUSTMENT (+)") -> 1.0625
A9: =IFERROR(__xludf.DUMMYFUNCTION("""COMPUTED_VALUE"""),"PGJB-4L") -> PGJB-4L | B9: =IFERROR(__xludf.DUMMYFUNCTION("""COMPUTED_VALUE"""),"POLYGLOSS PU JET BLACK 4L") -> POLYGLOSS PU JET BLACK 4L | C9: =IFERROR(__xludf.DUMMYFUNCTION("""COMPUTED_VALUE"""),1828.0) -> 1828 | D9: =IFERROR(__xludf.DUMMYFUNCTION("""COMPUTED_VALUE"""),"GALON") -> GALON | E9: =IFERROR(__xludf.DUMMYFUNCTION("""COMPUTED_VALUE"""),0.0) -> 0 | F9: =SUMIF(SALES!D:D, A9, SALES!H:H) + SUMIFS('STOCK IN TRANSFER'!G:G, 'STOCK IN TRANSFER'!D:D, A9, 'STOCK IN TRANSFER'!F:F, "TRANSFER") + SUMIFS('STOCK IN TRANSFER'!G:G, 'STOCK IN TRANSFER'!D:D, A9, 'STOCK IN TRANSFER'!F:F, "ADJUSTMENT (-)") -> 2.625 | G9: =SUMIFS('STOCK IN TRANSFER'!G:G, 'STOCK IN TRANSFER'!D:D, A9, 'STOCK IN TRANSFER'!F:F, "STOCK IN") + SUMIFS('STOCK IN TRANSFER'!G:G, 'STOCK IN TRANSFER'!D:D, A9, 'STOCK IN TRANSFER'!F:F, "ADJUSTMENT (+)") -> 2.625
A10: =IFERROR(__xludf.DUMMYFUNCTION("""COMPUTED_VALUE"""),"PGFB-4L") -> PGFB-4L | B10: =IFERROR(__xludf.DUMMYFUNCTION("""COMPUTED_VALUE"""),"POLYGLOSS PU FLAT BLACK 4L") -> POLYGLOSS PU FLAT BLACK 4L | C10: =IFERROR(__xludf.DUMMYFUNCTION("""COMPUTED_VALUE"""),1930.0) -> 1930 | D10: =IFERROR(__xludf.DUMMYFUNCTION("""COMPUTED_VALUE"""),"GALON") -> GALON | E10: =IFERROR(__xludf.DUMMYFUNCTION("""COMPUTED_VALUE"""),0.0) -> 0 | F10: =SUMIF(SALES!D:D, A10, SALES!H:H) + SUMIFS('STOCK IN TRANSFER'!G:G, 'STOCK IN TRANSFER'!D:D, A10, 'STOCK IN TRANSFER'!F:F, "TRANSFER") + SUMIFS('STOCK IN TRANSFER'!G:G, 'STOCK IN TRANSFER'!D:D, A10, 'STOCK IN TRANSFER'!F:F, "ADJUSTMENT (-)") -> 2.71875 | G10: =SUMIFS('STOCK IN TRANSFER'!G:G, 'STOCK IN TRANSFER'!D:D, A10, 'STOCK IN TRANSFER'!F:F, "STOCK IN") + SUMIFS('STOCK IN TRANSFER'!G:G, 'STOCK IN TRANSFER'!D:D, A10, 'STOCK IN TRANSFER'!F:F, "ADJUSTMENT (+)") -> 2.71875
A11: =IFERROR(__xludf.DUMMYFUNCTION("""COMPUTED_VALUE"""),"PGANTI-C-1L") -> PGANTI-C-1L | B11: =IFERROR(__xludf.DUMMYFUNCTION("""COMPUTED_VALUE"""),"POLYGLOSS ANTI-CORROSSION") -> POLYGLOSS ANTI-CORROSSION | C11: =IFERROR(__xludf.DUMMYFUNCTION("""COMPUTED_VALUE"""),440.0) -> 440 | D11: =IFERROR(__xludf.DUMMYFUNCTION("""COMPUTED_VALUE"""),"LITER") -> LITER | E11: =IFERROR(__xludf.DUMMYFUNCTION("""COMPUTED_VALUE"""),3.0) -> 3 | F11: =SUMIF(SALES!D:D, A11, SALES!H:H) + SUMIFS('STOCK IN TRANSFER'!G:G, 'STOCK IN TRANSFER'!D:D, A11, 'STOCK IN TRANSFER'!F:F, "TRANSFER") + SUMIFS('STOCK IN TRANSFER'!G:G, 'STOCK IN TRANSFER'!D:D, A11, 'STOCK IN TRANSFER'!F:F, "ADJUSTMENT (-)") -> 3.5 | G11: =SUMIFS('STOCK IN TRANSFER'!G:G, 'STOCK IN TRANSFER'!D:D, A11, 'STOCK IN TRANSFER'!F:F, "STOCK IN") + SUMIFS('STOCK IN TRANSFER'!G:G, 'STOCK IN TRANSFER'!D:D, A11, 'STOCK IN TRANSFER'!F:F, "ADJUSTMENT (+)") -> 6.5
A12: =IFERROR(__xludf.DUMMYFUNCTION("""COMPUTED_VALUE"""),"PLQDW-4L") -> PLQDW-4L | B12: =IFERROR(__xludf.DUMMYFUNCTION("""COMPUTED_VALUE"""),"PLATONE QDE WHITE 4L") -> PLATONE QDE WHITE 4L | C12: =IFERROR(__xludf.DUMMYFUNCTION("""COMPUTED_VALUE"""),650.0) -> 650 | D12: =IFERROR(__xludf.DUMMYFUNCTION("""COMPUTED_VALUE"""),"GAL") -> GAL | E12: =IFERROR(__xludf.DUMMYFUNCTION("""COMPUTED_VALUE"""),0.0) -> 0 | F12: =SUMIF(SALES!D:D, A12, SALES!H:H) + SUMIFS('STOCK IN TRANSFER'!G:G, 'STOCK IN TRANSFER'!D:D, A12, 'STOCK IN TRANSFER'!F:F, "TRANSFER") + SUMIFS('STOCK IN TRANSFER'!G:G, 'STOCK IN TRANSFER'!D:D, A12, 'STOCK IN TRANSFER'!F:F, "ADJUSTMENT (-)") -> 2 | G12: =SUMIFS('STOCK IN TRANSFER'!G:G, 'STOCK IN TRANSFER'!D:D, A12, 'STOCK IN TRANSFER'!F:F, "STOCK IN") + SUMIFS('STOCK IN TRANSFER'!G:G, 'STOCK IN TRANSFER'!D:D, A12, 'STOCK IN TRANSFER'!F:F, "ADJUSTMENT (+)") -> 2
A13: =IFERROR(__xludf.DUMMYFUNCTION("""COMPUTED_VALUE"""),"PLQDB-1L") -> PLQDB-1L | B13: =IFERROR(__xludf.DUMMYFUNCTION("""COMPUTED_VALUE"""),"PLATONE QDE BLACK 1L") -> PLATONE QDE BLACK 1L | C13: =IFERROR(__xludf.DUMMYFUNCTION("""COMPUTED_VALUE"""),0.0) -> 0 | D13: =IFERROR(__xludf.DUMMYFUNCTION("""COMPUTED_VALUE"""),"LITER") -> LITER | E13: =IFERROR(__xludf.DUMMYFUNCTION("""COMPUTED_VALUE"""),0.0) -> 0 | F13: =SUMIF(SALES!D:D, A13, SALES!H:H) + SUMIFS('STOCK IN TRANSFER'!G:G, 'STOCK IN TRANSFER'!D:D, A13, 'STOCK IN TRANSFER'!F:F, "TRANSFER") + SUMIFS('STOCK IN TRANSFER'!G:G, 'STOCK IN TRANSFER'!D:D, A13, 'STOCK IN TRANSFER'!F:F, "ADJUSTMENT (-)") -> 0.1875 | G13: =SUMIFS('STOCK IN TRANSFER'!G:G, 'STOCK IN TRANSFER'!D:D, A13, 'STOCK IN TRANSFER'!F:F, "STOCK IN") + SUMIFS('STOCK IN TRANSFER'!G:G, 'STOCK IN TRANSFER'!D:D, A13, 'STOCK IN TRANSFER'!F:F, "ADJUSTMENT (+)") -> 0.1875
A14: =IFERROR(__xludf.DUMMYFUNCTION("""COMPUTED_VALUE"""),"SEALERMAX5170-4L") -> SEALERMAX5170-4L | B14: =IFERROR(__xludf.DUMMYFUNCTION("""COMPUTED_VALUE"""),"NIPPON SEALERMAX 5170 4L") -> NIPPON SEALERMAX 5170 4L | C14: =IFERROR(__xludf.DUMMYFUNCTION("""COMPUTED_VALUE"""),960.0) -> 960 | D14: =IFERROR(__xludf.DUMMYFUNCTION("""COMPUTED_VALUE"""),"GAL/S") -> GAL/S | E14: =IFERROR(__xludf.DUMMYFUNCTION("""COMPUTED_VALUE"""),0.0) -> 0 | F14: =SUMIF(SALES!D:D, A14, SALES!H:H) + SUMIFS('STOCK IN TRANSFER'!G:G, 'STOCK IN TRANSFER'!D:D, A14, 'STOCK IN TRANSFER'!F:F, "TRANSFER") + SUMIFS('STOCK IN TRANSFER'!G:G, 'STOCK IN TRANSFER'!D:D, A14, 'STOCK IN TRANSFER'!F:F, "ADJUSTMENT (-)") -> 0.5 | G14: =SUMIFS('STOCK IN TRANSFER'!G:G, 'STOCK IN TRANSFER'!D:D, A14, 'STOCK IN TRANSFER'!F:F, "STOCK IN") + SUMIFS('STOCK IN TRANSFER'!G:G, 'STOCK IN TRANSFER'!D:D, A14, 'STOCK IN TRANSFER'!F:F, "ADJUSTMENT (+)") -> 0.5
A15: =IFERROR(__xludf.DUMMYFUNCTION("""COMPUTED_VALUE"""),"NPR7") -> NPR7 | B15: =IFERROR(__xludf.DUMMYFUNCTION("""COMPUTED_VALUE"""),"NIPPON ROLLER PAINT #7") -> NIPPON ROLLER PAINT #7 | C15: =IFERROR(__xludf.DUMMYFUNCTION("""COMPUTED_VALUE"""),0.0) -> 0 | D15: =IFERROR(__xludf.DUMMYFUNCTION("""COMPUTED_VALUE"""),"PC/S") -> PC/S | E15: =IFERROR(__xludf.DUMMYFUNCTION("""COMPUTED_VALUE"""),0.0) -> 0 | F15: =SUMIF(SALES!D:D, A15, SALES!H:H) + SUMIFS('STOCK IN TRANSFER'!G:G, 'STOCK IN TRANSFER'!D:D, A15, 'STOCK IN TRANSFER'!F:F, "TRANSFER") + SUMIFS('STOCK IN TRANSFER'!G:G, 'STOCK IN TRANSFER'!D:D, A15, 'STOCK IN TRANSFER'!F:F, "ADJUSTMENT (-)") -> 2 | G15: =SUMIFS('STOCK IN TRANSFER'!G:G, 'STOCK IN TRANSFER'!D:D, A15, 'STOCK IN TRANSFER'!F:F, "STOCK IN") + SUMIFS('STOCK IN TRANSFER'!G:G, 'STOCK IN TRANSFER'!D:D, A15, 'STOCK IN TRANSFER'!F:F, "ADJUSTMENT (+)") -> 2
A16: =IFERROR(__xludf.DUMMYFUNCTION("""COMPUTED_VALUE"""),"SOB757") -> SOB757 | B16: =IFERROR(__xludf.DUMMYFUNCTION("""COMPUTED_VALUE"""),"NAX SOB757 HIGH GRADE URETHANE THINNER 4L") -> NAX SOB757 HIGH GRADE URETHANE THINNER 4L | C16: =IFERROR(__xludf.DUMMYFUNCTION("""COMPUTED_VALUE"""),570.0) -> 570 | D16: =IFERROR(__xludf.DUMMYFUNCTION("""COMPUTED_VALUE"""),"GAL") -> GAL | E16: =IFERROR(__xludf.DUMMYFUNCTION("""COMPUTED_VALUE"""),-3.012500000000003) -> -3.0125 | F16: =SUMIF(SALES!D:D, A16, SALES!H:H) + SUMIFS('STOCK IN TRANSFER'!G:G, 'STOCK IN TRANSFER'!D:D, A16, 'STOCK IN TRANSFER'!F:F, "TRANSFER") + SUMIFS('STOCK IN TRANSFER'!G:G, 'STOCK IN TRANSFER'!D:D, A16, 'STOCK IN TRANSFER'!F:F, "ADJUSTMENT (-)") -> 118.075 | G16: =SUMIFS('STOCK IN TRANSFER'!G:G, 'STOCK IN TRANSFER'!D:D, A16, 'STOCK IN TRANSFER'!F:F, "STOCK IN") + SUMIFS('STOCK IN TRANSFER'!G:G, 'STOCK IN TRANSFER'!D:D, A16, 'STOCK IN TRANSFER'!F:F, "ADJUSTMENT (+)") -> 115.0625
A17: =IFERROR(__xludf.DUMMYFUNCTION("""COMPUTED_VALUE"""),"BSAXGLWHTE-4L") -> BSAXGLWHTE-4L | B17: =IFERROR(__xludf.DUMMYFUNCTION("""COMPUTED_VALUE"""),"BOYSEN ACRYTEX GLOSS WHITE 4L (DOUBLE ENTRY)") -> BOYSEN ACRYTEX GLOSS WHITE 4L (DOUBLE ENTRY) | C17: =IFERROR(__xludf.DUMMYFUNCTION("""COMPUTED_VALUE"""),1080.0) -> 1080 | D17: =IFERROR(__xludf.DUMMYFUNCTION("""COMPUTED_VALUE"""),"GALON") -> GALON | E17: =IFERROR(__xludf.DUMMYFUNCTION("""COMPUTED_VALUE"""),0.0) -> 0 | F17: =SUMIF(SALES!D:D, A17, SALES!H:H) + SUMIFS('STOCK IN TRANSFER'!G:G, 'STOCK IN TRANSFER'!D:D, A17, 'STOCK IN TRANSFER'!F:F, "TRANSFER") + SUMIFS('STOCK IN TRANSFER'!G:G, 'STOCK IN TRANSFER'!D:D, A17, 'STOCK IN TRANSFER'!F:F, "ADJUSTMENT (-)") -> 2 | G17: =SUMIFS('STOCK IN TRANSFER'!G:G, 'STOCK IN TRANSFER'!D:D, A17, 'STOCK IN TRANSFER'!F:F, "STOCK IN") + SUMIFS('STOCK IN TRANSFER'!G:G, 'STOCK IN TRANSFER'!D:D, A17, 'STOCK IN TRANSFER'!F:F, "ADJUSTMENT (+)") -> 2
A18: =IFERROR(__xludf.DUMMYFUNCTION("""COMPUTED_VALUE"""),"B-1710") -> B-1710 | B18: =IFERROR(__xludf.DUMMYFUNCTION("""COMPUTED_VALUE"""),"BOYSEN ACRYTEX GLOSS WHITE 4L") -> BOYSEN ACRYTEX GLOSS WHITE 4L | C18: =IFERROR(__xludf.DUMMYFUNCTION("""COMPUTED_VALUE"""),1096.0) -> 1096 | D18: =IFERROR(__xludf.DUMMYFUNCTION("""COMPUTED_VALUE"""),"GALON") -> GALON | E18: =IFERROR(__xludf.DUMMYFUNCTION("""COMPUTED_VALUE"""),0.0) -> 0 | F18: =SUMIF(SALES!D:D, A18, SALES!H:H) + SUMIFS('STOCK IN TRANSFER'!G:G, 'STOCK IN TRANSFER'!D:D, A18, 'STOCK IN TRANSFER'!F:F, "TRANSFER") + SUMIFS('STOCK IN TRANSFER'!G:G, 'STOCK IN TRANSFER'!D:D, A18, 'STOCK IN TRANSFER'!F:F, "ADJUSTMENT (-)") -> 6 | G18: =SUMIFS('STOCK IN TRANSFER'!G:G, 'STOCK IN TRANSFER'!D:D, A18, 'STOCK IN TRANSFER'!F:F, "STOCK IN") + SUMIFS('STOCK IN TRANSFER'!G:G, 'STOCK IN TRANSFER'!D:D, A18, 'STOCK IN TRANSFER'!F:F, "ADJUSTMENT (+)") -> 6
A19: =IFERROR(__xludf.DUMMYFUNCTION("""COMPUTED_VALUE"""),"UTMIX-1L") -> UTMIX-1L | B19: =IFERROR(__xludf.DUMMYFUNCTION("""COMPUTED_VALUE"""),"URETHANE MIXING POLYGLOSS, DO IT 1L") -> URETHANE MIXING POLYGLOSS, DO IT 1L | C19: =IFERROR(__xludf.DUMMYFUNCTION("""COMPUTED_VALUE"""),850.0) -> 850 | D19: =IFERROR(__xludf.DUMMYFUNCTION("""COMPUTED_VALUE"""),"LITER") -> LITER | E19: =IFERROR(__xludf.DUMMYFUNCTION("""COMPUTED_VALUE"""),29.25) -> 29.25 | F19: =SUMIF(SALES!D:D, A19, SALES!H:H) + SUMIFS('STOCK IN TRANSFER'!G:G, 'STOCK IN TRANSFER'!D:D, A19, 'STOCK IN TRANSFER'!F:F, "TRANSFER") + SUMIFS('STOCK IN TRANSFER'!G:G, 'STOCK IN TRANSFER'!D:D, A19, 'STOCK IN TRANSFER'!F:F, "ADJUSTMENT (-)") -> 6.25 | G19: =SUMIFS('STOCK IN TRANSFER'!G:G, 'STOCK IN TRANSFER'!D:D, A19, 'STOCK IN TRANSFER'!F:F, "STOCK IN") + SUMIFS('STOCK IN TRANSFER'!G:G, 'STOCK IN TRANSFER'!D:D, A19, 'STOCK IN TRANSFER'!F:F, "ADJUSTMENT (+)") -> 35.5
A20: =IFERROR(__xludf.DUMMYFUNCTION("""COMPUTED_VALUE"""),"ROS- HAPPY DAYS-4L") -> ROS- HAPPY DAYS-4L | B20: =IFERROR(__xludf.DUMMYFUNCTION("""COMPUTED_VALUE"""),"RAIN OR SHINE- HAPPY DAYS 4L") -> RAIN OR SHINE- HAPPY DAYS 4L | C20: =IFERROR(__xludf.DUMMYFUNCTION("""COMPUTED_VALUE"""),650.0) -> 650 | D20: =IFERROR(__xludf.DUMMYFUNCTION("""COMPUTED_VALUE"""),"GALON") -> GALON | E20: =IFERROR(__xludf.DUMMYFUNCTION("""COMPUTED_VALUE"""),0.0) -> 0 | F20: =SUMIF(SALES!D:D, A20, SALES!H:H) + SUMIFS('STOCK IN TRANSFER'!G:G, 'STOCK IN TRANSFER'!D:D, A20, 'STOCK IN TRANSFER'!F:F, "TRANSFER") + SUMIFS('STOCK IN TRANSFER'!G:G, 'STOCK IN TRANSFER'!D:D, A20, 'STOCK IN TRANSFER'!F:F, "ADJUSTMENT (-)") -> 7 | G20: =SUMIFS('STOCK IN TRANSFER'!G:G, 'STOCK IN TRANSFER'!D:D, A20, 'STOCK IN TRANSFER'!F:F, "STOCK IN") + SUMIFS('STOCK IN TRANSFER'!G:G, 'STOCK IN TRANSFER'!D:D, A20, 'STOCK IN TRANSFER'!F:F, "ADJUSTMENT (+)") -> 7
A21: =IFERROR(__xludf.DUMMYFUNCTION("""COMPUTED_VALUE"""),"POLY- BT-ALUM-4L") -> POLY- BT-ALUM-4L | B21: =IFERROR(__xludf.DUMMYFUNCTION("""COMPUTED_VALUE"""),"POLYGLOSS-BRIGHT ALUMINUM 4L") -> POLYGLOSS-BRIGHT ALUMINUM 4L | C21: =IFERROR(__xludf.DUMMYFUNCTION("""COMPUTED_VALUE"""),1950.0) -> 1950 | D21: =IFERROR(__xludf.DUMMYFUNCTION("""COMPUTED_VALUE"""),"GALON") -> GALON | E21: =IFERROR(__xludf.DUMMYFUNCTION("""COMPUTED_VALUE"""),0.0) -> 0 | F21: =SUMIF(SALES!D:D, A21, SALES!H:H) + SUMIFS('STOCK IN TRANSFER'!G:G, 'STOCK IN TRANSFER'!D:D, A21, 'STOCK IN TRANSFER'!F:F, "TRANSFER") + SUMIFS('STOCK IN TRANSFER'!G:G, 'STOCK IN TRANSFER'!D:D, A21, 'STOCK IN TRANSFER'!F:F, "ADJUSTMENT (-)") -> 1.125 | G21: =SUMIFS('STOCK IN TRANSFER'!G:G, 'STOCK IN TRANSFER'!D:D, A21, 'STOCK IN TRANSFER'!F:F, "STOCK IN") + SUMIFS('STOCK IN TRANSFER'!G:G, 'STOCK IN TRANSFER'!D:D, A21, 'STOCK IN TRANSFER'!F:F, "ADJUSTMENT (+)") -> 1.125
A22: =IFERROR(__xludf.DUMMYFUNCTION("""COMPUTED_VALUE"""),"ACRY- REDUCER-4L") -> ACRY- REDUCER-4L | B22: =IFERROR(__xludf.DUMMYFUNCTION("""COMPUTED_VALUE"""),"ALPHA CHROMA ACRYTILE REDUCER") -> ALPHA CHROMA ACRYTILE REDUCER | C22: =IFERROR(__xludf.DUMMYFUNCTION("""COMPUTED_VALUE"""),550.0) -> 550 | D22: =IFERROR(__xludf.DUMMYFUNCTION("""COMPUTED_VALUE"""),"GALON") -> GALON | E22: =IFERROR(__xludf.DUMMYFUNCTION("""COMPUTED_VALUE"""),0.0) -> 0 | F22: =SUMIF(SALES!D:D, A22, SALES!H:H) + SUMIFS('STOCK IN TRANSFER'!G:G, 'STOCK IN TRANSFER'!D:D, A22, 'STOCK IN TRANSFER'!F:F, "TRANSFER") + SUMIFS('STOCK IN TRANSFER'!G:G, 'STOCK IN TRANSFER'!D:D, A22, 'STOCK IN TRANSFER'!F:F, "ADJUSTMENT (-)") -> 1 | G22: =SUMIFS('STOCK IN TRANSFER'!G:G, 'STOCK IN TRANSFER'!D:D, A22, 'STOCK IN TRANSFER'!F:F, "STOCK IN") + SUMIFS('STOCK IN TRANSFER'!G:G, 'STOCK IN TRANSFER'!D:D, A22, 'STOCK IN TRANSFER'!F:F, "ADJUSTMENT (+)") -> 1
A23: =IFERROR(__xludf.DUMMYFUNCTION("""COMPUTED_VALUE"""),"ROS-SR-100") -> ROS-SR-100 | B23: =IFERROR(__xludf.DUMMYFUNCTION("""COMPUTED_VALUE"""),"WHITE SUN ROOF ROS-SR-100 RAIN OR SHINE 4L") -> WHITE SUN ROOF ROS-SR-100 RAIN OR SHINE 4L | C23: =IFERROR(__xludf.DUMMYFUNCTION("""COMPUTED_VALUE"""),672.4) -> 672.4 | D23: =IFERROR(__xludf.DUMMYFUNCTION("""COMPUTED_VALUE"""),"4L") -> 4L | E23: =IFERROR(__xludf.DUMMYFUNCTION("""COMPUTED_VALUE"""),2.0) -> 2 | F23: =SUMIF(SALES!D:D, A23, SALES!H:H) + SUMIFS('STOCK IN TRANSFER'!G:G, 'STOCK IN TRANSFER'!D:D, A23, 'STOCK IN TRANSFER'!F:F, "TRANSFER") + SUMIFS('STOCK IN TRANSFER'!G:G, 'STOCK IN TRANSFER'!D:D, A23, 'STOCK IN TRANSFER'!F:F, "ADJUSTMENT (-)") -> 2 | G23: =SUMIFS('STOCK IN TRANSFER'!G:G, 'STOCK IN TRANSFER'!D:D, A23, 'STOCK IN TRANSFER'!F:F, "STOCK IN") + SUMIFS('STOCK IN TRANSFER'!G:G, 'STOCK IN TRANSFER'!D:D, A23, 'STOCK IN TRANSFER'!F:F, "ADJUSTMENT (+)") -> 4
A24: =IFERROR(__xludf.DUMMYFUNCTION("""COMPUTED_VALUE"""),"WRSGW-4L") -> WRSGW-4L | B24: =IFERROR(__xludf.DUMMYFUNCTION("""COMPUTED_VALUE"""),"WELCOAT REGULAR SEMI-GLOSS LATEX WHITE 4L") -> WELCOAT REGULAR SEMI-GLOSS LATEX WHITE 4L | C24: =IFERROR(__xludf.DUMMYFUNCTION("""COMPUTED_VALUE"""),558.0) -> 558 | D24: =IFERROR(__xludf.DUMMYFUNCTION("""COMPUTED_VALUE"""),"GALON") -> GALON | E24: =IFERROR(__xludf.DUMMYFUNCTION("""COMPUTED_VALUE"""),0.0) -> 0 | F24: =SUMIF(SALES!D:D, A24, SALES!H:H) + SUMIFS('STOCK IN TRANSFER'!G:G, 'STOCK IN TRANSFER'!D:D, A24, 'STOCK IN TRANSFER'!F:F, "TRANSFER") + SUMIFS('STOCK IN TRANSFER'!G:G, 'STOCK IN TRANSFER'!D:D, A24, 'STOCK IN TRANSFER'!F:F, "ADJUSTMENT (-)") -> 0 | G24: =SUMIFS('STOCK IN TRANSFER'!G:G, 'STOCK IN TRANSFER'!D:D, A24, 'STOCK IN TRANSFER'!F:F, "STOCK IN") + SUMIFS('STOCK IN TRANSFER'!G:G, 'STOCK IN TRANSFER'!D:D, A24, 'STOCK IN TRANSFER'!F:F, "ADJUSTMENT (+)") -> 0
A25: =IFERROR(__xludf.DUMMYFUNCTION("""COMPUTED_VALUE"""),"WQD1000-4L") -> WQD1000-4L | B25: =IFERROR(__xludf.DUMMYFUNCTION("""COMPUTED_VALUE"""),"WELCOAT REGULAR QDE WHITE 4L") -> WELCOAT REGULAR QDE WHITE 4L | C25: =IFERROR(__xludf.DUMMYFUNCTION("""COMPUTED_VALUE"""),695.0) -> 695 | D25: =IFERROR(__xludf.DUMMYFUNCTION("""COMPUTED_VALUE"""),"GALON") -> GALON | E25: =IFERROR(__xludf.DUMMYFUNCTION("""COMPUTED_VALUE"""),0.0) -> 0 | F25: =SUMIF(SALES!D:D, A25, SALES!H:H) + SUMIFS('STOCK IN TRANSFER'!G:G, 'STOCK IN TRANSFER'!D:D, A25, 'STOCK IN TRANSFER'!F:F, "TRANSFER") + SUMIFS('STOCK IN TRANSFER'!G:G, 'STOCK IN TRANSFER'!D:D, A25, 'STOCK IN TRANSFER'!F:F, "ADJUSTMENT (-)") -> 0 | G25: =SUMIFS('STOCK IN TRANSFER'!G:G, 'STOCK IN TRANSFER'!D:D, A25, 'STOCK IN TRANSFER'!F:F, "STOCK IN") + SUMIFS('STOCK IN TRANSFER'!G:G, 'STOCK IN TRANSFER'!D:D, A25, 'STOCK IN TRANSFER'!F:F, "ADJUSTMENT (+)") -> 0
A26: =IFERROR(__xludf.DUMMYFUNCTION("""COMPUTED_VALUE"""),"WQD1150-4L") -> WQD1150-4L | B26: =IFERROR(__xludf.DUMMYFUNCTION("""COMPUTED_VALUE"""),"WELCOAT REGULAR QDE BLACK 4L") -> WELCOAT REGULAR QDE BLACK 4L | C26: =IFERROR(__xludf.DUMMYFUNCTION("""COMPUTED_VALUE"""),570.0) -> 570 | D26: =IFERROR(__xludf.DUMMYFUNCTION("""COMPUTED_VALUE"""),"GALON") -> GALON | E26: =IFERROR(__xludf.DUMMYFUNCTION("""COMPUTED_VALUE"""),1.0) -> 1 | F26: =SUMIF(SALES!D:D, A26, SALES!H:H) + SUMIFS('STOCK IN TRANSFER'!G:G, 'STOCK IN TRANSFER'!D:D, A26, 'STOCK IN TRANSFER'!F:F, "TRANSFER") + SUMIFS('STOCK IN TRANSFER'!G:G, 'STOCK IN TRANSFER'!D:D, A26, 'STOCK IN TRANSFER'!F:F, "ADJUSTMENT (-)") -> 1 | G26: =SUMIFS('STOCK IN TRANSFER'!G:G, 'STOCK IN TRANSFER'!D:D, A26, 'STOCK IN TRANSFER'!F:F, "STOCK IN") + SUMIFS('STOCK IN TRANSFER'!G:G, 'STOCK IN TRANSFER'!D:D, A26, 'STOCK IN TRANSFER'!F:F, "ADJUSTMENT (+)") -> 2
A27: =IFERROR(__xludf.DUMMYFUNCTION("""COMPUTED_VALUE"""),"QDEMIX-1L") -> QDEMIX-1L | B27: =IFERROR(__xludf.DUMMYFUNCTION("""COMPUTED_VALUE"""),"QDE MIXING NP, DAVIES, BOYSEN, ALPHA CHROMA, WC 1L") -> QDE MIXING NP, DAVIES, BOYSEN, ALPHA CHROMA, WC 1L | C27: =IFERROR(__xludf.DUMMYFUNCTION("""COMPUTED_VALUE"""),200.0) -> 200 | D27: =IFERROR(__xludf.DUMMYFUNCTION("""COMPUTED_VALUE"""),"LITER") -> LITER | E27: =IFERROR(__xludf.DUMMYFUNCTION("""COMPUTED_VALUE"""),9.75) -> 9.75 | F27: =SUMIF(SALES!D:D, A27, SALES!H:H) + SUMIFS('STOCK IN TRANSFER'!G:G, 'STOCK IN TRANSFER'!D:D, A27, 'STOCK IN TRANSFER'!F:F, "TRANSFER") + SUMIFS('STOCK IN TRANSFER'!G:G, 'STOCK IN TRANSFER'!D:D, A27, 'STOCK IN TRANSFER'!F:F, "ADJUSTMENT (-)") -> 29.75 | G27: =SUMIFS('STOCK IN TRANSFER'!G:G, 'STOCK IN TRANSFER'!D:D, A27, 'STOCK IN TRANSFER'!F:F, "STOCK IN") + SUMIFS('STOCK IN TRANSFER'!G:G, 'STOCK IN TRANSFER'!D:D, A27, 'STOCK IN TRANSFER'!F:F, "ADJUSTMENT (+)") -> 39.5
A28: =IFERROR(__xludf.DUMMYFUNCTION("""COMPUTED_VALUE"""),"PWAC-9042-1L") -> PWAC-9042-1L | B28: =IFERROR(__xludf.DUMMYFUNCTION("""COMPUTED_VALUE"""),"WELCOAT ACRY-TILE TINTING COLOR PHTHALO GREEN PWAC-9042") -> WELCOAT ACRY-TILE TINTING COLOR PHTHALO GREEN PWAC-9042 | C28: =IFERROR(__xludf.DUMMYFUNCTION("""COMPUTED_VALUE"""),402.0) -> 402 | D28: =IFERROR(__xludf.DUMMYFUNCTION("""COMPUTED_VALUE"""),"LITER") -> LITER | E28: =IFERROR(__xludf.DUMMYFUNCTION("""COMPUTED_VALUE"""),3.0) -> 3 | F28: =SUMIF(SALES!D:D, A28, SALES!H:H) + SUMIFS('STOCK IN TRANSFER'!G:G, 'STOCK IN TRANSFER'!D:D, A28, 'STOCK IN TRANSFER'!F:F, "TRANSFER") + SUMIFS('STOCK IN TRANSFER'!G:G, 'STOCK IN TRANSFER'!D:D, A28, 'STOCK IN TRANSFER'!F:F, "ADJUSTMENT (-)") -> 0 | G28: =SUMIFS('STOCK IN TRANSFER'!G:G, 'STOCK IN TRANSFER'!D:D, A28, 'STOCK IN TRANSFER'!F:F, "STOCK IN") + SUMIFS('STOCK IN TRANSFER'!G:G, 'STOCK IN TRANSFER'!D:D, A28, 'STOCK IN TRANSFER'!F:F, "ADJUSTMENT (+)") -> 3
A29: =IFERROR(__xludf.DUMMYFUNCTION("""COMPUTED_VALUE"""),"PWAC-7242-1/4L") -> PWAC-7242-1/4L | B29: =IFERROR(__xludf.DUMMYFUNCTION("""COMPUTED_VALUE"""),"WELCOAT ACRY-TILE TINTING COLOR PHTHALO BLUE PWAC-7242") -> WELCOAT ACRY-TILE TINTING COLOR PHTHALO BLUE PWAC-7242 | C29: =IFERROR(__xludf.DUMMYFUNCTION("""COMPUTED_VALUE"""),111.0) -> 111 | D29: =IFERROR(__xludf.DUMMYFUNCTION("""COMPUTED_VALUE"""),"CAN") -> CAN | E29: =IFERROR(__xludf.DUMMYFUNCTION("""COMPUTED_VALUE"""),12.0) -> 12 | F29: =SUMIF(SALES!D:D, A29, SALES!H:H) + SUMIFS('STOCK IN TRANSFER'!G:G, 'STOCK IN TRANSFER'!D:D, A29, 'STOCK IN TRANSFER'!F:F, "TRANSFER") + SUMIFS('STOCK IN TRANSFER'!G:G, 'STOCK IN TRANSFER'!D:D, A29, 'STOCK IN TRANSFER'!F:F, "ADJUSTMENT (-)") -> 0 | G29: =SUMIFS('STOCK IN TRANSFER'!G:G, 'STOCK IN TRANSFER'!D:D, A29, 'STOCK IN TRANSFER'!F:F, "STOCK IN") + SUMIFS('STOCK IN TRANSFER'!G:G, 'STOCK IN TRANSFER'!D:D, A29, 'STOCK IN TRANSFER'!F:F, "ADJUSTMENT (+)") -> 12
A30: =IFERROR(__xludf.DUMMYFUNCTION("""COMPUTED_VALUE"""),"PWAC-2142-1L") -> PWAC-2142-1L | B30: =IFERROR(__xludf.DUMMYFUNCTION("""COMPUTED_VALUE"""),"WELCOAT ACRY-TILE TINTING COLOR PERMANENT RED PWAC-2142") -> WELCOAT ACRY-TILE TINTING COLOR PERMANENT RED PWAC-2142 | C30: =IFERROR(__xludf.DUMMYFUNCTION("""COMPUTED_VALUE"""),461.0) -> 461 | D30: =IFERROR(__xludf.DUMMYFUNCTION("""COMPUTED_VALUE"""),"LITER") -> LITER | E30: =IFERROR(__xludf.DUMMYFUNCTION("""COMPUTED_VALUE"""),2.0) -> 2 | F30: =SUMIF(SALES!D:D, A30, SALES!H:H) + SUMIFS('STOCK IN TRANSFER'!G:G, 'STOCK IN TRANSFER'!D:D, A30, 'STOCK IN TRANSFER'!F:F, "TRANSFER") + SUMIFS('STOCK IN TRANSFER'!G:G, 'STOCK IN TRANSFER'!D:D, A30, 'STOCK IN TRANSFER'!F:F, "ADJUSTMENT (-)") -> 0 | G30: =SUMIFS('STOCK IN TRANSFER'!G:G, 'STOCK IN TRANSFER'!D:D, A30, 'STOCK IN TRANSFER'!F:F, "STOCK IN") + SUMIFS('STOCK IN TRANSFER'!G:G, 'STOCK IN TRANSFER'!D:D, A30, 'STOCK IN TRANSFER'!F:F, "ADJUSTMENT (+)") -> 2
A31: =IFERROR(__xludf.DUMMYFUNCTION("""COMPUTED_VALUE"""),"PWAC-5042-1/4L") -> PWAC-5042-1/4L | B31: =IFERROR(__xludf.DUMMYFUNCTION("""COMPUTED_VALUE"""),"WELCOAT ACRY-TILE TINTING COLOR HANSA YELLOW PWAC-5042") -> WELCOAT ACRY-TILE TINTING COLOR HANSA YELLOW PWAC-5042 | C31: =IFERROR(__xludf.DUMMYFUNCTION("""COMPUTED_VALUE"""),141.0) -> 141 | D31: =IFERROR(__xludf.DUMMYFUNCTION("""COMPUTED_VALUE"""),"CAN") -> CAN | E31: =IFERROR(__xludf.DUMMYFUNCTION("""COMPUTED_VALUE"""),12.0) -> 12 | F31: =SUMIF(SALES!D:D, A31, SALES!H:H) + SUMIFS('STOCK IN TRANSFER'!G:G, 'STOCK IN TRANSFER'!D:D, A31, 'STOCK IN TRANSFER'!F:F, "TRANSFER") + SUMIFS('STOCK IN TRANSFER'!G:G, 'STOCK IN TRANSFER'!D:D, A31, 'STOCK IN TRANSFER'!F:F, "ADJUSTMENT (-)") -> 0 | G31: =SUMIFS('STOCK IN TRANSFER'!G:G, 'STOCK IN TRANSFER'!D:D, A31, 'STOCK IN TRANSFER'!F:F, "STOCK IN") + SUMIFS('STOCK IN TRANSFER'!G:G, 'STOCK IN TRANSFER'!D:D, A31, 'STOCK IN TRANSFER'!F:F, "ADJUSTMENT (+)") -> 12
A32: =IFERROR(__xludf.DUMMYFUNCTION("""COMPUTED_VALUE"""),"WCPOD") -> WCPOD | B32: =IFERROR(__xludf.DUMMYFUNCTION("""COMPUTED_VALUE"""),"WASTE COTTON POD") -> WASTE COTTON POD | C32: =IFERROR(__xludf.DUMMYFUNCTION("""COMPUTED_VALUE"""),70.0) -> 70 | D32: =IFERROR(__xludf.DUMMYFUNCTION("""COMPUTED_VALUE"""),"KL") -> KL | E32: =IFERROR(__xludf.DUMMYFUNCTION("""COMPUTED_VALUE"""),24.5) -> 24.5 | F32: =SUMIF(SALES!D:D, A32, SALES!H:H) + SUMIFS('STOCK IN TRANSFER'!G:G, 'STOCK IN TRANSFER'!D:D, A32, 'STOCK IN TRANSFER'!F:F, "TRANSFER") + SUMIFS('STOCK IN TRANSFER'!G:G, 'STOCK IN TRANSFER'!D:D, A32, 'STOCK IN TRANSFER'!F:F, "ADJUSTMENT (-)") -> 14.25 | G32: =SUMIFS('STOCK IN TRANSFER'!G:G, 'STOCK IN TRANSFER'!D:D, A32, 'STOCK IN TRANSFER'!F:F, "STOCK IN") + SUMIFS('STOCK IN TRANSFER'!G:G, 'STOCK IN TRANSFER'!D:D, A32, 'STOCK IN TRANSFER'!F:F, "ADJUSTMENT (+)") -> 38.75
A33: =IFERROR(__xludf.DUMMYFUNCTION("""COMPUTED_VALUE"""),"VSEAL") -> VSEAL | B33: =IFERROR(__xludf.DUMMYFUNCTION("""COMPUTED_VALUE"""),"VULCASEAL") -> VULCASEAL | C33: =IFERROR(__xludf.DUMMYFUNCTION("""COMPUTED_VALUE"""),62.0) -> 62 | D33: =IFERROR(__xludf.DUMMYFUNCTION("""COMPUTED_VALUE"""),"PCS") -> PCS | E33: =IFERROR(__xludf.DUMMYFUNCTION("""COMPUTED_VALUE"""),3.0) -> 3 | F33: =SUMIF(SALES!D:D, A33, SALES!H:H) + SUMIFS('STOCK IN TRANSFER'!G:G, 'STOCK IN TRANSFER'!D:D, A33, 'STOCK IN TRANSFER'!F:F, "TRANSFER") + SUMIFS('STOCK IN TRANSFER'!G:G, 'STOCK IN TRANSFER'!D:D, A33, 'STOCK IN TRANSFER'!F:F, "ADJUSTMENT (-)") -> 5 | G33: =SUMIFS('STOCK IN TRANSFER'!G:G, 'STOCK IN TRANSFER'!D:D, A33, 'STOCK IN TRANSFER'!F:F, "STOCK IN") + SUMIFS('STOCK IN TRANSFER'!G:G, 'STOCK IN TRANSFER'!D:D, A33, 'STOCK IN TRANSFER'!F:F, "ADJUSTMENT (+)") -> 8
A34: =IFERROR(__xludf.DUMMYFUNCTION("""COMPUTED_VALUE"""),"ROS-823") -> ROS-823 | B34: =IFERROR(__xludf.DUMMYFUNCTION("""COMPUTED_VALUE"""),"VIBRANT RUBY ROS-823 RAIN OR SHINE 4L") -> VIBRANT RUBY ROS-823 RAIN OR SHINE 4L | C34: =IFERROR(__xludf.DUMMYFUNCTION("""COMPUTED_VALUE"""),1015.0) -> 1015 | D34: =IFERROR(__xludf.DUMMYFUNCTION("""COMPUTED_VALUE"""),"4L") -> 4L | E34: =IFERROR(__xludf.DUMMYFUNCTION("""COMPUTED_VALUE"""),2.0) -> 2 | F34: =SUMIF(SALES!D:D, A34, SALES!H:H) + SUMIFS('STOCK IN TRANSFER'!G:G, 'STOCK IN TRANSFER'!D:D, A34, 'STOCK IN TRANSFER'!F:F, "TRANSFER") + SUMIFS('STOCK IN TRANSFER'!G:G, 'STOCK IN TRANSFER'!D:D, A34, 'STOCK IN TRANSFER'!F:F, "ADJUSTMENT (-)") -> 1 | G34: =SUMIFS('STOCK IN TRANSFER'!G:G, 'STOCK IN TRANSFER'!D:D, A34, 'STOCK IN TRANSFER'!F:F, "STOCK IN") + SUMIFS('STOCK IN TRANSFER'!G:G, 'STOCK IN TRANSFER'!D:D, A34, 'STOCK IN TRANSFER'!F:F, "ADJUSTMENT (+)") -> 3
A35: =IFERROR(__xludf.DUMMYFUNCTION("""COMPUTED_VALUE"""),"AC-11-1L") -> AC-11-1L | B35: =IFERROR(__xludf.DUMMYFUNCTION("""COMPUTED_VALUE"""),"VENETIAN RED ACRY-COLOR COLOR AC-11 1L DAVIES") -> VENETIAN RED ACRY-COLOR COLOR AC-11 1L DAVIES | C35: =IFERROR(__xludf.DUMMYFUNCTION("""COMPUTED_VALUE"""),108.0) -> 108 | D35: =IFERROR(__xludf.DUMMYFUNCTION("""COMPUTED_VALUE"""),"1L") -> 1L | E35: =IFERROR(__xludf.DUMMYFUNCTION("""COMPUTED_VALUE"""),4.0) -> 4 | F35: =SUMIF(SALES!D:D, A35, SALES!H:H) + SUMIFS('STOCK IN TRANSFER'!G:G, 'STOCK IN TRANSFER'!D:D, A35, 'STOCK IN TRANSFER'!F:F, "TRANSFER") + SUMIFS('STOCK IN TRANSFER'!G:G, 'STOCK IN TRANSFER'!D:D, A35, 'STOCK IN TRANSFER'!F:F, "ADJUSTMENT (-)") -> 0 | G35: =SUMIFS('STOCK IN TRANSFER'!G:G, 'STOCK IN TRANSFER'!D:D, A35, 'STOCK IN TRANSFER'!F:F, "STOCK IN") + SUMIFS('STOCK IN TRANSFER'!G:G, 'STOCK IN TRANSFER'!D:D, A35, 'STOCK IN TRANSFER'!F:F, "ADJUSTMENT (+)") -> 4
A36: =IFERROR(__xludf.DUMMYFUNCTION("""COMPUTED_VALUE"""),"UNOPT-BOT") -> UNOPT-BOT | B36: =IFERROR(__xludf.DUMMYFUNCTION("""COMPUTED_VALUE"""),"UNO PAINT THINNER BOT") -> UNO PAINT THINNER BOT | C36: =IFERROR(__xludf.DUMMYFUNCTION("""COMPUTED_VALUE"""),52.0) -> 52 | D36: =IFERROR(__xludf.DUMMYFUNCTION("""COMPUTED_VALUE"""),"PC/S") -> PC/S | E36: =IFERROR(__xludf.DUMMYFUNCTION("""COMPUTED_VALUE"""),0.0) -> 0 | F36: =SUMIF(SALES!D:D, A36, SALES!H:H) + SUMIFS('STOCK IN TRANSFER'!G:G, 'STOCK IN TRANSFER'!D:D, A36, 'STOCK IN TRANSFER'!F:F, "TRANSFER") + SUMIFS('STOCK IN TRANSFER'!G:G, 'STOCK IN TRANSFER'!D:D, A36, 'STOCK IN TRANSFER'!F:F, "ADJUSTMENT (-)") -> 2 | G36: =SUMIFS('STOCK IN TRANSFER'!G:G, 'STOCK IN TRANSFER'!D:D, A36, 'STOCK IN TRANSFER'!F:F, "STOCK IN") + SUMIFS('STOCK IN TRANSFER'!G:G, 'STOCK IN TRANSFER'!D:D, A36, 'STOCK IN TRANSFER'!F:F, "ADJUSTMENT (+)") -> 2
A37: =IFERROR(__xludf.DUMMYFUNCTION("""COMPUTED_VALUE"""),"UNOLT-BOT") -> UNOLT-BOT | B37: =IFERROR(__xludf.DUMMYFUNCTION("""COMPUTED_VALUE"""),"UNO LACQUER THINNER BOT") -> UNO LACQUER THINNER BOT | C37: =IFERROR(__xludf.DUMMYFUNCTION("""COMPUTED_VALUE"""),50.0) -> 50 | D37: =IFERROR(__xludf.DUMMYFUNCTION("""COMPUTED_VALUE"""),"BOT") -> BOT | E37: =IFERROR(__xludf.DUMMYFUNCTION("""COMPUTED_VALUE"""),4.0) -> 4 | F37: =SUMIF(SALES!D:D, A37, SALES!H:H) + SUMIFS('STOCK IN TRANSFER'!G:G, 'STOCK IN TRANSFER'!D:D, A37, 'STOCK IN TRANSFER'!F:F, "TRANSFER") + SUMIFS('STOCK IN TRANSFER'!G:G, 'STOCK IN TRANSFER'!D:D, A37, 'STOCK IN TRANSFER'!F:F, "ADJUSTMENT (-)") -> 37 | G37: =SUMIFS('STOCK IN TRANSFER'!G:G, 'STOCK IN TRANSFER'!D:D, A37, 'STOCK IN TRANSFER'!F:F, "STOCK IN") + SUMIFS('STOCK IN TRANSFER'!G:G, 'STOCK IN TRANSFER'!D:D, A37, 'STOCK IN TRANSFER'!F:F, "ADJUSTMENT (+)") -> 41
A38: =IFERROR(__xludf.DUMMYFUNCTION("""COMPUTED_VALUE"""),"UNOLT-4L") -> UNOLT-4L | B38: =IFERROR(__xludf.DUMMYFUNCTION("""COMPUTED_VALUE"""),"UNO LACQUER THINNER 4L") -> UNO LACQUER THINNER 4L | C38: =IFERROR(__xludf.DUMMYFUNCTION("""COMPUTED_VALUE"""),360.0) -> 360 | D38: =IFERROR(__xludf.DUMMYFUNCTION("""COMPUTED_VALUE"""),"GAL/S") -> GAL/S | E38: =IFERROR(__xludf.DUMMYFUNCTION("""COMPUTED_VALUE"""),1.0) -> 1 | F38: =SUMIF(SALES!D:D, A38, SALES!H:H) + SUMIFS('STOCK IN TRANSFER'!G:G, 'STOCK IN TRANSFER'!D:D, A38, 'STOCK IN TRANSFER'!F:F, "TRANSFER") + SUMIFS('STOCK IN TRANSFER'!G:G, 'STOCK IN TRANSFER'!D:D, A38, 'STOCK IN TRANSFER'!F:F, "ADJUSTMENT (-)") -> 4 | G38: =SUMIFS('STOCK IN TRANSFER'!G:G, 'STOCK IN TRANSFER'!D:D, A38, 'STOCK IN TRANSFER'!F:F, "STOCK IN") + SUMIFS('STOCK IN TRANSFER'!G:G, 'STOCK IN TRANSFER'!D:D, A38, 'STOCK IN TRANSFER'!F:F, "ADJUSTMENT (+)") -> 5
A39: =IFERROR(__xludf.DUMMYFUNCTION("""COMPUTED_VALUE"""),"AC-10-1L") -> AC-10-1L | B39: =IFERROR(__xludf.DUMMYFUNCTION("""COMPUTED_VALUE"""),"TOLUIDINE RED ACRY-COLOR AC-10 1L DAVIES") -> TOLUIDINE RED ACRY-COLOR AC-10 1L DAVIES | C39: =IFERROR(__xludf.DUMMYFUNCTION("""COMPUTED_VALUE"""),108.0) -> 108 | D39: =IFERROR(__xludf.DUMMYFUNCTION("""COMPUTED_VALUE"""),"1L") -> 1L | E39: =IFERROR(__xludf.DUMMYFUNCTION("""COMPUTED_VALUE"""),0.0) -> 0 | F39: =SUMIF(SALES!D:D, A39, SALES!H:H) + SUMIFS('STOCK IN TRANSFER'!G:G, 'STOCK IN TRANSFER'!D:D, A39, 'STOCK IN TRANSFER'!F:F, "TRANSFER") + SUMIFS('STOCK IN TRANSFER'!G:G, 'STOCK IN TRANSFER'!D:D, A39, 'STOCK IN TRANSFER'!F:F, "ADJUSTMENT (-)") -> 4 | G39: =SUMIFS('STOCK IN TRANSFER'!G:G, 'STOCK IN TRANSFER'!D:D, A39, 'STOCK IN TRANSFER'!F:F, "STOCK IN") + SUMIFS('STOCK IN TRANSFER'!G:G, 'STOCK IN TRANSFER'!D:D, A39, 'STOCK IN TRANSFER'!F:F, "ADJUSTMENT (+)") -> 4
A40: =IFERROR(__xludf.DUMMYFUNCTION("""COMPUTED_VALUE"""),"TOUT-4L") -> TOUT-4L | B40: =IFERROR(__xludf.DUMMYFUNCTION("""COMPUTED_VALUE"""),"TIMEOUT URETHANE THINNER 4L") -> TIMEOUT URETHANE THINNER 4L | C40: =IFERROR(__xludf.DUMMYFUNCTION("""COMPUTED_VALUE"""),510.0) -> 510 | D40: =IFERROR(__xludf.DUMMYFUNCTION("""COMPUTED_VALUE"""),"GAL") -> GAL | E40: =IFERROR(__xludf.DUMMYFUNCTION("""COMPUTED_VALUE"""),0.0) -> 0 | F40: =SUMIF(SALES!D:D, A40, SALES!H:H) + SUMIFS('STOCK IN TRANSFER'!G:G, 'STOCK IN TRANSFER'!D:D, A40, 'STOCK IN TRANSFER'!F:F, "TRANSFER") + SUMIFS('STOCK IN TRANSFER'!G:G, 'STOCK IN TRANSFER'!D:D, A40, 'STOCK IN TRANSFER'!F:F, "ADJUSTMENT (-)") -> 1 | G40: =SUMIFS('STOCK IN TRANSFER'!G:G, 'STOCK IN TRANSFER'!D:D, A40, 'STOCK IN TRANSFER'!F:F, "STOCK IN") + SUMIFS('STOCK IN TRANSFER'!G:G, 'STOCK IN TRANSFER'!D:D, A40, 'STOCK IN TRANSFER'!F:F, "ADJUSTMENT (+)") -> 1
A41: =IFERROR(__xludf.DUMMYFUNCTION("""COMPUTED_VALUE"""),"TOBF-4L") -> TOBF-4L | B41: =IFERROR(__xludf.DUMMYFUNCTION("""COMPUTED_VALUE"""),"TIMEOUT BODY FILLER WITH HARDENER 4L") -> TIMEOUT BODY FILLER WITH HARDENER 4L | C41: =IFERROR(__xludf.DUMMYFUNCTION("""COMPUTED_VALUE"""),585.0) -> 585 | D41: =IFERROR(__xludf.DUMMYFUNCTION("""COMPUTED_VALUE"""),"GAL") -> GAL | E41: =IFERROR(__xludf.DUMMYFUNCTION("""COMPUTED_VALUE"""),11.0) -> 11 | F41: =SUMIF(SALES!D:D, A41, SALES!H:H) + SUMIFS('STOCK IN TRANSFER'!G:G, 'STOCK IN TRANSFER'!D:D, A41, 'STOCK IN TRANSFER'!F:F, "TRANSFER") + SUMIFS('STOCK IN TRANSFER'!G:G, 'STOCK IN TRANSFER'!D:D, A41, 'STOCK IN TRANSFER'!F:F, "ADJUSTMENT (-)") -> 18 | G41: =SUMIFS('STOCK IN TRANSFER'!G:G, 'STOCK IN TRANSFER'!D:D, A41, 'STOCK IN TRANSFER'!F:F, "STOCK IN") + SUMIFS('STOCK IN TRANSFER'!G:G, 'STOCK IN TRANSFER'!D:D, A41, 'STOCK IN TRANSFER'!F:F, "ADJUSTMENT (+)") -> 29
A42: =IFERROR(__xludf.DUMMYFUNCTION("""COMPUTED_VALUE"""),"TOBF-1L") -> TOBF-1L | B42: =IFERROR(__xludf.DUMMYFUNCTION("""COMPUTED_VALUE"""),"TIMEOUT BODY FILLER WITH HARDENER 1L") -> TIMEOUT BODY FILLER WITH HARDENER 1L | C42: =IFERROR(__xludf.DUMMYFUNCTION("""COMPUTED_VALUE"""),160.0) -> 160 | D42: =IFERROR(__xludf.DUMMYFUNCTION("""COMPUTED_VALUE"""),"LTR") -> LTR | E42: =IFERROR(__xludf.DUMMYFUNCTION("""COMPUTED_VALUE"""),9.0) -> 9 | F42: =SUMIF(SALES!D:D, A42, SALES!H:H) + SUMIFS('STOCK IN TRANSFER'!G:G, 'STOCK IN TRANSFER'!D:D, A42, 'STOCK IN TRANSFER'!F:F, "TRANSFER") + SUMIFS('STOCK IN TRANSFER'!G:G, 'STOCK IN TRANSFER'!D:D, A42, 'STOCK IN TRANSFER'!F:F, "ADJUSTMENT (-)") -> 15 | G42: =SUMIFS('STOCK IN TRANSFER'!G:G, 'STOCK IN TRANSFER'!D:D, A42, 'STOCK IN TRANSFER'!F:F, "STOCK IN") + SUMIFS('STOCK IN TRANSFER'!G:G, 'STOCK IN TRANSFER'!D:D, A42, 'STOCK IN TRANSFER'!F:F, "ADJUSTMENT (+)") -> 24
A43: =IFERROR(__xludf.DUMMYFUNCTION("""COMPUTED_VALUE"""),"TOAT-4L") -> TOAT-4L | B43: =IFERROR(__xludf.DUMMYFUNCTION("""COMPUTED_VALUE"""),"TIMEOUT ACRYLIC THINNER 4L") -> TIMEOUT ACRYLIC THINNER 4L | C43: =IFERROR(__xludf.DUMMYFUNCTION("""COMPUTED_VALUE"""),500.0) -> 500 | D43: =IFERROR(__xludf.DUMMYFUNCTION("""COMPUTED_VALUE"""),"GAL") -> GAL | E43: =IFERROR(__xludf.DUMMYFUNCTION("""COMPUTED_VALUE"""),0.0) -> 0 | F43: =SUMIF(SALES!D:D, A43, SALES!H:H) + SUMIFS('STOCK IN TRANSFER'!G:G, 'STOCK IN TRANSFER'!D:D, A43, 'STOCK IN TRANSFER'!F:F, "TRANSFER") + SUMIFS('STOCK IN TRANSFER'!G:G, 'STOCK IN TRANSFER'!D:D, A43, 'STOCK IN TRANSFER'!F:F, "ADJUSTMENT (-)") -> 0 | G43: =SUMIFS('STOCK IN TRANSFER'!G:G, 'STOCK IN TRANSFER'!D:D, A43, 'STOCK IN TRANSFER'!F:F, "STOCK IN") + SUMIFS('STOCK IN TRANSFER'!G:G, 'STOCK IN TRANSFER'!D:D, A43, 'STOCK IN TRANSFER'!F:F, "ADJUSTMENT (+)") -> 0
A44: =IFERROR(__xludf.DUMMYFUNCTION("""COMPUTED_VALUE"""),"TOTHALOBLU-4L") -> TOTHALOBLU-4L | B44: =IFERROR(__xludf.DUMMYFUNCTION("""COMPUTED_VALUE"""),"TIMEOUT ACRYLIC THALO BLUE 4L") -> TIMEOUT ACRYLIC THALO BLUE 4L | C44: =IFERROR(__xludf.DUMMYFUNCTION("""COMPUTED_VALUE"""),1060.0) -> 1060 | D44: =IFERROR(__xludf.DUMMYFUNCTION("""COMPUTED_VALUE"""),"GAL") -> GAL | E44: =IFERROR(__xludf.DUMMYFUNCTION("""COMPUTED_VALUE"""),3.0) -> 3 | F44: =SUMIF(SALES!D:D, A44, SALES!H:H) + SUMIFS('STOCK IN TRANSFER'!G:G, 'STOCK IN TRANSFER'!D:D, A44, 'STOCK IN TRANSFER'!F:F, "TRANSFER") + SUMIFS('STOCK IN TRANSFER'!G:G, 'STOCK IN TRANSFER'!D:D, A44, 'STOCK IN TRANSFER'!F:F, "ADJUSTMENT (-)") -> 0 | G44: =SUMIFS('STOCK IN TRANSFER'!G:G, 'STOCK IN TRANSFER'!D:D, A44, 'STOCK IN TRANSFER'!F:F, "STOCK IN") + SUMIFS('STOCK IN TRANSFER'!G:G, 'STOCK IN TRANSFER'!D:D, A44, 'STOCK IN TRANSFER'!F:F, "ADJUSTMENT (+)") -> 3
A45: =IFERROR(__xludf.DUMMYFUNCTION("""COMPUTED_VALUE"""),"TLWAX") -> TLWAX | B45: =IFERROR(__xludf.DUMMYFUNCTION("""COMPUTED_VALUE"""),"TIMELESS PREMIUM LIQUID WAX 5OML") -> TIMELESS PREMIUM LIQUID WAX 5OML | C45: =IFERROR(__xludf.DUMMYFUNCTION("""COMPUTED_VALUE"""),50.0) -> 50 | D45: =IFERROR(__xludf.DUMMYFUNCTION("""COMPUTED_VALUE"""),"PC/S") -> PC/S | E45: =IFERROR(__xludf.DUMMYFUNCTION("""COMPUTED_VALUE"""),32.0) -> 32 | F45: =SUMIF(SALES!D:D, A45, SALES!H:H) + SUMIFS('STOCK IN TRANSFER'!G:G, 'STOCK IN TRANSFER'!D:D, A45, 'STOCK IN TRANSFER'!F:F, "TRANSFER") + SUMIFS('STOCK IN TRANSFER'!G:G, 'STOCK IN TRANSFER'!D:D, A45, 'STOCK IN TRANSFER'!F:F, "ADJUSTMENT (-)") -> 15 | G45: =SUMIFS('STOCK IN TRANSFER'!G:G, 'STOCK IN TRANSFER'!D:D, A45, 'STOCK IN TRANSFER'!F:F, "STOCK IN") + SUMIFS('STOCK IN TRANSFER'!G:G, 'STOCK IN TRANSFER'!D:D, A45, 'STOCK IN TRANSFER'!F:F, "ADJUSTMENT (+)") -> 47
A46: =IFERROR(__xludf.DUMMYFUNCTION("""COMPUTED_VALUE"""),"ROS-302") -> ROS-302 | B46: =IFERROR(__xludf.DUMMYFUNCTION("""COMPUTED_VALUE"""),"TILE RED ROS-302 RAIN OR SHINE 4L") -> TILE RED ROS-302 RAIN OR SHINE 4L | C46: =IFERROR(__xludf.DUMMYFUNCTION("""COMPUTED_VALUE"""),661.1) -> 661.1 | D46: =IFERROR(__xludf.DUMMYFUNCTION("""COMPUTED_VALUE"""),"4L") -> 4L | E46: =IFERROR(__xludf.DUMMYFUNCTION("""COMPUTED_VALUE"""),0.0) -> 0 | F46: =SUMIF(SALES!D:D, A46, SALES!H:H) + SUMIFS('STOCK IN TRANSFER'!G:G, 'STOCK IN TRANSFER'!D:D, A46, 'STOCK IN TRANSFER'!F:F, "TRANSFER") + SUMIFS('STOCK IN TRANSFER'!G:G, 'STOCK IN TRANSFER'!D:D, A46, 'STOCK IN TRANSFER'!F:F, "ADJUSTMENT (-)") -> 0 | G46: =SUMIFS('STOCK IN TRANSFER'!G:G, 'STOCK IN TRANSFER'!D:D, A46, 'STOCK IN TRANSFER'!F:F, "STOCK IN") + SUMIFS('STOCK IN TRANSFER'!G:G, 'STOCK IN TRANSFER'!D:D, A46, 'STOCK IN TRANSFER'!F:F, "ADJUSTMENT (+)") -> 0
A47: =IFERROR(__xludf.DUMMYFUNCTION("""COMPUTED_VALUE"""),"AC-30-1L") -> AC-30-1L | B47: =IFERROR(__xludf.DUMMYFUNCTION("""COMPUTED_VALUE"""),"THALO GREEN ACRY-COLOR AC-30 1L DAVIES") -> THALO GREEN ACRY-COLOR AC-30 1L DAVIES | C47: =IFERROR(__xludf.DUMMYFUNCTION("""COMPUTED_VALUE"""),103.0) -> 103 | D47: =IFERROR(__xludf.DUMMYFUNCTION("""COMPUTED_VALUE"""),"1L") -> 1L | E47: =IFERROR(__xludf.DUMMYFUNCTION("""COMPUTED_VALUE"""),6.0) -> 6 | F47: =SUMIF(SALES!D:D, A47, SALES!H:H) + SUMIFS('STOCK IN TRANSFER'!G:G, 'STOCK IN TRANSFER'!D:D, A47, 'STOCK IN TRANSFER'!F:F, "TRANSFER") + SUMIFS('STOCK IN TRANSFER'!G:G, 'STOCK IN TRANSFER'!D:D, A47, 'STOCK IN TRANSFER'!F:F, "ADJUSTMENT (-)") -> 1 | G47: =SUMIFS('STOCK IN TRANSFER'!G:G, 'STOCK IN TRANSFER'!D:D, A47, 'STOCK IN TRANSFER'!F:F, "STOCK IN") + SUMIFS('STOCK IN TRANSFER'!G:G, 'STOCK IN TRANSFER'!D:D, A47, 'STOCK IN TRANSFER'!F:F, "ADJUSTMENT (+)") -> 7
A48: =IFERROR(__xludf.DUMMYFUNCTION("""COMPUTED_VALUE"""),"AC-20-1L") -> AC-20-1L | B48: =IFERROR(__xludf.DUMMYFUNCTION("""COMPUTED_VALUE"""),"THALO BLUE ACRY-COLOR AC-20 1L DAVIES") -> THALO BLUE ACRY-COLOR AC-20 1L DAVIES | C48: =IFERROR(__xludf.DUMMYFUNCTION("""COMPUTED_VALUE"""),103.0) -> 103 | D48: =IFERROR(__xludf.DUMMYFUNCTION("""COMPUTED_VALUE"""),"1L") -> 1L | E48: =IFERROR(__xludf.DUMMYFUNCTION("""COMPUTED_VALUE"""),0.0) -> 0 | F48: =SUMIF(SALES!D:D, A48, SALES!H:H) + SUMIFS('STOCK IN TRANSFER'!G:G, 'STOCK IN TRANSFER'!D:D, A48, 'STOCK IN TRANSFER'!F:F, "TRANSFER") + SUMIFS('STOCK IN TRANSFER'!G:G, 'STOCK IN TRANSFER'!D:D, A48, 'STOCK IN TRANSFER'!F:F, "ADJUSTMENT (-)") -> 2 | G48: =SUMIFS('STOCK IN TRANSFER'!G:G, 'STOCK IN TRANSFER'!D:D, A48, 'STOCK IN TRANSFER'!F:F, "STOCK IN") + SUMIFS('STOCK IN TRANSFER'!G:G, 'STOCK IN TRANSFER'!D:D, A48, 'STOCK IN TRANSFER'!F:F, "ADJUSTMENT (+)") -> 2
A49: =IFERROR(__xludf.DUMMYFUNCTION("""COMPUTED_VALUE"""),"TEXAS") -> TEXAS | B49: =IFERROR(__xludf.DUMMYFUNCTION("""COMPUTED_VALUE"""),"TEXAS RUBBERIZED") -> TEXAS RUBBERIZED | C49: =IFERROR(__xludf.DUMMYFUNCTION("""COMPUTED_VALUE"""),500.0) -> 500 | D49: =IFERROR(__xludf.DUMMYFUNCTION("""COMPUTED_VALUE"""),"GAL") -> GAL | E49: =IFERROR(__xludf.DUMMYFUNCTION("""COMPUTED_VALUE"""),0.0) -> 0 | F49: =SUMIF(SALES!D:D, A49, SALES!H:H) + SUMIFS('STOCK IN TRANSFER'!G:G, 'STOCK IN TRANSFER'!D:D, A49, 'STOCK IN TRANSFER'!F:F, "TRANSFER") + SUMIFS('STOCK IN TRANSFER'!G:G, 'STOCK IN TRANSFER'!D:D, A49, 'STOCK IN TRANSFER'!F:F, "ADJUSTMENT (-)") -> 0 | G49: =SUMIFS('STOCK IN TRANSFER'!G:G, 'STOCK IN TRANSFER'!D:D, A49, 'STOCK IN TRANSFER'!F:F, "STOCK IN") + SUMIFS('STOCK IN TRANSFER'!G:G, 'STOCK IN TRANSFER'!D:D, A49, 'STOCK IN TRANSFER'!F:F, "ADJUSTMENT (+)") -> 0
A50: =IFERROR(__xludf.DUMMYFUNCTION("""COMPUTED_VALUE"""),"MTX") -> MTX | B50: =IFERROR(__xludf.DUMMYFUNCTION("""COMPUTED_VALUE"""),"SUPRA GLOSS (TURTLE WAX)") -> SUPRA GLOSS (TURTLE WAX) | C50: =IFERROR(__xludf.DUMMYFUNCTION("""COMPUTED_VALUE"""),700.0) -> 700 | D50: =IFERROR(__xludf.DUMMYFUNCTION("""COMPUTED_VALUE"""),"LTR") -> LTR | E50: =IFERROR(__xludf.DUMMYFUNCTION("""COMPUTED_VALUE"""),11.0) -> 11 | F50: =SUMIF(SALES!D:D, A50, SALES!H:H) + SUMIFS('STOCK IN TRANSFER'!G:G, 'STOCK IN TRANSFER'!D:D, A50, 'STOCK IN TRANSFER'!F:F, "TRANSFER") + SUMIFS('STOCK IN TRANSFER'!G:G, 'STOCK IN TRANSFER'!D:D, A50, 'STOCK IN TRANSFER'!F:F, "ADJUSTMENT (-)") -> 1 | G50: =SUMIFS('STOCK IN TRANSFER'!G:G, 'STOCK IN TRANSFER'!D:D, A50, 'STOCK IN TRANSFER'!F:F, "STOCK IN") + SUMIFS('STOCK IN TRANSFER'!G:G, 'STOCK IN TRANSFER'!D:D, A50, 'STOCK IN TRANSFER'!F:F, "ADJUSTMENT (+)") -> 12
A51: =IFERROR(__xludf.DUMMYFUNCTION("""COMPUTED_VALUE"""),"WEBER") -> WEBER | B51: =IFERROR(__xludf.DUMMYFUNCTION("""COMPUTED_VALUE"""),"SPRAY GUN F-75G WEBER") -> SPRAY GUN F-75G WEBER | C51: =IFERROR(__xludf.DUMMYFUNCTION("""COMPUTED_VALUE"""),750.0) -> 750 | D51: =IFERROR(__xludf.DUMMYFUNCTION("""COMPUTED_VALUE"""),"SET") -> SET | E51: =IFERROR(__xludf.DUMMYFUNCTION("""COMPUTED_VALUE"""),0.0) -> 0 | F51: =SUMIF(SALES!D:D, A51, SALES!H:H) + SUMIFS('STOCK IN TRANSFER'!G:G, 'STOCK IN TRANSFER'!D:D, A51, 'STOCK IN TRANSFER'!F:F, "TRANSFER") + SUMIFS('STOCK IN TRANSFER'!G:G, 'STOCK IN TRANSFER'!D:D, A51, 'STOCK IN TRANSFER'!F:F, "ADJUSTMENT (-)") -> 1 | G51: =SUMIFS('STOCK IN TRANSFER'!G:G, 'STOCK IN TRANSFER'!D:D, A51, 'STOCK IN TRANSFER'!F:F, "STOCK IN") + SUMIFS('STOCK IN TRANSFER'!G:G, 'STOCK IN TRANSFER'!D:D, A51, 'STOCK IN TRANSFER'!F:F, "ADJUSTMENT (+)") -> 1
A52: =IFERROR(__xludf.DUMMYFUNCTION("""COMPUTED_VALUE"""),"B-715") -> B-715 | B52: =IFERROR(__xludf.DUMMYFUNCTION("""COMPUTED_VALUE"""),"SEMI GLOSS WHITE ACRYLIC LATEX B-715 BOYSEN 4L") -> SEMI GLOSS WHITE ACRYLIC LATEX B-715 BOYSEN 4L | C52: =IFERROR(__xludf.DUMMYFUNCTION("""COMPUTED_VALUE"""),728.0) -> 728 | D52: =IFERROR(__xludf.DUMMYFUNCTION("""COMPUTED_VALUE"""),"4L") -> 4L | E52: =IFERROR(__xludf.DUMMYFUNCTION("""COMPUTED_VALUE"""),0.0) -> 0 | F52: =SUMIF(SALES!D:D, A52, SALES!H:H) + SUMIFS('STOCK IN TRANSFER'!G:G, 'STOCK IN TRANSFER'!D:D, A52, 'STOCK IN TRANSFER'!F:F, "TRANSFER") + SUMIFS('STOCK IN TRANSFER'!G:G, 'STOCK IN TRANSFER'!D:D, A52, 'STOCK IN TRANSFER'!F:F, "ADJUSTMENT (-)") -> 0 | G52: =SUMIFS('STOCK IN TRANSFER'!G:G, 'STOCK IN TRANSFER'!D:D, A52, 'STOCK IN TRANSFER'!F:F, "STOCK IN") + SUMIFS('STOCK IN TRANSFER'!G:G, 'STOCK IN TRANSFER'!D:D, A52, 'STOCK IN TRANSFER'!F:F, "ADJUSTMENT (+)") -> 0
A53: =IFERROR(__xludf.DUMMYFUNCTION("""COMPUTED_VALUE"""),"EA80") -> EA80 | B53: =IFERROR(__xludf.DUMMYFUNCTION("""COMPUTED_VALUE"""),"SAND PAPER #80") -> SAND PAPER #80 | C53: =IFERROR(__xludf.DUMMYFUNCTION("""COMPUTED_VALUE"""),28.0) -> 28 | D53: =IFERROR(__xludf.DUMMYFUNCTION("""COMPUTED_VALUE"""),"PC/S") -> PC/S | E53: =IFERROR(__xludf.DUMMYFUNCTION("""COMPUTED_VALUE"""),136.0) -> 136 | F53: =SUMIF(SALES!D:D, A53, SALES!H:H) + SUMIFS('STOCK IN TRANSFER'!G:G, 'STOCK IN TRANSFER'!D:D, A53, 'STOCK IN TRANSFER'!F:F, "TRANSFER") + SUMIFS('STOCK IN TRANSFER'!G:G, 'STOCK IN TRANSFER'!D:D, A53, 'STOCK IN TRANSFER'!F:F, "ADJUSTMENT (-)") -> 24 | G53: =SUMIFS('STOCK IN TRANSFER'!G:G, 'STOCK IN TRANSFER'!D:D, A53, 'STOCK IN TRANSFER'!F:F, "STOCK IN") + SUMIFS('STOCK IN TRANSFER'!G:G, 'STOCK IN TRANSFER'!D:D, A53, 'STOCK IN TRANSFER'!F:F, "ADJUSTMENT (+)") -> 160
A54: =IFERROR(__xludf.DUMMYFUNCTION("""COMPUTED_VALUE"""),"EA100") -> EA100 | B54: =IFERROR(__xludf.DUMMYFUNCTION("""COMPUTED_VALUE"""),"SAND PAPER #100") -> SAND PAPER #100 | C54: =IFERROR(__xludf.DUMMYFUNCTION("""COMPUTED_VALUE"""),28.0) -> 28 | D54: =IFERROR(__xludf.DUMMYFUNCTION("""COMPUTED_VALUE"""),"PC/S") -> PC/S | E54: =IFERROR(__xludf.DUMMYFUNCTION("""COMPUTED_VALUE"""),104.0) -> 104 | F54: =SUMIF(SALES!D:D, A54, SALES!H:H) + SUMIFS('STOCK IN TRANSFER'!G:G, 'STOCK IN TRANSFER'!D:D, A54, 'STOCK IN TRANSFER'!F:F, "TRANSFER") + SUMIFS('STOCK IN TRANSFER'!G:G, 'STOCK IN TRANSFER'!D:D, A54, 'STOCK IN TRANSFER'!F:F, "ADJUSTMENT (-)") -> 5 | G54: =SUMIFS('STOCK IN TRANSFER'!G:G, 'STOCK IN TRANSFER'!D:D, A54, 'STOCK IN TRANSFER'!F:F, "STOCK IN") + SUMIFS('STOCK IN TRANSFER'!G:G, 'STOCK IN TRANSFER'!D:D, A54, 'STOCK IN TRANSFER'!F:F, "ADJUSTMENT (+)") -> 109
A55: =IFERROR(__xludf.DUMMYFUNCTION("""COMPUTED_VALUE"""),"ROS-SR-183") -> ROS-SR-183 | B55: =IFERROR(__xludf.DUMMYFUNCTION("""COMPUTED_VALUE"""),"SAMAR BEIGE SUN ROOF ROS-SR-183 RAIN OR SHINE 4L") -> SAMAR BEIGE SUN ROOF ROS-SR-183 RAIN OR SHINE 4L | C55: =IFERROR(__xludf.DUMMYFUNCTION("""COMPUTED_VALUE"""),577.6) -> 577.6 | D55: =IFERROR(__xludf.DUMMYFUNCTION("""COMPUTED_VALUE"""),"4L") -> 4L | E55: =IFERROR(__xludf.DUMMYFUNCTION("""COMPUTED_VALUE"""),2.0) -> 2 | F55: =SUMIF(SALES!D:D, A55, SALES!H:H) + SUMIFS('STOCK IN TRANSFER'!G:G, 'STOCK IN TRANSFER'!D:D, A55, 'STOCK IN TRANSFER'!F:F, "TRANSFER") + SUMIFS('STOCK IN TRANSFER'!G:G, 'STOCK IN TRANSFER'!D:D, A55, 'STOCK IN TRANSFER'!F:F, "ADJUSTMENT (-)") -> 0 | G55: =SUMIFS('STOCK IN TRANSFER'!G:G, 'STOCK IN TRANSFER'!D:D, A55, 'STOCK IN TRANSFER'!F:F, "STOCK IN") + SUMIFS('STOCK IN TRANSFER'!G:G, 'STOCK IN TRANSFER'!D:D, A55, 'STOCK IN TRANSFER'!F:F, "ADJUSTMENT (+)") -> 2
A56: =IFERROR(__xludf.DUMMYFUNCTION("""COMPUTED_VALUE"""),"RUGBY") -> RUGBY | B56: =IFERROR(__xludf.DUMMYFUNCTION("""COMPUTED_VALUE"""),"RUGBY") -> RUGBY | C56: =IFERROR(__xludf.DUMMYFUNCTION("""COMPUTED_VALUE"""),66.0) -> 66 | D56: =IFERROR(__xludf.DUMMYFUNCTION("""COMPUTED_VALUE"""),"PCS") -> PCS | E56: =IFERROR(__xludf.DUMMYFUNCTION("""COMPUTED_VALUE"""),15.0) -> 15 | F56: =SUMIF(SALES!D:D, A56, SALES!H:H) + SUMIFS('STOCK IN TRANSFER'!G:G, 'STOCK IN TRANSFER'!D:D, A56, 'STOCK IN TRANSFER'!F:F, "TRANSFER") + SUMIFS('STOCK IN TRANSFER'!G:G, 'STOCK IN TRANSFER'!D:D, A56, 'STOCK IN TRANSFER'!F:F, "ADJUSTMENT (-)") -> 3 | G56: =SUMIFS('STOCK IN TRANSFER'!G:G, 'STOCK IN TRANSFER'!D:D, A56, 'STOCK IN TRANSFER'!F:F, "STOCK IN") + SUMIFS('STOCK IN TRANSFER'!G:G, 'STOCK IN TRANSFER'!D:D, A56, 'STOCK IN TRANSFER'!F:F, "ADJUSTMENT (+)") -> 18
A57: =IFERROR(__xludf.DUMMYFUNCTION("""COMPUTED_VALUE"""),"ROBPNTSTRNR") -> ROBPNTSTRNR | B57: =IFERROR(__xludf.DUMMYFUNCTION("""COMPUTED_VALUE"""),"ROBFILTER PAINT STRAINER 125M") -> ROBFILTER PAINT STRAINER 125M | C57: =IFERROR(__xludf.DUMMYFUNCTION("""COMPUTED_VALUE"""),11.0) -> 11 | D57: =IFERROR(__xludf.DUMMYFUNCTION("""COMPUTED_VALUE"""),"PC/S") -> PC/S | E57: =IFERROR(__xludf.DUMMYFUNCTION("""COMPUTED_VALUE"""),8.0) -> 8 | F57: =SUMIF(SALES!D:D, A57, SALES!H:H) + SUMIFS('STOCK IN TRANSFER'!G:G, 'STOCK IN TRANSFER'!D:D, A57, 'STOCK IN TRANSFER'!F:F, "TRANSFER") + SUMIFS('STOCK IN TRANSFER'!G:G, 'STOCK IN TRANSFER'!D:D, A57, 'STOCK IN TRANSFER'!F:F, "ADJUSTMENT (-)") -> 7 | G57: =SUMIFS('STOCK IN TRANSFER'!G:G, 'STOCK IN TRANSFER'!D:D, A57, 'STOCK IN TRANSFER'!F:F, "STOCK IN") + SUMIFS('STOCK IN TRANSFER'!G:G, 'STOCK IN TRANSFER'!D:D, A57, 'STOCK IN TRANSFER'!F:F, "ADJUSTMENT (+)") -> 15
A58: =IFERROR(__xludf.DUMMYFUNCTION("""COMPUTED_VALUE"""),"ROBTCKCLTH") -> ROBTCKCLTH | B58: =IFERROR(__xludf.DUMMYFUNCTION("""COMPUTED_VALUE"""),"ROBERLO TACK CLOTH") -> ROBERLO TACK CLOTH | C58: =IFERROR(__xludf.DUMMYFUNCTION("""COMPUTED_VALUE"""),40.0) -> 40 | D58: =IFERROR(__xludf.DUMMYFUNCTION("""COMPUTED_VALUE"""),"PCS") -> PCS | E58: =IFERROR(__xludf.DUMMYFUNCTION("""COMPUTED_VALUE"""),0.0) -> 0 | F58: =SUMIF(SALES!D:D, A58, SALES!H:H) + SUMIFS('STOCK IN TRANSFER'!G:G, 'STOCK IN TRANSFER'!D:D, A58, 'STOCK IN TRANSFER'!F:F, "TRANSFER") + SUMIFS('STOCK IN TRANSFER'!G:G, 'STOCK IN TRANSFER'!D:D, A58, 'STOCK IN TRANSFER'!F:F, "ADJUSTMENT (-)") -> 0 | G58: =SUMIFS('STOCK IN TRANSFER'!G:G, 'STOCK IN TRANSFER'!D:D, A58, 'STOCK IN TRANSFER'!F:F, "STOCK IN") + SUMIFS('STOCK IN TRANSFER'!G:G, 'STOCK IN TRANSFER'!D:D, A58, 'STOCK IN TRANSFER'!F:F, "ADJUSTMENT (+)") -> 0
A59: =IFERROR(__xludf.DUMMYFUNCTION("""COMPUTED_VALUE"""),"ROBRC-1KG") -> ROBRC-1KG | B59: =IFERROR(__xludf.DUMMYFUNCTION("""COMPUTED_VALUE"""),"ROBERLO RUBBING COMPOUND 1KG") -> ROBERLO RUBBING COMPOUND 1KG | C59: =IFERROR(__xludf.DUMMYFUNCTION("""COMPUTED_VALUE"""),780.0) -> 780 | D59: =IFERROR(__xludf.DUMMYFUNCTION("""COMPUTED_VALUE"""),"KG") -> KG | E59: =IFERROR(__xludf.DUMMYFUNCTION("""COMPUTED_VALUE"""),3.5) -> 3.5 | F59: =SUMIF(SALES!D:D, A59, SALES!H:H) + SUMIFS('STOCK IN TRANSFER'!G:G, 'STOCK IN TRANSFER'!D:D, A59, 'STOCK IN TRANSFER'!F:F, "TRANSFER") + SUMIFS('STOCK IN TRANSFER'!G:G, 'STOCK IN TRANSFER'!D:D, A59, 'STOCK IN TRANSFER'!F:F, "ADJUSTMENT (-)") -> 9.25 | G59: =SUMIFS('STOCK IN TRANSFER'!G:G, 'STOCK IN TRANSFER'!D:D, A59, 'STOCK IN TRANSFER'!F:F, "STOCK IN") + SUMIFS('STOCK IN TRANSFER'!G:G, 'STOCK IN TRANSFER'!D:D, A59, 'STOCK IN TRANSFER'!F:F, "ADJUSTMENT (+)") -> 12.75
A60: =IFERROR(__xludf.DUMMYFUNCTION("""COMPUTED_VALUE"""),"B-1750") -> B-1750 | B60: =IFERROR(__xludf.DUMMYFUNCTION("""COMPUTED_VALUE"""),"REDUCER ACRYTEX B-1750 BOYSEN 4L") -> REDUCER ACRYTEX B-1750 BOYSEN 4L | C60: =IFERROR(__xludf.DUMMYFUNCTION("""COMPUTED_VALUE"""),479.0) -> 479 | D60: =IFERROR(__xludf.DUMMYFUNCTION("""COMPUTED_VALUE"""),"4L") -> 4L | E60: =IFERROR(__xludf.DUMMYFUNCTION("""COMPUTED_VALUE"""),0.0) -> 0 | F60: =SUMIF(SALES!D:D, A60, SALES!H:H) + SUMIFS('STOCK IN TRANSFER'!G:G, 'STOCK IN TRANSFER'!D:D, A60, 'STOCK IN TRANSFER'!F:F, "TRANSFER") + SUMIFS('STOCK IN TRANSFER'!G:G, 'STOCK IN TRANSFER'!D:D, A60, 'STOCK IN TRANSFER'!F:F, "ADJUSTMENT (-)") -> 3 | G60: =SUMIFS('STOCK IN TRANSFER'!G:G, 'STOCK IN TRANSFER'!D:D, A60, 'STOCK IN TRANSFER'!F:F, "STOCK IN") + SUMIFS('STOCK IN TRANSFER'!G:G, 'STOCK IN TRANSFER'!D:D, A60, 'STOCK IN TRANSFER'!F:F, "ADJUSTMENT (+)") -> 3
A61: =IFERROR(__xludf.DUMMYFUNCTION("""COMPUTED_VALUE"""),"PWTCO-4333") -> PWTCO-4333 | B61: =IFERROR(__xludf.DUMMYFUNCTION("""COMPUTED_VALUE"""),"RAW UMBER TINTING COLOR PWTCO-4333 1/4L PREMIUM WELCOAT") -> RAW UMBER TINTING COLOR PWTCO-4333 1/4L PREMIUM WELCOAT | C61: =IFERROR(__xludf.DUMMYFUNCTION("""COMPUTED_VALUE"""),72.0195) -> 72.0195 | D61: =IFERROR(__xludf.DUMMYFUNCTION("""COMPUTED_VALUE"""),"1/4L") -> 1/4L | E61: =IFERROR(__xludf.DUMMYFUNCTION("""COMPUTED_VALUE"""),1.0) -> 1 | F61: =SUMIF(SALES!D:D, A61, SALES!H:H) + SUMIFS('STOCK IN TRANSFER'!G:G, 'STOCK IN TRANSFER'!D:D, A61, 'STOCK IN TRANSFER'!F:F, "TRANSFER") + SUMIFS('STOCK IN TRANSFER'!G:G, 'STOCK IN TRANSFER'!D:D, A61, 'STOCK IN TRANSFER'!F:F, "ADJUSTMENT (-)") -> 0 | G61: =SUMIFS('STOCK IN TRANSFER'!G:G, 'STOCK IN TRANSFER'!D:D, A61, 'STOCK IN TRANSFER'!F:F, "STOCK IN") + SUMIFS('STOCK IN TRANSFER'!G:G, 'STOCK IN TRANSFER'!D:D, A61, 'STOCK IN TRANSFER'!F:F, "ADJUSTMENT (+)") -> 1
A62: =IFERROR(__xludf.DUMMYFUNCTION("""COMPUTED_VALUE"""),"PWTAC-4317-1L") -> PWTAC-4317-1L | B62: =IFERROR(__xludf.DUMMYFUNCTION("""COMPUTED_VALUE"""),"RAW UMBER ACRY-COLOR PWTAC-4317 1L WELCOAT PREMIUM") -> RAW UMBER ACRY-COLOR PWTAC-4317 1L WELCOAT PREMIUM | C62: =IFERROR(__xludf.DUMMYFUNCTION("""COMPUTED_VALUE"""),104.6) -> 104.6 | D62: =IFERROR(__xludf.DUMMYFUNCTION("""COMPUTED_VALUE"""),"1L") -> 1L | E62: =IFERROR(__xludf.DUMMYFUNCTION("""COMPUTED_VALUE"""),6.0) -> 6 | F62: =SUMIF(SALES!D:D, A62, SALES!H:H) + SUMIFS('STOCK IN TRANSFER'!G:G, 'STOCK IN TRANSFER'!D:D, A62, 'STOCK IN TRANSFER'!F:F, "TRANSFER") + SUMIFS('STOCK IN TRANSFER'!G:G, 'STOCK IN TRANSFER'!D:D, A62, 'STOCK IN TRANSFER'!F:F, "ADJUSTMENT (-)") -> 0 | G62: =SUMIFS('STOCK IN TRANSFER'!G:G, 'STOCK IN TRANSFER'!D:D, A62, 'STOCK IN TRANSFER'!F:F, "STOCK IN") + SUMIFS('STOCK IN TRANSFER'!G:G, 'STOCK IN TRANSFER'!D:D, A62, 'STOCK IN TRANSFER'!F:F, "ADJUSTMENT (+)") -> 6
A63: =IFERROR(__xludf.DUMMYFUNCTION("""COMPUTED_VALUE"""),"AC-90-1L") -> AC-90-1L | B63: =IFERROR(__xludf.DUMMYFUNCTION("""COMPUTED_VALUE"""),"RAW SIENNA ACRY-COLOR AC-90 1L DAVIES") -> RAW SIENNA ACRY-COLOR AC-90 1L DAVIES | C63: =IFERROR(__xludf.DUMMYFUNCTION("""COMPUTED_VALUE"""),115.0) -> 115 | D63: =IFERROR(__xludf.DUMMYFUNCTION("""COMPUTED_VALUE"""),"1L") -> 1L | E63: =IFERROR(__xludf.DUMMYFUNCTION("""COMPUTED_VALUE"""),2.0) -> 2 | F63: =SUMIF(SALES!D:D, A63, SALES!H:H) + SUMIFS('STOCK IN TRANSFER'!G:G, 'STOCK IN TRANSFER'!D:D, A63, 'STOCK IN TRANSFER'!F:F, "TRANSFER") + SUMIFS('STOCK IN TRANSFER'!G:G, 'STOCK IN TRANSFER'!D:D, A63, 'STOCK IN TRANSFER'!F:F, "ADJUSTMENT (-)") -> 2 | G63: =SUMIFS('STOCK IN TRANSFER'!G:G, 'STOCK IN TRANSFER'!D:D, A63, 'STOCK IN TRANSFER'!F:F, "STOCK IN") + SUMIFS('STOCK IN TRANSFER'!G:G, 'STOCK IN TRANSFER'!D:D, A63, 'STOCK IN TRANSFER'!F:F, "ADJUSTMENT (+)") -> 4
A64: =IFERROR(__xludf.DUMMYFUNCTION("""COMPUTED_VALUE"""),"ROS-1000") -> ROS-1000 | B64: =IFERROR(__xludf.DUMMYFUNCTION("""COMPUTED_VALUE"""),"RAIN OR SHINE XTRA GLOSS 4L") -> RAIN OR SHINE XTRA GLOSS 4L | C64: =IFERROR(__xludf.DUMMYFUNCTION("""COMPUTED_VALUE"""),656.0) -> 656 | D64: =IFERROR(__xludf.DUMMYFUNCTION("""COMPUTED_VALUE"""),"GALON") -> GALON | E64: =IFERROR(__xludf.DUMMYFUNCTION("""COMPUTED_VALUE"""),0.0) -> 0 | F64: =SUMIF(SALES!D:D, A64, SALES!H:H) + SUMIFS('STOCK IN TRANSFER'!G:G, 'STOCK IN TRANSFER'!D:D, A64, 'STOCK IN TRANSFER'!F:F, "TRANSFER") + SUMIFS('STOCK IN TRANSFER'!G:G, 'STOCK IN TRANSFER'!D:D, A64, 'STOCK IN TRANSFER'!F:F, "ADJUSTMENT (-)") -> 0 | G64: =SUMIFS('STOCK IN TRANSFER'!G:G, 'STOCK IN TRANSFER'!D:D, A64, 'STOCK IN TRANSFER'!F:F, "STOCK IN") + SUMIFS('STOCK IN TRANSFER'!G:G, 'STOCK IN TRANSFER'!D:D, A64, 'STOCK IN TRANSFER'!F:F, "ADJUSTMENT (+)") -> 0
A65: =IFERROR(__xludf.DUMMYFUNCTION("""COMPUTED_VALUE"""),"ROS-109") -> ROS-109 | B65: =IFERROR(__xludf.DUMMYFUNCTION("""COMPUTED_VALUE"""),"RAIN OR SHINE TULLE WHITE") -> RAIN OR SHINE TULLE WHITE | C65: =IFERROR(__xludf.DUMMYFUNCTION("""COMPUTED_VALUE"""),665.0) -> 665 | D65: =IFERROR(__xludf.DUMMYFUNCTION("""COMPUTED_VALUE"""),"GALON") -> GALON | E65: =IFERROR(__xludf.DUMMYFUNCTION("""COMPUTED_VALUE"""),0.0) -> 0 | F65: =SUMIF(SALES!D:D, A65, SALES!H:H) + SUMIFS('STOCK IN TRANSFER'!G:G, 'STOCK IN TRANSFER'!D:D, A65, 'STOCK IN TRANSFER'!F:F, "TRANSFER") + SUMIFS('STOCK IN TRANSFER'!G:G, 'STOCK IN TRANSFER'!D:D, A65, 'STOCK IN TRANSFER'!F:F, "ADJUSTMENT (-)") -> 1 | G65: =SUMIFS('STOCK IN TRANSFER'!G:G, 'STOCK IN TRANSFER'!D:D, A65, 'STOCK IN TRANSFER'!F:F, "STOCK IN") + SUMIFS('STOCK IN TRANSFER'!G:G, 'STOCK IN TRANSFER'!D:D, A65, 'STOCK IN TRANSFER'!F:F, "ADJUSTMENT (+)") -> 1
A66: =IFERROR(__xludf.DUMMYFUNCTION("""COMPUTED_VALUE"""),"ROS-171") -> ROS-171 | B66: =IFERROR(__xludf.DUMMYFUNCTION("""COMPUTED_VALUE"""),"RAIN OR SHINE TOUCH OF GRAY") -> RAIN OR SHINE TOUCH OF GRAY | C66: =IFERROR(__xludf.DUMMYFUNCTION("""COMPUTED_VALUE"""),0.0) -> 0 | D66: =IFERROR(__xludf.DUMMYFUNCTION("""COMPUTED_VALUE"""),"GALON") -> GALON | E66: =IFERROR(__xludf.DUMMYFUNCTION("""COMPUTED_VALUE"""),0.0) -> 0 | F66: =SUMIF(SALES!D:D, A66, SALES!H:H) + SUMIFS('STOCK IN TRANSFER'!G:G, 'STOCK IN TRANSFER'!D:D, A66, 'STOCK IN TRANSFER'!F:F, "TRANSFER") + SUMIFS('STOCK IN TRANSFER'!G:G, 'STOCK IN TRANSFER'!D:D, A66, 'STOCK IN TRANSFER'!F:F, "ADJUSTMENT (-)") -> 0 | G66: =SUMIFS('STOCK IN TRANSFER'!G:G, 'STOCK IN TRANSFER'!D:D, A66, 'STOCK IN TRANSFER'!F:F, "STOCK IN") + SUMIFS('STOCK IN TRANSFER'!G:G, 'STOCK IN TRANSFER'!D:D, A66, 'STOCK IN TRANSFER'!F:F, "ADJUSTMENT (+)") -> 0
A67: =IFERROR(__xludf.DUMMYFUNCTION("""COMPUTED_VALUE"""),"ROS-SG-4L") -> ROS-SG-4L | B67: =IFERROR(__xludf.DUMMYFUNCTION("""COMPUTED_VALUE"""),"RAIN OR SHINE STONE GRAY 4L") -> RAIN OR SHINE STONE GRAY 4L | C67: =IFERROR(__xludf.DUMMYFUNCTION("""COMPUTED_VALUE"""),665.0) -> 665 | D67: =IFERROR(__xludf.DUMMYFUNCTION("""COMPUTED_VALUE"""),"GALON") -> GALON | E67: =IFERROR(__xludf.DUMMYFUNCTION("""COMPUTED_VALUE"""),0.0) -> 0 | F67: =SUMIF(SALES!D:D, A67, SALES!H:H) + SUMIFS('STOCK IN TRANSFER'!G:G, 'STOCK IN TRANSFER'!D:D, A67, 'STOCK IN TRANSFER'!F:F, "TRANSFER") + SUMIFS('STOCK IN TRANSFER'!G:G, 'STOCK IN TRANSFER'!D:D, A67, 'STOCK IN TRANSFER'!F:F, "ADJUSTMENT (-)") -> 2 | G67: =SUMIFS('STOCK IN TRANSFER'!G:G, 'STOCK IN TRANSFER'!D:D, A67, 'STOCK IN TRANSFER'!F:F, "STOCK IN") + SUMIFS('STOCK IN TRANSFER'!G:G, 'STOCK IN TRANSFER'!D:D, A67, 'STOCK IN TRANSFER'!F:F, "ADJUSTMENT (+)") -> 2
A68: =IFERROR(__xludf.DUMMYFUNCTION("""COMPUTED_VALUE"""),"ROS-933-4L") -> ROS-933-4L | B68: =IFERROR(__xludf.DUMMYFUNCTION("""COMPUTED_VALUE"""),"RAIN OR SHINE ROS-933 COOL MINT 4L") -> RAIN OR SHINE ROS-933 COOL MINT 4L | C68: =IFERROR(__xludf.DUMMYFUNCTION("""COMPUTED_VALUE"""),665.0) -> 665 | D68: =IFERROR(__xludf.DUMMYFUNCTION("""COMPUTED_VALUE"""),"GALON") -> GALON | E68: =IFERROR(__xludf.DUMMYFUNCTION("""COMPUTED_VALUE"""),0.0) -> 0 | F68: =SUMIF(SALES!D:D, A68, SALES!H:H) + SUMIFS('STOCK IN TRANSFER'!G:G, 'STOCK IN TRANSFER'!D:D, A68, 'STOCK IN TRANSFER'!F:F, "TRANSFER") + SUMIFS('STOCK IN TRANSFER'!G:G, 'STOCK IN TRANSFER'!D:D, A68, 'STOCK IN TRANSFER'!F:F, "ADJUSTMENT (-)") -> 0 | G68: =SUMIFS('STOCK IN TRANSFER'!G:G, 'STOCK IN TRANSFER'!D:D, A68, 'STOCK IN TRANSFER'!F:F, "STOCK IN") + SUMIFS('STOCK IN TRANSFER'!G:G, 'STOCK IN TRANSFER'!D:D, A68, 'STOCK IN TRANSFER'!F:F, "ADJUSTMENT (+)") -> 0
A69: =IFERROR(__xludf.DUMMYFUNCTION("""COMPUTED_VALUE"""),"ROS-629-4L") -> ROS-629-4L | B69: =IFERROR(__xludf.DUMMYFUNCTION("""COMPUTED_VALUE"""),"RAIN OR SHINE ROS-629 TULIPS 4L") -> RAIN OR SHINE ROS-629 TULIPS 4L | C69: =IFERROR(__xludf.DUMMYFUNCTION("""COMPUTED_VALUE"""),665.0) -> 665 | D69: =IFERROR(__xludf.DUMMYFUNCTION("""COMPUTED_VALUE"""),"GALON") -> GALON | E69: =IFERROR(__xludf.DUMMYFUNCTION("""COMPUTED_VALUE"""),0.0) -> 0 | F69: =SUMIF(SALES!D:D, A69, SALES!H:H) + SUMIFS('STOCK IN TRANSFER'!G:G, 'STOCK IN TRANSFER'!D:D, A69, 'STOCK IN TRANSFER'!F:F, "TRANSFER") + SUMIFS('STOCK IN TRANSFER'!G:G, 'STOCK IN TRANSFER'!D:D, A69, 'STOCK IN TRANSFER'!F:F, "ADJUSTMENT (-)") -> 4 | G69: =SUMIFS('STOCK IN TRANSFER'!G:G, 'STOCK IN TRANSFER'!D:D, A69, 'STOCK IN TRANSFER'!F:F, "STOCK IN") + SUMIFS('STOCK IN TRANSFER'!G:G, 'STOCK IN TRANSFER'!D:D, A69, 'STOCK IN TRANSFER'!F:F, "ADJUSTMENT (+)") -> 4
A70: =IFERROR(__xludf.DUMMYFUNCTION("""COMPUTED_VALUE"""),"ROS-7000") -> ROS-7000 | B70: =IFERROR(__xludf.DUMMYFUNCTION("""COMPUTED_VALUE"""),"RAIN OR SHINE PREPA WHITE 4L") -> RAIN OR SHINE PREPA WHITE 4L | C70: =IFERROR(__xludf.DUMMYFUNCTION("""COMPUTED_VALUE"""),546.0) -> 546 | D70: =IFERROR(__xludf.DUMMYFUNCTION("""COMPUTED_VALUE"""),"GALON") -> GALON | E70: =IFERROR(__xludf.DUMMYFUNCTION("""COMPUTED_VALUE"""),0.0) -> 0 | F70: =SUMIF(SALES!D:D, A70, SALES!H:H) + SUMIFS('STOCK IN TRANSFER'!G:G, 'STOCK IN TRANSFER'!D:D, A70, 'STOCK IN TRANSFER'!F:F, "TRANSFER") + SUMIFS('STOCK IN TRANSFER'!G:G, 'STOCK IN TRANSFER'!D:D, A70, 'STOCK IN TRANSFER'!F:F, "ADJUSTMENT (-)") -> 1 | G70: =SUMIFS('STOCK IN TRANSFER'!G:G, 'STOCK IN TRANSFER'!D:D, A70, 'STOCK IN TRANSFER'!F:F, "STOCK IN") + SUMIFS('STOCK IN TRANSFER'!G:G, 'STOCK IN TRANSFER'!D:D, A70, 'STOCK IN TRANSFER'!F:F, "ADJUSTMENT (+)") -> 1
A71: =IFERROR(__xludf.DUMMYFUNCTION("""COMPUTED_VALUE"""),"ROS-OB-4L") -> ROS-OB-4L | B71: =IFERROR(__xludf.DUMMYFUNCTION("""COMPUTED_VALUE"""),"RAIN OR SHINE OCEAN BLUE 4L") -> RAIN OR SHINE OCEAN BLUE 4L | C71: =IFERROR(__xludf.DUMMYFUNCTION("""COMPUTED_VALUE"""),665.0) -> 665 | D71: =IFERROR(__xludf.DUMMYFUNCTION("""COMPUTED_VALUE"""),"GALON") -> GALON | E71: =IFERROR(__xludf.DUMMYFUNCTION("""COMPUTED_VALUE"""),0.0) -> 0 | F71: =SUMIF(SALES!D:D, A71, SALES!H:H) + SUMIFS('STOCK IN TRANSFER'!G:G, 'STOCK IN TRANSFER'!D:D, A71, 'STOCK IN TRANSFER'!F:F, "TRANSFER") + SUMIFS('STOCK IN TRANSFER'!G:G, 'STOCK IN TRANSFER'!D:D, A71, 'STOCK IN TRANSFER'!F:F, "ADJUSTMENT (-)") -> 0 | G71: =SUMIFS('STOCK IN TRANSFER'!G:G, 'STOCK IN TRANSFER'!D:D, A71, 'STOCK IN TRANSFER'!F:F, "STOCK IN") + SUMIFS('STOCK IN TRANSFER'!G:G, 'STOCK IN TRANSFER'!D:D, A71, 'STOCK IN TRANSFER'!F:F, "ADJUSTMENT (+)") -> 0
A72: =IFERROR(__xludf.DUMMYFUNCTION("""COMPUTED_VALUE"""),"ROS-223") -> ROS-223 | B72: =IFERROR(__xludf.DUMMYFUNCTION("""COMPUTED_VALUE"""),"RAIN OR SHINE NICOLE PINK 4L") -> RAIN OR SHINE NICOLE PINK 4L | C72: =IFERROR(__xludf.DUMMYFUNCTION("""COMPUTED_VALUE"""),0.0) -> 0 | D72: =IFERROR(__xludf.DUMMYFUNCTION("""COMPUTED_VALUE"""),"GALON") -> GALON | E72: =IFERROR(__xludf.DUMMYFUNCTION("""COMPUTED_VALUE"""),0.0) -> 0 | F72: =SUMIF(SALES!D:D, A72, SALES!H:H) + SUMIFS('STOCK IN TRANSFER'!G:G, 'STOCK IN TRANSFER'!D:D, A72, 'STOCK IN TRANSFER'!F:F, "TRANSFER") + SUMIFS('STOCK IN TRANSFER'!G:G, 'STOCK IN TRANSFER'!D:D, A72, 'STOCK IN TRANSFER'!F:F, "ADJUSTMENT (-)") -> 1 | G72: =SUMIFS('STOCK IN TRANSFER'!G:G, 'STOCK IN TRANSFER'!D:D, A72, 'STOCK IN TRANSFER'!F:F, "STOCK IN") + SUMIFS('STOCK IN TRANSFER'!G:G, 'STOCK IN TRANSFER'!D:D, A72, 'STOCK IN TRANSFER'!F:F, "ADJUSTMENT (+)") -> 1
A73: =IFERROR(__xludf.DUMMYFUNCTION("""COMPUTED_VALUE"""),"ROS-368") -> ROS-368 | B73: =IFERROR(__xludf.DUMMYFUNCTION("""COMPUTED_VALUE"""),"RAIN OR SHINE MY WAY 4L") -> RAIN OR SHINE MY WAY 4L | C73: =IFERROR(__xludf.DUMMYFUNCTION("""COMPUTED_VALUE"""),727.0) -> 727 | D73: =IFERROR(__xludf.DUMMYFUNCTION("""COMPUTED_VALUE"""),"GALON") -> GALON | E73: =IFERROR(__xludf.DUMMYFUNCTION("""COMPUTED_VALUE"""),0.0) -> 0 | F73: =SUMIF(SALES!D:D, A73, SALES!H:H) + SUMIFS('STOCK IN TRANSFER'!G:G, 'STOCK IN TRANSFER'!D:D, A73, 'STOCK IN TRANSFER'!F:F, "TRANSFER") + SUMIFS('STOCK IN TRANSFER'!G:G, 'STOCK IN TRANSFER'!D:D, A73, 'STOCK IN TRANSFER'!F:F, "ADJUSTMENT (-)") -> 0 | G73: =SUMIFS('STOCK IN TRANSFER'!G:G, 'STOCK IN TRANSFER'!D:D, A73, 'STOCK IN TRANSFER'!F:F, "STOCK IN") + SUMIFS('STOCK IN TRANSFER'!G:G, 'STOCK IN TRANSFER'!D:D, A73, 'STOCK IN TRANSFER'!F:F, "ADJUSTMENT (+)") -> 0
A74: =IFERROR(__xludf.DUMMYFUNCTION("""COMPUTED_VALUE"""),"ROSGRN-4L") -> ROSGRN-4L | B74: =IFERROR(__xludf.DUMMYFUNCTION("""COMPUTED_VALUE"""),"RAIN OR SHINE MIX GREEN 4L") -> RAIN OR SHINE MIX GREEN 4L | C74: =IFERROR(__xludf.DUMMYFUNCTION("""COMPUTED_VALUE"""),0.0) -> 0 | D74: =IFERROR(__xludf.DUMMYFUNCTION("""COMPUTED_VALUE"""),"GALON") -> GALON | E74: =IFERROR(__xludf.DUMMYFUNCTION("""COMPUTED_VALUE"""),0.0) -> 0 | F74: =SUMIF(SALES!D:D, A74, SALES!H:H) + SUMIFS('STOCK IN TRANSFER'!G:G, 'STOCK IN TRANSFER'!D:D, A74, 'STOCK IN TRANSFER'!F:F, "TRANSFER") + SUMIFS('STOCK IN TRANSFER'!G:G, 'STOCK IN TRANSFER'!D:D, A74, 'STOCK IN TRANSFER'!F:F, "ADJUSTMENT (-)") -> 0 | G74: =SUMIFS('STOCK IN TRANSFER'!G:G, 'STOCK IN TRANSFER'!D:D, A74, 'STOCK IN TRANSFER'!F:F, "STOCK IN") + SUMIFS('STOCK IN TRANSFER'!G:G, 'STOCK IN TRANSFER'!D:D, A74, 'STOCK IN TRANSFER'!F:F, "ADJUSTMENT (+)") -> 0
A75: =IFERROR(__xludf.DUMMYFUNCTION("""COMPUTED_VALUE"""),"ROSG-4L") -> ROSG-4L | B75: =IFERROR(__xludf.DUMMYFUNCTION("""COMPUTED_VALUE"""),"RAIN OR SHINE MIX GARY 4L") -> RAIN OR SHINE MIX GARY 4L | C75: =IFERROR(__xludf.DUMMYFUNCTION("""COMPUTED_VALUE"""),950.0) -> 950 | D75: =IFERROR(__xludf.DUMMYFUNCTION("""COMPUTED_VALUE"""),"GALON") -> GALON | E75: =IFERROR(__xludf.DUMMYFUNCTION("""COMPUTED_VALUE"""),0.0) -> 0 | F75: =SUMIF(SALES!D:D, A75, SALES!H:H) + SUMIFS('STOCK IN TRANSFER'!G:G, 'STOCK IN TRANSFER'!D:D, A75, 'STOCK IN TRANSFER'!F:F, "TRANSFER") + SUMIFS('STOCK IN TRANSFER'!G:G, 'STOCK IN TRANSFER'!D:D, A75, 'STOCK IN TRANSFER'!F:F, "ADJUSTMENT (-)") -> 0 | G75: =SUMIFS('STOCK IN TRANSFER'!G:G, 'STOCK IN TRANSFER'!D:D, A75, 'STOCK IN TRANSFER'!F:F, "STOCK IN") + SUMIFS('STOCK IN TRANSFER'!G:G, 'STOCK IN TRANSFER'!D:D, A75, 'STOCK IN TRANSFER'!F:F, "ADJUSTMENT (+)") -> 0
A76: =IFERROR(__xludf.DUMMYFUNCTION("""COMPUTED_VALUE"""),"ROS-888") -> ROS-888 | B76: =IFERROR(__xludf.DUMMYFUNCTION("""COMPUTED_VALUE"""),"RAIN OR SHINE LUCKY ORANGE 4L") -> RAIN OR SHINE LUCKY ORANGE 4L | C76: =IFERROR(__xludf.DUMMYFUNCTION("""COMPUTED_VALUE"""),1391.0) -> 1391 | D76: =IFERROR(__xludf.DUMMYFUNCTION("""COMPUTED_VALUE"""),"GALON") -> GALON | E76: =IFERROR(__xludf.DUMMYFUNCTION("""COMPUTED_VALUE"""),0.0) -> 0 | F76: =SUMIF(SALES!D:D, A76, SALES!H:H) + SUMIFS('STOCK IN TRANSFER'!G:G, 'STOCK IN TRANSFER'!D:D, A76, 'STOCK IN TRANSFER'!F:F, "TRANSFER") + SUMIFS('STOCK IN TRANSFER'!G:G, 'STOCK IN TRANSFER'!D:D, A76, 'STOCK IN TRANSFER'!F:F, "ADJUSTMENT (-)") -> 0 | G76: =SUMIFS('STOCK IN TRANSFER'!G:G, 'STOCK IN TRANSFER'!D:D, A76, 'STOCK IN TRANSFER'!F:F, "STOCK IN") + SUMIFS('STOCK IN TRANSFER'!G:G, 'STOCK IN TRANSFER'!D:D, A76, 'STOCK IN TRANSFER'!F:F, "ADJUSTMENT (+)") -> 0
A77: =IFERROR(__xludf.DUMMYFUNCTION("""COMPUTED_VALUE"""),"ROS-862") -> ROS-862 | B77: =IFERROR(__xludf.DUMMYFUNCTION("""COMPUTED_VALUE"""),"RAIN OR SHINE IVORY 4L") -> RAIN OR SHINE IVORY 4L | C77: =IFERROR(__xludf.DUMMYFUNCTION("""COMPUTED_VALUE"""),655.0) -> 655 | D77: =IFERROR(__xludf.DUMMYFUNCTION("""COMPUTED_VALUE"""),"GALON") -> GALON | E77: =IFERROR(__xludf.DUMMYFUNCTION("""COMPUTED_VALUE"""),1.0) -> 1 | F77: =SUMIF(SALES!D:D, A77, SALES!H:H) + SUMIFS('STOCK IN TRANSFER'!G:G, 'STOCK IN TRANSFER'!D:D, A77, 'STOCK IN TRANSFER'!F:F, "TRANSFER") + SUMIFS('STOCK IN TRANSFER'!G:G, 'STOCK IN TRANSFER'!D:D, A77, 'STOCK IN TRANSFER'!F:F, "ADJUSTMENT (-)") -> 1 | G77: =SUMIFS('STOCK IN TRANSFER'!G:G, 'STOCK IN TRANSFER'!D:D, A77, 'STOCK IN TRANSFER'!F:F, "STOCK IN") + SUMIFS('STOCK IN TRANSFER'!G:G, 'STOCK IN TRANSFER'!D:D, A77, 'STOCK IN TRANSFER'!F:F, "ADJUSTMENT (+)") -> 2
A78: =IFERROR(__xludf.DUMMYFUNCTION("""COMPUTED_VALUE"""),"ROSGRAY-4L") -> ROSGRAY-4L | B78: =IFERROR(__xludf.DUMMYFUNCTION("""COMPUTED_VALUE"""),"RAIN OR SHINE GRAY LATEX 4L") -> RAIN OR SHINE GRAY LATEX 4L | C78: =IFERROR(__xludf.DUMMYFUNCTION("""COMPUTED_VALUE"""),800.0) -> 800 | D78: =IFERROR(__xludf.DUMMYFUNCTION("""COMPUTED_VALUE"""),"GALON") -> GALON | E78: =IFERROR(__xludf.DUMMYFUNCTION("""COMPUTED_VALUE"""),0.0) -> 0 | F78: =SUMIF(SALES!D:D, A78, SALES!H:H) + SUMIFS('STOCK IN TRANSFER'!G:G, 'STOCK IN TRANSFER'!D:D, A78, 'STOCK IN TRANSFER'!F:F, "TRANSFER") + SUMIFS('STOCK IN TRANSFER'!G:G, 'STOCK IN TRANSFER'!D:D, A78, 'STOCK IN TRANSFER'!F:F, "ADJUSTMENT (-)") -> 0 | G78: =SUMIFS('STOCK IN TRANSFER'!G:G, 'STOCK IN TRANSFER'!D:D, A78, 'STOCK IN TRANSFER'!F:F, "STOCK IN") + SUMIFS('STOCK IN TRANSFER'!G:G, 'STOCK IN TRANSFER'!D:D, A78, 'STOCK IN TRANSFER'!F:F, "ADJUSTMENT (+)") -> 0
